Workbook
Name Actual_Expenses: '[1]Budget Overview'!$G$8
Name Actual_Income: '[1]Budget Overview'!$D$11
Name ActualNumberOfPayments: IFERROR(IF(LoanIsGood,IF(PaymentsPerYear=1,1,MATCH(0.01,End_Bal,-1)+1)),"")
Name Annual_Dividend: OFFSET(#REF!,0,0,IF(#REF!>100,100,#REF!))
Name AO: '[2]Repayment Schedule'!$F$7
Name ARMF_120: OFFSET([3]ARMF!$J$1,[3]ARMF!$Z$1+1,0,[3]ARMF!$AB$1,1)
Name ARMF_120_2: OFFSET([3]ARMF!$J$1,[3]ARMF!$AF$1+1,0,[3]ARMF!$AH$1,1)
Name ARMF_20: OFFSET([3]ARMF!$H$1,[3]ARMF!$Z$1+1,0,[3]ARMF!$AB$1,1)
Name ARMF_20_2: OFFSET([3]ARMF!$H$1,[3]ARMF!$AF$1+1,0,[3]ARMF!$AH$1,1)
Name ARMF_50: OFFSET([3]ARMF!$I$1,[3]ARMF!$Z$1+1,0,[3]ARMF!$AB$1,1)
Name ARMF_50_2: OFFSET([3]ARMF!$I$1,[3]ARMF!$AF$1+1,0,[3]ARMF!$AH$1,1)
Name ARMF_D_2: OFFSET([3]ARMF!$A$1,[3]ARMF!$AF$1+1,0,[3]ARMF!$AH$1,1)
Name ARMF_DATE: OFFSET([3]ARMF!$A$1,[3]ARMF!$Z$1+1,0,[3]ARMF!$AB$1,1)
Name ARMF_P_2: OFFSET([3]ARMF!$B$1,[3]ARMF!$AF$1+1,0,[3]ARMF!$AH$1,1)
Name ARMF_PRICE: OFFSET([3]ARMF!$B$1,[3]ARMF!$Z$1+1,0,[3]ARMF!$AB$1,1)
Name Categories: [4]!TblDV4[Category]
Name ColumnTitle1: [2]!PaymentSchedule[[#Headers],[PMT NO]]
Name current_date: DATE(2023,11,11)
Name End_Bal: [2]!PaymentSchedule[ENDING BALANCE]
Name Expenses_header_row: ROW([4]!Expense[[#Headers],[Expense]])
Name Expenses_max_row: MAX(ROW([4]!Expense[#Data]))
Name Expenses_min_row: MIN(ROW([4]!Expense[#Data]))
Name Expenses_total_row: ROW('[4]Budget Planning'!$C$36)
Name ExtraPayments: '[2]Excel Amortization Schedule'!$E$14
Name income_header_row: ROW([4]!Income[[#Headers],[Income]])
Name income_max_row: MAX(ROW([4]!Income[#Data]))
Name Income_min_row: MIN(ROW([4]!Income[#Data]))
Name income_total_row: ROW('[4]Budget Planning'!$C$20)
Name InterestRate: '[2]Excel Amortization Schedule'!$E$9
Name is_empty: '[4]Budget Dashboard'!$H1
Name LastCol: MATCH(REPT("z",255),'[2]Excel Amortization Schedule'!$16:$16)
Name LastRow: MATCH(9.99E+307,'[2]Excel Amortization Schedule'!$B:$B)
Name List_Categories: [5]!Category_List_Table[To add a category, type below]
Name loan: '[2]Repayment Schedule'!$B$8
Name LoanAmount: '[2]Excel Amortization Schedule'!$E$8
Name LoanIsGood: ('[2]Excel Amortization Schedule'!$E$8*'[2]Excel Amortization Schedule'!$E$9*'[2]Excel Amortization Schedule'!$E$10*'[2]Excel Amortization Schedule'!$E$12)>0
Name LoanPeriod: '[2]Excel Amortization Schedule'!$E$10
Name LoanStartDate: '[2]Excel Amortization Schedule'!$E$12
Name Name1: '[6]Week 1'!$B$6
Name Name2: '[6]Week 1'!$B$13
Name Name3: '[6]Week 1'!$B$20
Name Name4: '[6]Week 1'!$B$27
Name New_Balance: OFFSET(#REF!,0,0,IF(#REF!>100,100,#REF!))
Name P_Annual_Dividend: OFFSET([7]Portfolio!$D$32,0,0,IF([7]Portfolio!$D$13>100,100,[7]Portfolio!$D$13))
Name P_New_Balance: OFFSET(#REF!,0,0,IF(#REF!>100,100,#REF!))
Name P_Principal: OFFSET([7]Portfolio!$C$32,0,0,IF([7]Portfolio!$D$13>100,100,[7]Portfolio!$D$13))
Name P_Year: OFFSET([7]Portfolio!$B$32,0,0,IF([7]Portfolio!$D$13>100,100,[7]Portfolio!$D$13))
Name P_Yield_On_Cost: OFFSET([7]Portfolio!$F$32,0,0,IF([7]Portfolio!$D$13>100,100,[7]Portfolio!$D$13))
Name PAFA_120: OFFSET([3]PAFA!$J$1,[3]PAFA!$Z$1+1,0,[3]PAFA!$AB$1,1)
Name PAFA_120_2: OFFSET([3]PAFA!$J$1,[3]PAFA!$AF$1+1,0,[3]PAFA!$AH$1,1)
Name PAFA_20: OFFSET([3]PAFA!$H$1,[3]PAFA!$Z$1+1,0,[3]PAFA!$AB$1,1)
Name PAFA_20_2: OFFSET([3]PAFA!$H$1,[3]PAFA!$AF$1+1,0,[3]PAFA!$AH$1,1)
Name PAFA_50: OFFSET([3]PAFA!$I$1,[3]PAFA!$Z$1+1,0,[3]PAFA!$AB$1,1)
Name PAFA_50_2: OFFSET([3]PAFA!$I$1,[3]PAFA!$AF$1+1,0,[3]PAFA!$AH$1,1)
Name PAFA_D_2: OFFSET([3]PAFA!$A$1,[3]PAFA!$AF$1+1,0,[3]PAFA!$AH$1,1)
Name PAFA_DATE: OFFSET([3]PAFA!$A$1,[3]PAFA!$Z$1+1,0,[3]PAFA!$AB$1,1)
Name PAFA_P_2: OFFSET([3]PAFA!$B$1,[3]PAFA!$AF$1+1,0,[3]PAFA!$AH$1,1)
Name PAFA_PRICE: OFFSET([3]PAFA!$B$1,[3]PAFA!$Z$1+1,0,[3]PAFA!$AB$1,1)
Name PAMA_120: OFFSET([3]PAMA!$J$1,[3]PAMA!$Z$1+1,0,[3]PAMA!$AB$1,1)
Name PAMA_120_2: OFFSET([3]PAMA!$J$1,[3]PAMA!$AF$1+1,0,[3]PAMA!$AH$1,1)

Sheet Retirement Dashboard
B1: It's time to plan for your retirement. | H1: Singaporean CPF Allocation Rates (From 2025 Jan 1) Salary above $750/Month | Q1: Retirement Sum (Est FRS Increase 3% to 3.5% pa) | V1: Estimated Pay Out (Est increase 3% to 3.5%pa)
B2: Before we begin, let’s understand how ready you are for retirement. | H2: Age Band | I2: Total CPF | J2: OA | K2: SA | L2: MA | M2: Total | N2: Employer | O2: Employee | Q2: Age | R2: Year | S2: BRS | T2: FRS | U2: ERS | V2: BRS | W2: FRS | X2: ERS
B3: 2025 | H3: 35 & Below | I3: =SUM(J3:L3) -> 0.37 | J3: =62.17%*M3 -> 0.230029 | K3: =16.21%*M3 -> 0.059977 | L3: =21.62%*M3 -> 0.079994 | M3: =N3+O3 -> 0.37 | N3: 0.17 | O3: 0.2 | Q3: =C9 -> 27 | R3: =B3 -> 2025 | S3: 106500 | T3: 213000 | U3: 426000 | V3: 840 | W3: 1590 | X3: 3330
H4: Above 35-45 | I4: =SUM(J4:L4) -> 0.37 | J4: =56.77%*M4 -> 0.210049 | K4: =18.91%*M4 -> 0.069967 | L4: =24.32%*M4 -> 0.089984 | M4: =N4+O4 -> 0.37 | N4: 0.17 | O4: 0.2 | Q4: =Q3+1 -> 28 | R4: =R3+1 -> 2026 | S4: 110200 | T4: 220440 | U4: 440800 | V4: 850 | W4: 1600 | X4: =X3*103.31% -> 3440.223
B5: VIP Information | H5: Above 45-50 | I5: =SUM(J5:L5) -> 0.37 | J5: =51.36%*M5 -> 0.190032 | K5: =21.62%*M5 -> 0.079994 | L5: =27.02%*M5 -> 0.099974 | M5: =N5+O5 -> 0.37 | N5: 0.17 | O5: 0.2 | Q5: =Q4+1 -> 29 | R5: =R4+1 -> 2027 | S5: 114100 | T5: 228200 | U5: 456400 | V5: 900 | W5: 1670 | X5: 3550
B6: Your Name | C6: Siti | D6: Desired Retirement Age | E6: 65 | H6: Above 50-55 | I6: =SUM(J6:L6) -> 0.37 | J6: =40.55%*M6 -> 0.150035 | K6: =31.08%*M6 -> 0.114996 | L6: =28.37%*M6 -> 0.104969 | M6: =N6+O6 -> 0.37 | N6: 0.17 | O6: 0.2 | Q6: =Q5+1 -> 30 | R6: =R5+1 -> 2028 | S6: =(S5*103.47%) -> 118059.27 | T6: =T5*103.5% -> 236187 | U6: =U5*103.5% -> 472374 | V6: 930 | W6: 1730 | X6: =X5*103.31% -> 3667.505
B7: Gender | C7: Female | D7: Choice of CPFL | E7: FRS | H7: Above 55-60 | I7: =SUM(J7:L7) -> 0.299494 | J7: =30.872%*M7 -> 0.100334 | K7: =27.41%*M7 -> 0.0890825 | L7: =33.87%*M7 -> 0.1100775 | M7: =N7+O7 -> 0.325 | N7: =32.5%-17% -> 0.155 | O7: 0.17 | Q7: =Q6+1 -> 31 | R7: =R6+1 -> 2029 | S7: =(S6*103.5%) -> 122191.34 | T7: =T6*103.5% -> 244453.54 | U7: =U6*103.5% -> 488907.09 | V7: 950 | W7: 1780 | X7: =X6*103.31% -> 3788.8994
B8: Your Birthday | C8: 36331 | H8: Above 60-65 | I8: =SUM(J8:L8) -> 0.234295 | J8: =15.62%*M8 -> 0.036707 | K8: =36.36%*M8 -> 0.085446 | L8: =47.72%*M8 -> 0.112142 | M8: =N8+O8 -> 0.235 | N8: =23.5%-O8 -> 0.12 | O8: 0.115 | Q8: =Q7+1 -> 32 | R8: =R7+1 -> 2030 | S8: =(S7*103.5%) -> 126468.04 | T8: =T7*103.5% -> 253009.42 | U8: =U7*103.5% -> 506018.84 | V8: 980 | W8: 1840 | X8: =X7*103.31% -> 3914.312
B9: Your Age Current | C9: =ROUND((TODAY()-C8)/365,0) -> 27 | H9: Above 65 -70 | I9: =SUM(J9:L9) -> 0.165 | J9: =6.07%*M9 -> 0.0100155 | K9: =30.3%*M9 -> 0.049995 | L9: =63.63%*M9 -> 0.1049895 | M9: =N9+O9 -> 0.165 | N9: =16.5%-O9 -> 0.09 | O9: 0.075 | Q9: =Q8+1 -> 33 | R9: =R8+1 -> 2031 | S9: =(S8*103.5%) -> 130894.42 | T9: =T8*103.5% -> 261864.75 | U9: =U8*103.5% -> 523729.5 | V9: =V8+30 -> 1010 | W9: =W8+60 -> 1900 | X9: =X8*103.31% -> 4043.8757
B10: Current Gross Wage Per month | C10: 4000 | H10: Above 70 | I10: =SUM(J10:L10) -> 0.125 | J10: =8%*M10 -> 0.01 | K10: =8%*M10 -> 0.01 | L10: =84%*M10 -> 0.105 | M10: =N10+O10 -> 0.125 | N10: =12.5%-O10 -> 0.075 | O10: 0.05 | Q10: =Q9+1 -> 34 | R10: =R9+1 -> 2032 | S10: =(S9*103.5%) -> 135475.73 | T10: =T9*103.5% -> 271030.01 | U10: =U9*103.5% -> 542060.03 | V10: =V9+30 -> 1040 | W10: =W9+60 -> 1960 | X10: =X9*103.31% -> 4177.728
B11: TTL mths of salary +AWS+Bonus | C11: 14 | Q11: =Q10+1 -> 35 | R11: =R10+1 -> 2033 | S11: =(S10*103.5%) -> 140217.38 | T11: =T10*103.5% -> 280516.07 | U11: =U10*103.5% -> 561032.13 | V11: =V10+30 -> 1070 | W11: =W10+60 -> 2020 | X11: =X10*103.31% -> 4316.0108
B12: Current Gross Wage per Year | C12: =C10*C11 -> 56000 | Q12: =Q11+1 -> 36 | R12: =R11+1 -> 2034 | S12: =(S11*103.5%) -> 145124.99 | T12: =T11*103.5% -> 290334.13 | U12: =U11*103.5% -> 580668.26 | V12: =V11+30 -> 1100 | W12: =W11+60 -> 2080 | X12: =X11*103.31% -> 4458.8708
B13: Current Additional Month OA | C13: =C10*E13 -> 920.116 | D13: OA Band | E13: =IF($C$9<=35,J3,IF($C$9<=45,J4,IF($C$9<=50,J5,IF($C$9<=55,J6,IF($C$9<=60,J7,IF($C$9<=65,J8,IF(J14<=70,J9,J10))))))) -> 0.230029 | Q13: =Q12+1 -> 37 | R13: =R12+1 -> 2035 | S13: =(S12*103.5%) -> 150204.36 | T13: =T12*103.5% -> 300495.82 | U13: =U12*103.5% -> 600991.64 | V13: =V12+30 -> 1130 | W13: =W12+60 -> 2140 | X13: =X12*103.31% -> 4606.4594
B14: Current Additional Month SA | C14: =C10*E14 -> 239.908 | D14: SA Band | E14: =IF($C$9<=35,K3,IF($C$9<=45,K4,IF($C$9<=50,K5,IF($C$9<=55,K6,IF($C$9<=60,K7,IF($C$9<=65,K8,IF($C$9<=70,K9,K10))))))) -> 0.059977 | Q14: =Q13+1 -> 38 | R14: =R13+1 -> 2036 | S14: =(S13*103.5%) -> 155461.51 | T14: =T13*103.5% -> 311013.18 | U14: =U13*103.5% -> 622026.35 | V14: =V13+30 -> 1160 | W14: =W13+60 -> 2200 | X14: =X13*103.31% -> 4758.9332
B15: Current Additional Month MA | C15: =E15*C10 -> 319.976 | D15: MA Band | E15: =IF($C$9<=35,L3,IF($C$9<=45,L4,IF($C$9<=50,L5,IF($C$9<=55,L6,IF($C$9<=60,L7,IF($C$9<=65,L8,IF($C$9<=70,L9,L10))))))) -> 0.079994 | Q15: =Q14+1 -> 39 | R15: =R14+1 -> 2037 | S15: =(S14*103.5%) -> 160902.67 | T15: =T14*103.5% -> 321898.64 | U15: =U14*103.5% -> 643797.27 | V15: =V14+30 -> 1190 | W15: =W14+60 -> 2260 | X15: =X14*103.31% -> 4916.4539
B16: Employer CPF Contribution | C16: =E16*C10 -> 680 | D16: Employer Contribution | E16: =IF($C$9<=35,N3,IF($C$9<=45,N4,IF($C$9<=50,N5,IF($C$9<=55,N6,IF($C$9<=60,N7,IF($C$9<=65,N8,IF($C$9<=70,N9,N10))))))) -> 0.17 | Q16: =Q15+1 -> 40 | R16: =R15+1 -> 2038 | S16: =(S15*103.5%) -> 166534.26 | T16: =T15*103.5% -> 333165.09 | U16: =U15*103.5% -> 666330.18 | V16: =V15+30 -> 1220 | W16: =W15+60 -> 2320 | X16: =X15*103.31% -> 5079.1885
B17: Employee CPF Contribution | C17: =E17*C10 -> 800 | D17: Employee Contribution | E17: =IF($C$9<=35,O3,IF($C$9<=45,O4,IF($C$9<=50,O5,IF($C$9<=55,O6,IF($C$9<=60,O7,IF($C$9<=65,O8,IF($C$9<=70,O9,O10))))))) -> 0.2 | Q17: =Q16+1 -> 41 | R17: =R16+1 -> 2039 | S17: =(S16*103.5%) -> 172362.96 | T17: =T16*103.5% -> 344825.87 | U17: =U16*103.5% -> 689651.74 | V17: =V16+30 -> 1250 | W17: =W16+60 -> 2380 | X17: =X16*103.31% -> 5247.3096
B18: Total CPF Contribution | C18: =C17+C16 -> 1480 | Q18: =Q17+1 -> 42 | R18: =R17+1 -> 2040 | S18: =(S17*103.5%) -> 178395.66 | T18: =T17*103.5% -> 356894.77 | U18: =U17*103.5% -> 713789.55 | V18: =V17+30 -> 1280 | W18: =W17+60 -> 2440 | X18: =X17*103.31% -> 5420.9956
B19: OA Balance YTD | C19: 21000 | D19: Estimated OA | E19: =C13*12*17 -> 187703.66 | Q19: =Q18+1 -> 43 | R19: =R18+1 -> 2041 | S19: =(S18*103.5%) -> 184639.51 | T19: =T18*103.5% -> 369386.09 | U19: =U18*103.5% -> 738772.18 | V19: =V18+30 -> 1310 | W19: =W18+60 -> 2500 | X19: =X18*103.31% -> 5600.4305
B20: SA Balance YTD | C20: 60000 | D20: Estimated SA | E20: =C14*12*17 -> 48941.232 | Q20: =Q19+1 -> 44 | R20: =R19+1 -> 2042 | S20: =(S19*103.5%) -> 191101.89 | T20: =T19*103.5% -> 382314.6 | U20: =U19*103.5% -> 764629.21 | V20: =V19+30 -> 1340 | W20: =W19+60 -> 2560 | X20: =X19*103.31% -> 5785.8048
B21: MA Balance YTD | C21: 40000 | D21: Estimated MA | E21: =C15*12*17 -> 65275.104 | Q21: =Q20+1 -> 45 | R21: =R20+1 -> 2043 | S21: =(S20*103.5%) -> 197790.46 | T21: =T20*103.5% -> 395695.61 | U21: =U20*103.5% -> 791391.23 | V21: =V20+30 -> 1370 | W21: =W20+60 -> 2620 | X21: =X20*103.31% -> 5977.3149
Q22: =Q21+1 -> 46 | R22: =R21+1 -> 2044 | S22: =(S21*103.5%) -> 204713.13 | T22: =T21*103.5% -> 409544.96 | U22: =U21*103.5% -> 819089.92 | V22: =V21+30 -> 1400 | W22: =W21+60 -> 2680 | X22: =X21*103.31% -> 6175.164
B23: CPFL | Q23: =Q22+1 -> 47 | R23: =R22+1 -> 2045 | S23: =(S22*103.5%) -> 211878.09 | T23: =T22*103.5% -> 423879.03 | U23: =U22*103.5% -> 847758.07 | V23: =V22+30 -> 1430 | W23: =W22+60 -> 2740 | X23: =X22*103.31% -> 6379.562
B24: Year Age 55 | C24: =YEAR(TODAY()) + (55 - (YEAR(TODAY()) - YEAR(C8))) -> 2054 | D24: Years to Age 55 | E24: =$C$24-YEAR(TODAY()) -> 28 | Q24: =Q23+1 -> 48 | R24: =R23+1 -> 2046 | S24: =(S23*103.5%) -> 219293.82 | T24: =T23*103.5% -> 438714.8 | U24: =U23*103.5% -> 877429.6 | V24: =V23+30 -> 1460 | W24: =W23+60 -> 2800 | X24: =X23*103.31% -> 6590.7255
B25: Estimated BRS | C25: =INDEX($S$2:$S$39,MATCH($C$24,$R$2:$R$39,1)) -> 288768.08 | D25: Estimated Payout | E25: =INDEX($V$2:$V$39,MATCH($C$24,$R$2:$R$39,1)) -> 1700 | Q25: =Q24+1 -> 49 | R25: =R24+1 -> 2047 | S25: =(S24*103.5%) -> 226969.1 | T25: =T24*103.5% -> 454069.82 | U25: =U24*103.5% -> 908139.64 | V25: =V24+30 -> 1490 | W25: =W24+60 -> 2860 | X25: =X24*103.31% -> 6808.8785
B26: Estimated FRS | C26: =INDEX($T$2:$T$39,MATCH($C$24,$R$2:$R$39,1)) -> 577703.61 | D26: Estimated Payout | E26: =INDEX($W$2:$W$39,MATCH($C$24,$R$2:$R$39,1)) -> 3280 | Q26: =Q25+1 -> 50 | R26: =R25+1 -> 2048 | S26: =(S25*103.5%) -> 234913.02 | T26: =T25*103.5% -> 469962.26 | U26: =U25*103.5% -> 939924.52 | V26: =V25+30 -> 1520 | W26: =W25+60 -> 2920 | X26: =X25*103.31% -> 7034.2524
B27: Estimated ERS | C27: =INDEX($U$2:$U$39,MATCH($C$24,$R$2:$R$39,1)) -> 1155407.2 | D27: Estimated Payout | E27: =INDEX($X$2:$X$39,MATCH($C$24,$R$2:$R$39,1)) -> 8552.0871 | Q27: =Q26+1 -> 51 | R27: =R26+1 -> 2049 | S27: =(S26*103.5%) -> 243134.98 | T27: =T26*103.5% -> 486410.94 | U27: =U26*103.5% -> 972821.88 | V27: =V26+30 -> 1550 | W27: =W26+60 -> 2980 | X27: =X26*103.31% -> 7267.0861
Q28: =Q27+1 -> 52 | R28: =R27+1 -> 2050 | S28: =(S27*103.5%) -> 251644.7 | T28: =T27*103.5% -> 503435.32 | U28: =U27*103.5% -> 1006870.6 | V28: =V27+30 -> 1580 | W28: =W27+60 -> 3040 | X28: =X27*103.31% -> 7507.6267
B29: Inflation Adjusted | C29: 0.02 | D29: Inflation Adjusted BRS | E29: =FV(-$C$29,$C$24-YEAR(TODAY()),0,-E25) -> 965.5595 | Q29: =Q28+1 -> 53 | R29: =R28+1 -> 2051 | S29: =(S28*103.5%) -> 260452.27 | T29: =T28*103.5% -> 521055.56 | U29: =U28*103.5% -> 1042111.1 | V29: =V28+30 -> 1610 | W29: =W28+60 -> 3100 | X29: =X28*103.31% -> 7756.1291
D30: Inflation Adjusted FRS | E30: =FV(-$C$29,$C$24-YEAR(TODAY()),0,-E26) -> 1862.9619 | Q30: =Q29+1 -> 54 | R30: =R29+1 -> 2052 | S30: =(S29*103.5%) -> 269568.09 | T30: =T29*103.5% -> 539292.51 | U30: =U29*103.5% -> 1078585 | V30: =V29+30 -> 1640 | W30: =W29+60 -> 3160 | X30: =X29*103.31% -> 8012.857
D31: Inflation Adjusted ERS | E31: =FV(-$C$29,$C$24-YEAR(TODAY()),0,-E27) -> 4857.3817 | Q31: =Q30+1 -> 55 | R31: =R30+1 -> 2053 | S31: =(S30*103.5%) -> 279002.98 | T31: =T30*103.5% -> 558167.74 | U31: =U30*103.5% -> 1116335.5 | V31: =V30+30 -> 1670 | W31: =W30+60 -> 3220 | X31: =X30*103.31% -> 8278.0826
Q32: =Q31+1 -> 56 | R32: =R31+1 -> 2054 | S32: =(S31*103.5%) -> 288768.08 | T32: =T31*103.5% -> 577703.61 | U32: =U31*103.5% -> 1155407.2 | V32: =V31+30 -> 1700 | W32: =W31+60 -> 3280 | X32: =X31*103.31% -> 8552.0871
B33: Accumulation CPFL At Age 65 | Q33: =Q32+1 -> 57 | R33: =R32+1 -> 2055 | S33: =(S32*103.5%) -> 298874.96 | T33: =T32*103.5% -> 597923.24 | U33: =U32*103.5% -> 1195846.5 | V33: =V32+30 -> 1730 | W33: =W32+60 -> 3340 | X33: =X32*103.31% -> 8835.1612
B34: Estimated Accumulation CPFL BRS | C34: =C25*(1+0.04)^10 -> 427447.3 | D34: Estimated Accumulation FRS | E34: =C26*(1+0.04)^10 -> 855142.47 | Q34: =Q33+1 -> 58 | R34: =R33+1 -> 2056 | S34: =(S33*103.5%) -> 309335.59 | T34: =T33*103.5% -> 618850.55 | U34: =U33*103.5% -> 1237701.1 | V34: =V33+30 -> 1760 | W34: =W33+60 -> 3400 | X34: =X33*103.31% -> 9127.605
B35: Monthly Payout till Age 80 | C35: =E25*12*15 -> 306000 | D35: Monthly Payout till Age 80 | E35: =E26*12*15 -> 590400 | Q35: =Q34+1 -> 59 | R35: =R34+1 -> 2057 | S35: =(S34*103.5%) -> 320162.33 | T35: =T34*103.5% -> 640510.32 | U35: =U34*103.5% -> 1281020.6 | V35: =V34+30 -> 1790 | W35: =W34+60 -> 3460 | X35: =X34*103.31% -> 9429.7287
B36: CPBL Death Payout | C36: =C34-C35 -> 121447.3 | D36: CPBL Death Payout | E36: =E34-E35 -> 264742.47 | Q36: =Q35+1 -> 60 | R36: =R35+1 -> 2058 | S36: =(S35*103.5%) -> 331368.02 | T36: =T35*103.5% -> 662928.18 | U36: =U35*103.5% -> 1325856.4 | V36: =V35+30 -> 1820 | W36: =W35+60 -> 3520 | X36: =X35*103.31% -> 9741.8528
Q37: =Q36+1 -> 61 | R37: =R36+1 -> 2059 | S37: =(S36*103.5%) -> 342965.9 | T37: =T36*103.5% -> 686130.67 | U37: =U36*103.5% -> 1372261.3 | V37: =V36+30 -> 1850 | W37: =W36+60 -> 3580 | X37: =X36*103.31% -> 10064.308
Q38: =Q37+1 -> 62 | R38: =R37+1 -> 2060 | S38: =(S37*103.5%) -> 354969.7 | T38: =T37*103.5% -> 710145.24 | U38: =U37*103.5% -> 1420290.5 | V38: =V37+30 -> 1880 | W38: =W37+60 -> 3640 | X38: =X37*103.31% -> 10397.437
B39: Medical Insurance | Q39: =Q38+1 -> 63 | R39: =R38+1 -> 2061 | S39: =(S38+3900) -> 358869.7 | T39: =T38*103.5% -> 735000.33 | U39: =U38*103.5% -> 1470000.7 | V39: =V38+30 -> 1910 | W39: =W38+60 -> 3700 | X39: =X38*103.31% -> 10741.592
B40: Private Hospital Plan | C40: Yes
B41: Careshield | C41: Yes
B42: Private Careshield Plan | C42: Yes | D42: Term (Till Age 67/84) | E42: 67
B45: When do you wish to retire? | D45: 65
B46: Years of Retirement | D46: =E47-D45 -> 25 | F46: Yrs Old
D47: Your Age will be | E47: 90
B48: Accumulation Years | D48: =D45-#REF! -> #REF!
B49: Desired Monthly Supplement | D49: =D51 -> 1000
F50: 0.02
B51: Desired Monthly Fund | D51: 1000 | E51: Inflation Rate | F51: =FV(F50,$D$117,0,-D51) -> 2122.2988
B52: Monthly Fund At Retirement Age | D52: =D45 -> 65 | E52: will become | F52: =F51*D53*12 -> 636689.64
B53: Total Fund Needed | D53: =D46 -> 25 | E53: will become
F95: =YEAR(E96) -> 2054
B96: 2.Your eligibility for CPF Life at Age 55 | D96: Year | E96: =TODAY()+(55-$C$9)*365 -> 56403
B97: OA Accumulated Amount by age | C97: 55 | D97: ='[10]CPF TB'!D42 -> 93497.753
B98: SA Accumulated Amount by age | C98: =C97 -> 55 | D98: ='[10]CPF TB'!E42 -> 373778.16
B99: MA Accumulated Amount by age | C99: =C98 -> 55 | D99: ='[10]CPF TB'!C42 -> 75500
B100: RA Accumulated Amount by age | C100: =C99 -> 55 | D100: =D97+D98 -> 467275.92
C103: Sum Required | D103: Eligibility | E103: Est Monthly Payout
B104: Current OA | C104: =C19 -> 21000
B105: Current SA | C105: =C20 -> 60000
B106: Current MA | C106: =#REF! -> #REF! | G106: =FV(F119,$D$117,0,-E107) -> 4032.3677
B107: FRS | C107: ='[10]CPF TB'!H42 -> 261864.75 | D107: ='[10]CPF TB'!C48 -> Yes | E107: ='[10]CPF TB'!D48 -> 1900 | G107: =FV(F119,$D$117,0,-E108) -> 8582.3125
B108: ERS | C108: ='[10]CPF TB'!I42 -> 523729.5 | D108: ='[10]CPF TB'!C49 -> No | E108: ='[10]CPF TB'!D49 -> 4043.8757 | G108: =FV(F119,$D$117,0,-E109) -> 2143.5218
B109: BRS | C109: ='[10]CPF TB'!G42 -> 130894.42 | D109: ='[10]CPF TB'!C47 -> Yes | E109: ='[10]CPF TB'!D47 -> 1010
B110: Surplus/Shortfall to achieve FRS | C110: =D100-C107 -> 205411.17
B112: Let's gauge how much funds you need to set aside for your retirement.
B114: When do you wish to retire? | D114: 65
B115: Years of Retirement | D115: =E116-D114 -> 25 | F115: Yrs Old
D116: Your Age will be | E116: 90
B117: Accumulation Years | D117: =D114-C9 -> 38
B118: Desired Monthly Supplement | D118: =D120 -> 1000
F119: 0.02
B120: Desired Monthly Fund | D120: 1000 | E120: Inflation Rate | F120: =FV(F119,$D$117,0,-D120) -> 2122.2988
B121: Monthly Fund At Retirement Age | D121: =D114 -> 65 | E121: will become | F121: =F120*D122*12 -> 636689.64
B122: Total Fund Needed | D122: =D115 -> 25 | E122: will become
B127: 4.Let's estimate how much you will have at retirement with your current savings and investments. | F127: =D114 -> 65
B128: At Retirement | D128: Accumulated Amount by age
B129: CPF OA | D129: ='[10]CPF TB'!D41 -> 162761.75
B130: CPF SA | D130: ='[10]CPF TB'!E41 -> 714215.28
F131: 55
B132: Option A. After FRS | D132: Accumulated Amount by age
B133: CPF OA | D133: ='[10]CPF TB'!E53 -> 93497.753
B134: CPF SA | D134: ='[10]CPF TB'!D53 -> 111913.42
F135: =F131 -> 55
B136: Option B. After ERS | D136: Accumulated Amount by age
B137: CPF OA | D137: ='[10]CPF TB'!E62 -> -56453.579
B138: CPF SA | D138: ='[10]CPF TB'!D62 -> 0
F139: =F135 -> 55
B140: Option C. After BRS | D140: Accumulated Amount by age
B141: CPF OA | D141: ='[10]CPF TB'!E73 -> 93497.753
B142: CPF SA | D142: ='[10]CPF TB'!D73 -> 242883.74 | F142: Age
B144: CPF Life payout | C144: 65 | D144: 65
B145: WL Age | C145: =E116 -> 90 | D145: =E116 -> 90
G147: 65 | H147: CPFL Payout | I147: Total Income | J147: Age Cash withdrawal Ends
B148: Cash Withdrawal | D148: Age 56 | E148: Age | G148: ='[10]CPF TB'!G54 -> 248502.16 | H148: ='[10]CPF TB'!H54 -> 1900 | I148: =H148+D149 -> 2900 | J148: 63
B149: Total CPFL Payout Est (Full) | C149: =($D$145-$D$144)*E112*12 -> 0 | D149: =$D$118 -> 1000 | E149: CPFL (FRS) | G149: ='[10]CPF TB'!G63 -> 121550.82 | H149: ='[10]CPF TB'!H63 -> 4043.8757 | I149: =H149+D150 -> 5043.8757 | J149: 57
B150: Total CPFL Payout Est (Enhanced) | C150: =($D$145-$D$144)*E113*12 -> 0 | D150: =$D$118 -> 1000 | E150: CPFL (FRS) | G150: ='[10]CPF TB'!G74 -> 346822.09 | H150: ='[10]CPF TB'!H74 -> 1010 | I150: =H150+D151 -> 2010 | J150: ='[10]CPF TB'!B38 -> 90
B151: Total CPFL Payout Est (Basic) | C151: =($D$145-$D$144)*E114*12 -> 0 | D151: =$D$118 -> 1000 | E151: CPFL (BRS)
B154: Lets See if you can afford Dream Home
B155: House Price | D155: 350000
...

Sheet CPF TB
A1: F
B2: CPFL | AK2: CPF Interest Earned | AL2: Before Age 55 | AM2: CPF Interest Earned | AN2: After Age 55 | AR2: Retirement Sum (Est FRS Increase 3% to 3.5% pa) | AW2: Estimated Pay Out (Est increase 3% to 3.5%pa) | BA2: Careshield Life Premium estimation | BF2: Singaporean CPF Allocation Rates (From 2025 Jan 1) Salary above $750/Month
B3: MA Projection | M3: SA/RA Projection | T3: OA Projection | AB3: RAProjection | AK3: 1st 20K OA | AL3: 0.035 | AM3: 1st 20K OA | AN3: 0.06 | AR3: Age | AS3: Year | AT3: BRS | AU3: FRS | AV3: ERS | AW3: BRS | AX3: FRS | AY3: ERS | BA3: Premium Est Increase | BB3: 0.02 | BC3: Payout Est Increase | BD3: 0.02 | BF3: Age Band | BG3: Total CPF | BH3: OA | BI3: SA | BJ3: MA | BK3: Total | BL3: Employer | BM3: Employee
B4: Age | C4: CareShield Premium | D4: Medishield Premium | E4: Private Shield AWL | F4: Care Secure Premium | G4: Additional MA by Salary | H4: YOY MA - Outflow | I4: MA earned Interest YoY | J4: Excess Transfer to SA | K4: Total MA After Cap | M4: Transfer from MA | N4: Additional SA from Salary | O4: SA Before Int Earned | P4: 1st 40K Interest Earned YoY | Q4: Remaining Int Earned YoY | R4: Total SA | T4: Additional OA from Salary | U4: Housing Loan | V4: DPS | W4: OA before Int Earned | X4: 1st 20K Interest Earned YoY | Y4: Remaining Int Earned YoY | Z4: Total OA | AB4: BRS | AC4: FRS | AD4: ERS | AK4: Remaining OA | AL4: 0.025 | AM4: Next 20K OA | AN4: 0.05 | BA4: Age | BB4: Female | BC4: Male | BD4: Payout | BF4: 35 & Below | BG4: =SUM(BH4:BJ4) -> 0.37 | BH4: =62.17%*BK4 -> 0.230029 | BI4: =16.21%*BK4 -> 0.059977 | BJ4: =21.62%*BK4 -> 0.079994 | BK4: =BL4+BM4 -> 0.37 | BL4: 0.17 | BM4: 0.2
B5: =BH30 -> 52 | C5: =INDEX(BB5:BC42, MATCH(B5, BA5:BA42, 0), MATCH('Retirement Dashboard'!$C$7, BB4:BC4, 0)) -> 391.13286 | D5: =IF(B5<=20,$AL$14,IF(B5<=30,$AL$15,IF(B5<=40,$AL$16,IF(B5<=50,$AL$17,IF(B5<=60,$AL$18,IF(B5<=65,$AL$19,IF(B5<=70,$AL$20, IF(B5<=73,$AL$21,IF(B5<=75,$AL$22,IF(B5<=78,$AL$23,IF(B5<=80,$AL$24,IF(B5<=83,$AL$25,IF(B5<=85,$AL$26,IF(B5<=90,$AL$27,$AL$28)))))))))))))) -> 800 | E5: =IF(B5<=20,$AM$14,IF(B5<=30,$AM$15,IF(B5<=40,$AM$16,IF(B5<=50,$AM$17,IF(B5<=60,$AM$18,IF(B5<=65,$AM$19,IF(B5<=70,$AM$20, IF(B5<=73,$AM$21,IF(B5<=75,$AM$22,IF(B5<=78,$AM$23,IF(B5<=80,$AM$24,IF(B5<=83,$AM$25,IF(B5<=85,$AM$26,IF(B5<=90,$AM$27,$AM$28)))))))))))))) -> 600 | F5: =IF(AND('Retirement Dashboard'!$C$42="Yes", B5<= 'Retirement Dashboard'!$E$42), 600, 0) -> 600 | G5: =IF(B5<'Retirement Dashboard'!$E$6,IF(B5<=35,$BJ$4,IF(B5<=45,$BJ$5,IF(B5<=50,$BJ$6,IF(B5<=55,$BJ$7,IF(B5<=60,$BJ$8,IF(B5<=65,$BJ$9,IF(B5<=70,$BJ$10,$BJ$11)))))))*'Retirement Dashboard'!$C$12,0) -> 5878.264 | H5: ='Retirement Dashboard'!C21-C5-D5-E5-F5+G5 -> 43487.131 | I5: =$AL$8*H5 -> 1739.4852 | J5: =IF(I5+H5-$AL$35>0,I5+H5-$AL$35,0) -> 0 | K5: =H5+I5-J5 -> 45226.616 | M5: =IF(J5>=0,J5,0) -> 0 | N5: =IF(B5<$BH$31,IF(B6<=35,$BI$4,IF(B6<=45,$BI$5,IF(B6<=50,$BI$6,IF(B6<=55,$BI$7,IF(B6<=60,$BI$8,IF(B6<=65,$BI$9,IF(B6<=70,$BI$10,$BI$11)))))))*'Retirement Dashboard'!$C$12,0) -> 6439.776 | O5: =M5+N5+'Retirement Dashboard'!C20 -> 66439.776 | P5: =IF(B5<=55,$AL$5,$AL$6)*(IF(O5>=40000,40000,O5)) -> 2000 | Q5: =$AN$7*IF(O5>=40000,O5-40000,0) -> 1321.9888 | R5: =IF(B5>=55,0,O5+P5+Q5) -> 69761.765 | T5: =IF(B5<$BH$31,IF(B5<=35,$BH$4,IF(B6<=45,$BH$5,IF(B6<=50,$BH$6,IF(B6<=55,$BH$7,IF(B6<=60,$BH$8,IF(B6<=65,$BH$9,IF(B6<=70,$BH$10,$BH$11)))))))*'Retirement Dashboard'!$C$12,0) -> 8401.96 | U5: =IF(B5<($BH$57+$BH$30),$BH$56*12,0) -> 0 | V5: =IF(B5<=34,$AN$31,IF(B5<=39,$AN$32,IF(B5<=44,$AN$33,IF(B5<=49,$AN$34,IF(B5<=54,$AN$35,IF(B5<=59,$AN$36,IF(B5<=69,$AN$37,0))))))) -> 188 | W5: =IF(B5>=55,T5-U5-V5+'Retirement Dashboard'!C19,T5-U5-V5+'Retirement Dashboard'!C19) -> 29213.96 | X5: =IF(B5<=55,$AL$3,$AN$3)*(IF(W5>=20000,20000,W5)) -> 700 | Y5: =$AL$4*IF(W5>=20000,W5-20000,W5) -> 230.349 | Z5: =W5+X5+Y5 -> 30144.309 | AK5: 1st 40K SA | AL5: 0.05 | AM5: Remaining OA | AN5: 0.025 | AR5: ='Retirement Dashboard'!C9 -> 27 | AS5: =BH27 -> 2025 | AT5: 106500 | AU5: 213000 | AV5: 426000 | AW5: 840 | AX5: 1590 | AY5: 3330 | BA5: 30 | BB5: 253 | BC5: 206 | BD5: 662 | BF5: Above 35-45 | BG5: =SUM(BH5:BJ5) -> 0.37 | BH5: =56.77%*BK5 -> 0.210049 | BI5: =18.91%*BK5 -> 0.069967 | BJ5: =24.32%*BK5 -> 0.089984 | BK5: =BL5+BM5 -> 0.37 | BL5: 0.17 | BM5: 0.2
B6: =B5+1 -> 53 | C6: =IF(B6>=67,$BI$55,C5+(1.0244%*C5)) -> 395.13962 | D6: =IF(B6<=20,$AL$14,IF(B6<=30,$AL$15,IF(B6<=40,$AL$16,IF(B6<=50,$AL$17,IF(B6<=60,$AL$18,IF(B6<=65,$AL$19,IF(B6<=70,$AL$20, IF(B6<=73,$AL$21,IF(B6<=75,$AL$22,IF(B6<=78,$AL$23,IF(B6<=80,$AL$24,IF(B6<=83,$AL$25,IF(B6<=85,$AL$26,IF(B6<=90,$AL$27,$AL$28)))))))))))))) -> 800 | E6: =IF(B6<=20,$AM$14,IF(B6<=30,$AM$15,IF(B6<=40,$AM$16,IF(B6<=50,$AM$17,IF(B6<=60,$AM$18,IF(B6<=65,$AM$19,IF(B6<=70,$AM$20, IF(B6<=73,$AM$21,IF(B6<=75,$AM$22,IF(B6<=78,$AM$23,IF(B6<=80,$AM$24,IF(B6<=83,$AM$25,IF(B6<=85,$AM$26,IF(B6<=90,$AM$27,$AM$28)))))))))))))) -> 600 | F6: =IF(AND('Retirement Dashboard'!$C$42="Yes", B6<= 'Retirement Dashboard'!$E$42), 600, 0) -> 600 | G6: =IF(B6<'Retirement Dashboard'!$E$6,IF(B6<=35,$BJ$4,IF(B6<=45,$BJ$5,IF(B6<=50,$BJ$6,IF(B6<=55,$BJ$7,IF(B6<=60,$BJ$8,IF(B6<=65,$BJ$9,IF(B6<=70,$BJ$10,$BJ$11)))))))*'Retirement Dashboard'!$C$12,0) -> 5878.264 | H6: =K5-C6-D6-E6-F6+G6 -> 48709.741 | I6: =$AL$8*H6 -> 1948.3896 | J6: =IF(I6+H6-$AL$35>0,I6+H6-$AL$35,0) -> 0 | K6: =H6+I6-J6 -> 50658.13 | M6: =IF(J6>=0,J6,0) -> 0 | N6: =IF(B6<$BH$31,IF(B7<=35,$BI$4,IF(B7<=45,$BI$5,IF(B7<=50,$BI$6,IF(B7<=55,$BI$7,IF(B7<=60,$BI$8,IF(B7<=65,$BI$9,IF(B7<=70,$BI$10,$BI$11)))))))*'Retirement Dashboard'!$C$12,0) -> 6439.776 | O6: =R5+N6+M6 -> 76201.541 | P6: =IF(B6<=55,$AL$5,$AN$6)*(IF(O6>=40000,40000,O6)) -> 2000 | Q6: =$AN$7*IF(O6>=40000,O6-40000,0) -> 1810.077 | R6: =O6+P6+Q6 -> 80011.618 | T6: =IF(B6<$BH$31,IF(B6<=35,$BH$4,IF(B7<=45,$BH$5,IF(B7<=50,$BH$6,IF(B7<=55,$BH$7,IF(B7<=60,$BH$8,IF(B7<=65,$BH$9,IF(B7<=70,$BH$10,$BH$11)))))))*'Retirement Dashboard'!$C$12,0) -> 8401.96 | U6: =IF(B6<($BH$57+$BH$30),$BH$56*12,0) -> 0 | V6: =IF(B6<=34,$AN$31,IF(B6<=39,$AN$32,IF(B6<=44,$AN$33,IF(B6<=49,$AN$34,IF(B6<=54,$AN$35,IF(B6<=59,$AN$36,IF(B6<=69,$AN$37,0))))))) -> 188 | W6: =Z5+T6-U6-V6 -> 38358.269 | X6: =IF(B6<=55,$AL$3,$AN$3)*(IF(W6>=20000,20000,W6)) -> 700 | Y6: =$AL$4*IF(W6>=20000,W6-20000,W6) -> 458.95673 | Z6: =W6+X6+Y6 -> 39517.226 | AK6: Remaining SA | AL6: 0.04 | AM6: 1st 10K RA | AN6: 0.06 | AR6: =AR5+1 -> 28 | AS6: =AS5+1 -> 2026 | AT6: 110200 | AU6: 220440 | AV6: 440800 | AW6: 850 | AX6: 1600 | AY6: =AY5*103.31% -> 3440.223 | BA6: 31 | BB6: =(100%+$BB$3)*BB5 -> 258.06 | BC6: =(100%+$BB$3)*BC5 -> 210.12 | BD6: =(100%+$BD$3)*BD5 -> 675.24 | BF6: Above 45-50 | BG6: =SUM(BH6:BJ6) -> 0.37 | BH6: =51.36%*BK6 -> 0.190032 | BI6: =21.62%*BK6 -> 0.079994 | BJ6: =27.02%*BK6 -> 0.099974 | BK6: =BL6+BM6 -> 0.37 | BL6: 0.17 | BM6: 0.2
B7: =B6+1 -> 54 | C7: =IF(B7>=67,$BI$55,C6+(1.0244%*C6)) -> 399.18743 | D7: =IF(B7<=20,$AL$14,IF(B7<=30,$AL$15,IF(B7<=40,$AL$16,IF(B7<=50,$AL$17,IF(B7<=60,$AL$18,IF(B7<=65,$AL$19,IF(B7<=70,$AL$20, IF(B7<=73,$AL$21,IF(B7<=75,$AL$22,IF(B7<=78,$AL$23,IF(B7<=80,$AL$24,IF(B7<=83,$AL$25,IF(B7<=85,$AL$26,IF(B7<=90,$AL$27,$AL$28)))))))))))))) -> 800 | E7: =IF(B7<=20,$AM$14,IF(B7<=30,$AM$15,IF(B7<=40,$AM$16,IF(B7<=50,$AM$17,IF(B7<=60,$AM$18,IF(B7<=65,$AM$19,IF(B7<=70,$AM$20, IF(B7<=73,$AM$21,IF(B7<=75,$AM$22,IF(B7<=78,$AM$23,IF(B7<=80,$AM$24,IF(B7<=83,$AM$25,IF(B7<=85,$AM$26,IF(B7<=90,$AM$27,$AM$28)))))))))))))) -> 600 | F7: =IF(AND('Retirement Dashboard'!$C$42="Yes", B7<= 'Retirement Dashboard'!$E$42), 600, 0) -> 600 | G7: =IF(B7<'Retirement Dashboard'!$E$6,IF(B7<=35,$BJ$4,IF(B7<=45,$BJ$5,IF(B7<=50,$BJ$6,IF(B7<=55,$BJ$7,IF(B7<=60,$BJ$8,IF(B7<=65,$BJ$9,IF(B7<=70,$BJ$10,$BJ$11)))))))*'Retirement Dashboard'!$C$12,0) -> 5878.264 | H7: =K6-C7-D7-E7-F7+G7 -> 54137.207 | I7: =$AL$8*H7 -> 2165.4883 | J7: =IF(I7+H7-$AL$35>0,I7+H7-$AL$35,0) -> 0 | K7: =H7+I7-J7 -> 56302.695 | M7: =IF(J7>=0,J7,0) -> 0 | N7: =IF(B7<$BH$31,IF(B8<=35,$BI$4,IF(B8<=45,$BI$5,IF(B8<=50,$BI$6,IF(B8<=55,$BI$7,IF(B8<=60,$BI$8,IF(B8<=65,$BI$9,IF(B8<=70,$BI$10,$BI$11)))))))*'Retirement Dashboard'!$C$12,0) -> 6439.776 | O7: =R6+N7+M7 -> 86451.394 | P7: =IF(B7<=55,$AL$5,$AN$6)*(IF(O7>=40000,40000,O7)) -> 2000 | Q7: =$AN$7*IF(O7>=40000,O7-40000,0) -> 2322.5697 | R7: =O7+P7+Q7 -> 90773.964 | T7: =IF(B7<$BH$31,IF(B7<=35,$BH$4,IF(B8<=45,$BH$5,IF(B8<=50,$BH$6,IF(B8<=55,$BH$7,IF(B8<=60,$BH$8,IF(B8<=65,$BH$9,IF(B8<=70,$BH$10,$BH$11)))))))*'Retirement Dashboard'!$C$12,0) -> 8401.96 | U7: =IF(B7<($BH$57+$BH$30),$BH$56*12,0) -> 0 | V7: =IF(B7<=34,$AN$31,IF(B7<=39,$AN$32,IF(B7<=44,$AN$33,IF(B7<=49,$AN$34,IF(B7<=54,$AN$35,IF(B7<=59,$AN$36,IF(B7<=69,$AN$37,0))))))) -> 188 | W7: =Z6+T7-U7-V7 -> 47731.186 | X7: =IF(B7<=55,$AL$3,$AN$3)*(IF(W7>=20000,20000,W7)) -> 700 | Y7: =$AL$4*IF(W7>=20000,W7-20000,W7) -> 693.27964 | Z7: =W7+X7+Y7 -> 49124.465 | AK7: BHS transferred to | AL7: SA | AM7: Next 10K RA | AN7: 0.05 | AR7: =AR6+1 -> 29 | AS7: =AS6+1 -> 2027 | AT7: 114100 | AU7: 228200 | AV7: 456400 | AW7: 900 | AX7: 1670 | AY7: 3550 | BA7: 32 | BB7: =(100%+$BB$3)*BB6 -> 263.2212 | BC7: =(100%+$BB$3)*BC6 -> 214.3224 | BD7: =(100%+$BD$3)*BD6 -> 688.7448 | BF7: Above 50-55 | BG7: =SUM(BH7:BJ7) -> 0.37 | BH7: =40.55%*BK7 -> 0.150035 | BI7: =31.08%*BK7 -> 0.114996 | BJ7: =28.37%*BK7 -> 0.104969 | BK7: =BL7+BM7 -> 0.37 | BL7: 0.17 | BM7: 0.2
B8: =B7+1 -> 55 | C8: =IF(B8>=67,$BI$55,C7+(1.0244%*C7)) -> 403.27671 | D8: =IF(B8<=20,$AL$14,IF(B8<=30,$AL$15,IF(B8<=40,$AL$16,IF(B8<=50,$AL$17,IF(B8<=60,$AL$18,IF(B8<=65,$AL$19,IF(B8<=70,$AL$20, IF(B8<=73,$AL$21,IF(B8<=75,$AL$22,IF(B8<=78,$AL$23,IF(B8<=80,$AL$24,IF(B8<=83,$AL$25,IF(B8<=85,$AL$26,IF(B8<=90,$AL$27,$AL$28)))))))))))))) -> 800 | E8: =IF(B8<=20,$AM$14,IF(B8<=30,$AM$15,IF(B8<=40,$AM$16,IF(B8<=50,$AM$17,IF(B8<=60,$AM$18,IF(B8<=65,$AM$19,IF(B8<=70,$AM$20, IF(B8<=73,$AM$21,IF(B8<=75,$AM$22,IF(B8<=78,$AM$23,IF(B8<=80,$AM$24,IF(B8<=83,$AM$25,IF(B8<=85,$AM$26,IF(B8<=90,$AM$27,$AM$28)))))))))))))) -> 600 | F8: =IF(AND('Retirement Dashboard'!$C$42="Yes", B8<= 'Retirement Dashboard'!$E$42), 600, 0) -> 600 | G8: =IF(B8<'Retirement Dashboard'!$E$6,IF(B8<=35,$BJ$4,IF(B8<=45,$BJ$5,IF(B8<=50,$BJ$6,IF(B8<=55,$BJ$7,IF(B8<=60,$BJ$8,IF(B8<=65,$BJ$9,IF(B8<=70,$BJ$10,$BJ$11)))))))*'Retirement Dashboard'!$C$12,0) -> 5878.264 | H8: =K7-C8-D8-E8-F8+G8 -> 59777.683 | I8: =$AL$8*H8 -> 2391.1073 | J8: =IF(I8+H8-$AL$35>0,I8+H8-$AL$35,0) -> 0 | K8: =H8+I8-J8 -> 62168.79 | M8: =IF(J8>=0,J8,0) -> 0 | N8: =IF(B8<$BH$31,IF(B9<=35,$BI$4,IF(B9<=45,$BI$5,IF(B9<=50,$BI$6,IF(B9<=55,$BI$7,IF(B9<=60,$BI$8,IF(B9<=65,$BI$9,IF(B9<=70,$BI$10,$BI$11)))))))*'Retirement Dashboard'!$C$12,0) -> 4988.62 | O8: =R7+N8+M8 -> 95762.584 | P8: =IF(B8<=55,$AL$5,$AN$6)*(IF(O8>=40000,40000,O8)) -> 2000 | Q8: =$AN$7*IF(O8>=40000,O8-40000,0) -> 2788.1292 | R8: =O8+P8+Q8 -> 100550.71 | T8: =IF(B8<$BH$31,IF(B8<=35,$BH$4,IF(B9<=45,$BH$5,IF(B9<=50,$BH$6,IF(B9<=55,$BH$7,IF(B9<=60,$BH$8,IF(B9<=65,$BH$9,IF(B9<=70,$BH$10,$BH$11)))))))*'Retirement Dashboard'!$C$12,0) -> 5618.704 | U8: =IF(B8<($BH$57+$BH$30),$BH$56*12,0) -> 0 | V8: =IF(B8<=34,$AN$31,IF(B8<=39,$AN$32,IF(B8<=44,$AN$33,IF(B8<=49,$AN$34,IF(B8<=54,$AN$35,IF(B8<=59,$AN$36,IF(B8<=69,$AN$37,0))))))) -> 298 | W8: =Z7+T8-U8-V8 -> 54445.169 | X8: =IF(B8<=55,$AL$3,$AN$3)*(IF(W8>=20000,20000,W8)) -> 700 | Y8: =$AL$4*IF(W8>=20000,W8-20000,W8) -> 861.12923 | Z8: =W8+X8+Y8 -> 56006.299 | AK8: MA | AL8: 0.04 | AM8: Remaining RA | AN8: 0.04 | AR8: =AR7+1 -> 30 | AS8: =AS7+1 -> 2028 | AT8: =(AT7*103.47%) -> 118059.27 | AU8: =AU7*103.5% -> 236187 | AV8: =AV7*103.5% -> 472374 | AW8: 930 | AX8: 1730 | AY8: =AY7*103.31% -> 3667.505 | BA8: 33 | BB8: =(100%+$BB$3)*BB7 -> 268.48562 | BC8: =(100%+$BB$3)*BC7 -> 218.60885 | BD8: =(100%+$BD$3)*BD7 -> 702.5197 | BF8: Above 55-60 | BG8: =SUM(BH8:BJ8) -> 0.299494 | BH8: =30.872%*BK8 -> 0.100334 | BI8: =27.41%*BK8 -> 0.0890825 | BJ8: =33.87%*BK8 -> 0.1100775 | BK8: =BL8+BM8 -> 0.325 | BL8: =32.5%-17% -> 0.155 | BM8: 0.17
B9: =B8+1 -> 56 | C9: =IF(B9>=67,$BI$55,C8+(1.0244%*C8)) -> 407.40787 | D9: =IF(B9<=20,$AL$14,IF(B9<=30,$AL$15,IF(B9<=40,$AL$16,IF(B9<=50,$AL$17,IF(B9<=60,$AL$18,IF(B9<=65,$AL$19,IF(B9<=70,$AL$20, IF(B9<=73,$AL$21,IF(B9<=75,$AL$22,IF(B9<=78,$AL$23,IF(B9<=80,$AL$24,IF(B9<=83,$AL$25,IF(B9<=85,$AL$26,IF(B9<=90,$AL$27,$AL$28)))))))))))))) -> 800 | E9: =IF(B9<=20,$AM$14,IF(B9<=30,$AM$15,IF(B9<=40,$AM$16,IF(B9<=50,$AM$17,IF(B9<=60,$AM$18,IF(B9<=65,$AM$19,IF(B9<=70,$AM$20, IF(B9<=73,$AM$21,IF(B9<=75,$AM$22,IF(B9<=78,$AM$23,IF(B9<=80,$AM$24,IF(B9<=83,$AM$25,IF(B9<=85,$AM$26,IF(B9<=90,$AM$27,$AM$28)))))))))))))) -> 600 | F9: =IF(AND('Retirement Dashboard'!$C$42="Yes", B9<= 'Retirement Dashboard'!$E$42), 600, 0) -> 600 | G9: =IF(B9<'Retirement Dashboard'!$E$6,IF(B9<=35,$BJ$4,IF(B9<=45,$BJ$5,IF(B9<=50,$BJ$6,IF(B9<=55,$BJ$7,IF(B9<=60,$BJ$8,IF(B9<=65,$BJ$9,IF(B9<=70,$BJ$10,$BJ$11)))))))*'Retirement Dashboard'!$C$12,0) -> 6164.34 | H9: =K8-C9-D9-E9-F9+G9 -> 65925.722 | I9: =$AL$8*H9 -> 2637.0289 | J9: =IF(I9+H9-$AL$35>0,I9+H9-$AL$35,0) -> 0 | K9: =H9+I9-J9 -> 68562.751 | M9: =IF(J9>=0,J9,0) -> 0 | N9: =IF(B9<$BH$31,IF(B10<=35,$BI$4,IF(B10<=45,$BI$5,IF(B10<=50,$BI$6,IF(B10<=55,$BI$7,IF(B10<=60,$BI$8,IF(B10<=65,$BI$9,IF(B10<=70,$BI$10,$BI$11)))))))*'Retirement Dashboard'!$C$12,0) -> 4988.62 | O9: =R8+N9+M9 -> 105539.33 | P9: =IF(B9<=55,$AL$5,$AN$6)*(IF(O9>=40000,40000,O9)) -> 2400 | Q9: =$AN$7*IF(O9>=40000,O9-40000,0) -> 3276.9666 | R9: =O9+P9+Q9 -> 111216.3 | T9: =IF(B9<$BH$31,IF(B9<=35,$BH$4,IF(B10<=45,$BH$5,IF(B10<=50,$BH$6,IF(B10<=55,$BH$7,IF(B10<=60,$BH$8,IF(B10<=65,$BH$9,IF(B10<=70,$BH$10,$BH$11)))))))*'Retirement Dashboard'!$C$12,0) -> 5618.704 | U9: =IF(B9<($BH$57+$BH$30),$BH$56*12,0) -> 0 | V9: =IF(B9<=34,$AN$31,IF(B9<=39,$AN$32,IF(B9<=44,$AN$33,IF(B9<=49,$AN$34,IF(B9<=54,$AN$35,IF(B9<=59,$AN$36,IF(B9<=69,$AN$37,0))))))) -> 298 | W9: =Z8+T9-U9-V9 -> 61327.003 | X9: =IF(B9<=55,$AL$3,$AN$3)*(IF(W9>=20000,20000,W9)) -> 1200 | Y9: =$AL$4*IF(W9>=20000,W9-20000,W9) -> 1033.1751 | Z9: =W9+X9+Y9 -> 63560.178 | AM9: BHS Transfer to | AN9: RA | AR9: =AR8+1 -> 31 | AS9: =AS8+1 -> 2029 | AT9: =(AT8*103.5%) -> 122191.34 | AU9: =AU8*103.5% -> 244453.54 | AV9: =AV8*103.5% -> 488907.09 | AW9: 950 | AX9: 1780 | AY9: =AY8*103.31% -> 3788.8994 | BA9: 34 | BB9: =(100%+$BB$3)*BB8 -> 273.85534 | BC9: =(100%+$BB$3)*BC8 -> 222.98102 | BD9: =(100%+$BD$3)*BD8 -> 716.57009 | BF9: Above 60-65 | BG9: =SUM(BH9:BJ9) -> 0.234295 | BH9: =15.62%*BK9 -> 0.036707 | BI9: =36.36%*BK9 -> 0.085446 | BJ9: =47.72%*BK9 -> 0.112142 | BK9: =BL9+BM9 -> 0.235 | BL9: =23.5%-BM9 -> 0.12 | BM9: 0.115
B10: =B9+1 -> 57 | C10: =IF(B10>=67,$BI$55,C9+(1.0244%*C9)) -> 411.58136 | D10: =IF(B10<=20,$AL$14,IF(B10<=30,$AL$15,IF(B10<=40,$AL$16,IF(B10<=50,$AL$17,IF(B10<=60,$AL$18,IF(B10<=65,$AL$19,IF(B10<=70,$AL$20, IF(B10<=73,$AL$21,IF(B10<=75,$AL$22,IF(B10<=78,$AL$23,IF(B10<=80,$AL$24,IF(B10<=83,$AL$25,IF(B10<=85,$AL$26,IF(B10<=90,$AL$27,$AL$28)))))))))))))) -> 800 | E10: =IF(B10<=20,$AM$14,IF(B10<=30,$AM$15,IF(B10<=40,$AM$16,IF(B10<=50,$AM$17,IF(B10<=60,$AM$18,IF(B10<=65,$AM$19,IF(B10<=70,$AM$20, IF(B10<=73,$AM$21,IF(B10<=75,$AM$22,IF(B10<=78,$AM$23,IF(B10<=80,$AM$24,IF(B10<=83,$AM$25,IF(B10<=85,$AM$26,IF(B10<=90,$AM$27,$AM$28)))))))))))))) -> 600 | F10: =IF(AND('Retirement Dashboard'!$C$42="Yes", B10<= 'Retirement Dashboard'!$E$42), 600, 0) -> 600 | G10: =IF(B10<'Retirement Dashboard'!$E$6,IF(B10<=35,$BJ$4,IF(B10<=45,$BJ$5,IF(B10<=50,$BJ$6,IF(B10<=55,$BJ$7,IF(B10<=60,$BJ$8,IF(B10<=65,$BJ$9,IF(B10<=70,$BJ$10,$BJ$11)))))))*'Retirement Dashboard'!$C$12,0) -> 6164.34 | H10: =K9-C10-D10-E10-F10+G10 -> 72315.509 | I10: =$AL$8*H10 -> 2892.6204 | J10: =IF(I10+H10-$AL$35>0,I10+H10-$AL$35,0) -> 0 | K10: =H10+I10-J10 -> 75208.13 | M10: =IF(J10>=0,J10,0) -> 0 | N10: =IF(B10<$BH$31,IF(B11<=35,$BI$4,IF(B11<=45,$BI$5,IF(B11<=50,$BI$6,IF(B11<=55,$BI$7,IF(B11<=60,$BI$8,IF(B11<=65,$BI$9,IF(B11<=70,$BI$10,$BI$11)))))))*'Retirement Dashboard'!$C$12,0) -> 4988.62 | O10: =R9+N10+M10 -> 116204.92 | P10: =IF(B10<=55,$AL$5,$AN$6)*(IF(O10>=40000,40000,O10)) -> 2400 | Q10: =$AN$7*IF(O10>=40000,O10-40000,0) -> 3810.246 | R10: =O10+P10+Q10 -> 122415.17 | T10: =IF(B10<$BH$31,IF(B10<=35,$BH$4,IF(B11<=45,$BH$5,IF(B11<=50,$BH$6,IF(B11<=55,$BH$7,IF(B11<=60,$BH$8,IF(B11<=65,$BH$9,IF(B11<=70,$BH$10,$BH$11)))))))*'Retirement Dashboard'!$C$12,0) -> 5618.704 | U10: =IF(B10<($BH$57+$BH$30),$BH$56*12,0) -> 0 | V10: =IF(B10<=34,$AN$31,IF(B10<=39,$AN$32,IF(B10<=44,$AN$33,IF(B10<=49,$AN$34,IF(B10<=54,$AN$35,IF(B10<=59,$AN$36,IF(B10<=69,$AN$37,0))))))) -> 298 | W10: =Z9+T10-U10-V10 -> 68880.882 | X10: =IF(B10<=55,$AL$3,$AN$3)*(IF(W10>=20000,20000,W10)) -> 1200 | Y10: =$AL$4*IF(W10>=20000,W10-20000,W10) -> 1222.022 | Z10: =W10+X10+Y10 -> 71302.904 | AM10: MA | AN10: 0.04 | AR10: =AR9+1 -> 32 | AS10: =AS9+1 -> 2030 | AT10: =(AT9*103.5%) -> 126468.04 | AU10: =AU9*103.5% -> 253009.42 | AV10: =AV9*103.5% -> 506018.84 | AW10: 980 | AX10: 1840 | AY10: =AY9*103.31% -> 3914.312 | BA10: 35 | BB10: =(100%+$BB$3)*BB9 -> 279.33244 | BC10: =(100%+$BB$3)*BC9 -> 227.44065 | BD10: =(100%+$BD$3)*BD9 -> 730.90149 | BF10: Above 65 -70 | BG10: =SUM(BH10:BJ10) -> 0.165 | BH10: =6.07%*BK10 -> 0.0100155 | BI10: =30.3%*BK10 -> 0.049995 | BJ10: =63.63%*BK10 -> 0.1049895 | BK10: =BL10+BM10 -> 0.165 | BL10: =16.5%-BM10 -> 0.09 | BM10: 0.075
B11: =B10+1 -> 58 | C11: =IF(B11>=67,$BI$55,C10+(1.0244%*C10)) -> 415.7976 | D11: =IF(B11<=20,$AL$14,IF(B11<=30,$AL$15,IF(B11<=40,$AL$16,IF(B11<=50,$AL$17,IF(B11<=60,$AL$18,IF(B11<=65,$AL$19,IF(B11<=70,$AL$20, IF(B11<=73,$AL$21,IF(B11<=75,$AL$22,IF(B11<=78,$AL$23,IF(B11<=80,$AL$24,IF(B11<=83,$AL$25,IF(B11<=85,$AL$26,IF(B11<=90,$AL$27,$AL$28)))))))))))))) -> 800 | E11: =IF(B11<=20,$AM$14,IF(B11<=30,$AM$15,IF(B11<=40,$AM$16,IF(B11<=50,$AM$17,IF(B11<=60,$AM$18,IF(B11<=65,$AM$19,IF(B11<=70,$AM$20, IF(B11<=73,$AM$21,IF(B11<=75,$AM$22,IF(B11<=78,$AM$23,IF(B11<=80,$AM$24,IF(B11<=83,$AM$25,IF(B11<=85,$AM$26,IF(B11<=90,$AM$27,$AM$28)))))))))))))) -> 600 | F11: =IF(AND('Retirement Dashboard'!$C$42="Yes", B11<= 'Retirement Dashboard'!$E$42), 600, 0) -> 600 | G11: =IF(B11<'Retirement Dashboard'!$E$6,IF(B11<=35,$BJ$4,IF(B11<=45,$BJ$5,IF(B11<=50,$BJ$6,IF(B11<=55,$BJ$7,IF(B11<=60,$BJ$8,IF(B11<=65,$BJ$9,IF(B11<=70,$BJ$10,$BJ$11)))))))*'Retirement Dashboard'!$C$12,0) -> 6164.34 | H11: =K10-C11-D11-E11-F11+G11 -> 78956.672 | I11: =$AL$8*H11 -> 3158.2669 | J11: =IF(I11+H11-$AL$35>0,I11+H11-$AL$35,0) -> 6614.9392 | K11: =H11+I11-J11 -> 75500 | M11: =IF(J11>=0,J11,0) -> 6614.9392 | N11: =IF(B11<$BH$31,IF(B12<=35,$BI$4,IF(B12<=45,$BI$5,IF(B12<=50,$BI$6,IF(B12<=55,$BI$7,IF(B12<=60,$BI$8,IF(B12<=65,$BI$9,IF(B12<=70,$BI$10,$BI$11)))))))*'Retirement Dashboard'!$C$12,0) -> 4988.62 | O11: =R10+N11+M11 -> 134018.72 | P11: =IF(B11<=55,$AL$5,$AN$6)*(IF(O11>=40000,40000,O11)) -> 2400 | Q11: =$AN$7*IF(O11>=40000,O11-40000,0) -> 4700.9362 | R11: =O11+P11+Q11 -> 141119.66 | T11: =IF(B11<$BH$31,IF(B11<=35,$BH$4,IF(B12<=45,$BH$5,IF(B12<=50,$BH$6,IF(B12<=55,$BH$7,IF(B12<=60,$BH$8,IF(B12<=65,$BH$9,IF(B12<=70,$BH$10,$BH$11)))))))*'Retirement Dashboard'!$C$12,0) -> 5618.704 | U11: =IF(B11<($BH$57+$BH$30),$BH$56*12,0) -> 0 | V11: =IF(B11<=34,$AN$31,IF(B11<=39,$AN$32,IF(B11<=44,$AN$33,IF(B11<=49,$AN$34,IF(B11<=54,$AN$35,IF(B11<=59,$AN$36,IF(B11<=69,$AN$37,0))))))) -> 298 | W11: =Z10+T11-U11-V11 -> 76623.608 | X11: =IF(B11<=55,$AL$3,$AN$3)*(IF(W11>=20000,20000,W11)) -> 1200 | Y11: =$AL$4*IF(W11>=20000,W11-20000,W11) -> 1415.5902 | Z11: =W11+X11+Y11 -> 79239.198 | AR11: =AR10+1 -> 33 | AS11: =AS10+1 -> 2031 | AT11: =(AT10*103.5%) -> 130894.42 | AU11: =AU10*103.5% -> 261864.75 | AV11: =AV10*103.5% -> 523729.5 | AW11: =AW10+30 -> 1010 | AX11: =AX10+60 -> 1900 | AY11: =AY10*103.31% -> 4043.8757 | BA11: 36 | BB11: =(100%+$BB$3)*BB10 -> 284.91909 | BC11: =(100%+$BB$3)*BC10 -> 231.98946 | BD11: =(100%+$BD$3)*BD10 -> 745.51952 | BF11: Above 70 | BG11: =SUM(BH11:BJ11) -> 0.125 | BH11: =8%*BK11 -> 0.01 | BI11: =8%*BK11 -> 0.01 | BJ11: =84%*BK11 -> 0.105 | BK11: =BL11+BM11 -> 0.125 | BL11: =12.5%-BM11 -> 0.075 | BM11: 0.05
B12: =B11+1 -> 59 | C12: =IF(B12>=67,$BI$55,C11+(1.0244%*C11)) -> 420.05703 | D12: =IF(B12<=20,$AL$14,IF(B12<=30,$AL$15,IF(B12<=40,$AL$16,IF(B12<=50,$AL$17,IF(B12<=60,$AL$18,IF(B12<=65,$AL$19,IF(B12<=70,$AL$20, IF(B12<=73,$AL$21,IF(B12<=75,$AL$22,IF(B12<=78,$AL$23,IF(B12<=80,$AL$24,IF(B12<=83,$AL$25,IF(B12<=85,$AL$26,IF(B12<=90,$AL$27,$AL$28)))))))))))))) -> 800 | E12: =IF(B12<=20,$AM$14,IF(B12<=30,$AM$15,IF(B12<=40,$AM$16,IF(B12<=50,$AM$17,IF(B12<=60,$AM$18,IF(B12<=65,$AM$19,IF(B12<=70,$AM$20, IF(B12<=73,$AM$21,IF(B12<=75,$AM$22,IF(B12<=78,$AM$23,IF(B12<=80,$AM$24,IF(B12<=83,$AM$25,IF(B12<=85,$AM$26,IF(B12<=90,$AM$27,$AM$28)))))))))))))) -> 600 | F12: =IF(AND('Retirement Dashboard'!$C$42="Yes", B12<= 'Retirement Dashboard'!$E$42), 600, 0) -> 600 | G12: =IF(B12<'Retirement Dashboard'!$E$6,IF(B12<=35,$BJ$4,IF(B12<=45,$BJ$5,IF(B12<=50,$BJ$6,IF(B12<=55,$BJ$7,IF(B12<=60,$BJ$8,IF(B12<=65,$BJ$9,IF(B12<=70,$BJ$10,$BJ$11)))))))*'Retirement Dashboard'!$C$12,0) -> 6164.34 | H12: =K11-C12-D12-E12-F12+G12 -> 79244.283 | I12: =$AL$8*H12 -> 3169.7713 | J12: =IF(I12+H12-$AL$35>0,I12+H12-$AL$35,0) -> 6914.0543 | K12: =H12+I12-J12 -> 75500 | M12: =IF(J12>=0,J12,0) -> 6914.0543 | N12: =IF(B12<$BH$31,IF(B13<=35,$BI$4,IF(B13<=45,$BI$5,IF(B13<=50,$BI$6,IF(B13<=55,$BI$7,IF(B13<=60,$BI$8,IF(B13<=65,$BI$9,IF(B13<=70,$BI$10,$BI$11)))))))*'Retirement Dashboard'!$C$12,0) -> 4988.62 | O12: =R11+N12+M12 -> 153022.33 | P12: =IF(B12<=55,$AL$5,$AN$6)*(IF(O12>=40000,40000,O12)) -> 2400 | Q12: =$AN$7*IF(O12>=40000,O12-40000,0) -> 5651.1167 | R12: =O12+P12+Q12 -> 161073.45 | T12: =IF(B12<$BH$31,IF(B12<=35,$BH$4,IF(B13<=45,$BH$5,IF(B13<=50,$BH$6,IF(B13<=55,$BH$7,IF(B13<=60,$BH$8,IF(B13<=65,$BH$9,IF(B13<=70,$BH$10,$BH$11)))))))*'Retirement Dashboard'!$C$12,0) -> 5618.704 | U12: =IF(B12<($BH$57+$BH$30),$BH$56*12,0) -> 0 | V12: =IF(B12<=34,$AN$31,IF(B12<=39,$AN$32,IF(B12<=44,$AN$33,IF(B12<=49,$AN$34,IF(B12<=54,$AN$35,IF(B12<=59,$AN$36,IF(B12<=69,$AN$37,0))))))) -> 298 | W12: =Z11+T12-U12-V12 -> 84559.902 | X12: =IF(B12<=55,$AL$3,$AN$3)*(IF(W12>=20000,20000,W12)) -> 1200 | Y12: =$AL$4*IF(W12>=20000,W12-20000,W12) -> 1613.9975 | Z12: =W12+X12+Y12 -> 87373.899 | AK12: H&S | AR12: =AR11+1 -> 34 | AS12: =AS11+1 -> 2032 | AT12: =(AT11*103.5%) -> 135475.73 | AU12: =AU11*103.5% -> 271030.01 | AV12: =AV11*103.5% -> 542060.03 | AW12: =AW11+30 -> 1040 | AX12: =AX11+60 -> 1960 | AY12: =AY11*103.31% -> 4177.728 | BA12: 37 | BB12: =(100%+$BB$3)*BB11 -> 290.61747 | BC12: =(100%+$BB$3)*BC11 -> 236.62925 | BD12: =(100%+$BD$3)*BD11 -> 760.42991
B13: =B12+1 -> 60 | C13: =IF(B13>=67,$BI$55,C12+(1.0244%*C12)) -> 424.3601 | D13: =IF(B13<=20,$AL$14,IF(B13<=30,$AL$15,IF(B13<=40,$AL$16,IF(B13<=50,$AL$17,IF(B13<=60,$AL$18,IF(B13<=65,$AL$19,IF(B13<=70,$AL$20, IF(B13<=73,$AL$21,IF(B13<=75,$AL$22,IF(B13<=78,$AL$23,IF(B13<=80,$AL$24,IF(B13<=83,$AL$25,IF(B13<=85,$AL$26,IF(B13<=90,$AL$27,$AL$28)))))))))))))) -> 800 | E13: =IF(B13<=20,$AM$14,IF(B13<=30,$AM$15,IF(B13<=40,$AM$16,IF(B13<=50,$AM$17,IF(B13<=60,$AM$18,IF(B13<=65,$AM$19,IF(B13<=70,$AM$20, IF(B13<=73,$AM$21,IF(B13<=75,$AM$22,IF(B13<=78,$AM$23,IF(B13<=80,$AM$24,IF(B13<=83,$AM$25,IF(B13<=85,$AM$26,IF(B13<=90,$AM$27,$AM$28)))))))))))))) -> 600 | F13: =IF(AND('Retirement Dashboard'!$C$42="Yes", B13<= 'Retirement Dashboard'!$E$42), 600, 0) -> 600 | G13: =IF(B13<'Retirement Dashboard'!$E$6,IF(B13<=35,$BJ$4,IF(B13<=45,$BJ$5,IF(B13<=50,$BJ$6,IF(B13<=55,$BJ$7,IF(B13<=60,$BJ$8,IF(B13<=65,$BJ$9,IF(B13<=70,$BJ$10,$BJ$11)))))))*'Retirement Dashboard'!$C$12,0) -> 6164.34 | H13: =K12-C13-D13-E13-F13+G13 -> 79239.98 | I13: =$AL$8*H13 -> 3169.5992 | J13: =IF(I13+H13-$AL$35>0,I13+H13-$AL$35,0) -> 6909.5791 | K13: =H13+I13-J13 -> 75500 | M13: =IF(J13>=0,J13,0) -> 6909.5791 | N13: =IF(B13<$BH$31,IF(B14<=35,$BI$4,IF(B14<=45,$BI$5,IF(B14<=50,$BI$6,IF(B14<=55,$BI$7,IF(B14<=60,$BI$8,IF(B14<=65,$BI$9,IF(B14<=70,$BI$10,$BI$11)))))))*'Retirement Dashboard'!$C$12,0) -> 4784.976 | O13: =R12+N13+M13 -> 172768.01 | P13: =IF(B13<=55,$AL$5,$AN$6)*(IF(O13>=40000,40000,O13)) -> 2400 | Q13: =$AN$7*IF(O13>=40000,O13-40000,0) -> 6638.4003 | R13: =O13+P13+Q13 -> 181806.41 | T13: =IF(B13<$BH$31,IF(B13<=35,$BH$4,IF(B14<=45,$BH$5,IF(B14<=50,$BH$6,IF(B14<=55,$BH$7,IF(B14<=60,$BH$8,IF(B14<=65,$BH$9,IF(B14<=70,$BH$10,$BH$11)))))))*'Retirement Dashboard'!$C$12,0) -> 2055.592 | U13: =IF(B13<($BH$57+$BH$30),$BH$56*12,0) -> 0 | V13: =IF(B13<=34,$AN$31,IF(B13<=39,$AN$32,IF(B13<=44,$AN$33,IF(B13<=49,$AN$34,IF(B13<=54,$AN$35,IF(B13<=59,$AN$36,IF(B13<=69,$AN$37,0))))))) -> 298 | W13: =Z12+T13-U13-V13 -> 89131.491 | X13: =IF(B13<=55,$AL$3,$AN$3)*(IF(W13>=20000,20000,W13)) -> 1200 | Y13: =$AL$4*IF(W13>=20000,W13-20000,W13) -> 1728.2873 | Z13: =W13+X13+Y13 -> 92059.779 | AK13: Age | AL13: Medishield | AM13: Private Shield CPF Limit | AR13: =AR12+1 -> 35 | AS13: =AS12+1 -> 2033 | AT13: =(AT12*103.5%) -> 140217.38 | AU13: =AU12*103.5% -> 280516.07 | AV13: =AV12*103.5% -> 561032.13 | AW13: =AW12+30 -> 1070 | AX13: =AX12+60 -> 2020 | AY13: =AY12*103.31% -> 4316.0108 | BA13: 38 | BB13: =(100%+$BB$3)*BB12 -> 296.42982 | BC13: =(100%+$BB$3)*BC12 -> 241.36183 | BD13: =(100%+$BD$3)*BD12 -> 775.63851
B14: =B13+1 -> 61 | C14: =IF(B14>=67,$BI$55,C13+(1.0244%*C13)) -> 428.70724 | D14: =IF(B14<=20,$AL$14,IF(B14<=30,$AL$15,IF(B14<=40,$AL$16,IF(B14<=50,$AL$17,IF(B14<=60,$AL$18,IF(B14<=65,$AL$19,IF(B14<=70,$AL$20, IF(B14<=73,$AL$21,IF(B14<=75,$AL$22,IF(B14<=78,$AL$23,IF(B14<=80,$AL$24,IF(B14<=83,$AL$25,IF(B14<=85,$AL$26,IF(B14<=90,$AL$27,$AL$28)))))))))))))) -> 1020 | E14: =IF(B14<=20,$AM$14,IF(B14<=30,$AM$15,IF(B14<=40,$AM$16,IF(B14<=50,$AM$17,IF(B14<=60,$AM$18,IF(B14<=65,$AM$19,IF(B14<=70,$AM$20, IF(B14<=73,$AM$21,IF(B14<=75,$AM$22,IF(B14<=78,$AM$23,IF(B14<=80,$AM$24,IF(B14<=83,$AM$25,IF(B14<=85,$AM$26,IF(B14<=90,$AM$27,$AM$28)))))))))))))) -> 600 | F14: =IF(AND('Retirement Dashboard'!$C$42="Yes", B14<= 'Retirement Dashboard'!$E$42), 600, 0) -> 600 | G14: =IF(B14<'Retirement Dashboard'!$E$6,IF(B14<=35,$BJ$4,IF(B14<=45,$BJ$5,IF(B14<=50,$BJ$6,IF(B14<=55,$BJ$7,IF(B14<=60,$BJ$8,IF(B14<=65,$BJ$9,IF(B14<=70,$BJ$10,$BJ$11)))))))*'Retirement Dashboard'!$C$12,0) -> 6279.952 | H14: =K13-C14-D14-E14-F14+G14 -> 79131.245 | I14: =$AL$8*H14 -> 3165.2498 | J14: =IF(I14+H14-$AL$35>0,I14+H14-$AL$35,0) -> 6796.4946 | K14: =H14+I14-J14 -> 75500 | M14: =IF(J14>=0,J14,0) -> 6796.4946 | N14: =IF(B14<$BH$31,IF(B15<=35,$BI$4,IF(B15<=45,$BI$5,IF(B15<=50,$BI$6,IF(B15<=55,$BI$7,IF(B15<=60,$BI$8,IF(B15<=65,$BI$9,IF(B15<=70,$BI$10,$BI$11)))))))*'Retirement Dashboard'!$C$12,0) -> 4784.976 | O14: =R13+N14+M14 -> 193387.88 | P14: =IF(B14<=55,$AL$5,$AN$6)*(IF(O14>=40000,40000,O14)) -> 2400 | Q14: =$AN$7*IF(O14>=40000,O14-40000,0) -> 7669.3939 | R14: =O14+P14+Q14 -> 203457.27 | T14: =IF(B14<$BH$31,IF(B14<=35,$BH$4,IF(B15<=45,$BH$5,IF(B15<=50,$BH$6,IF(B15<=55,$BH$7,IF(B15<=60,$BH$8,IF(B15<=65,$BH$9,IF(B15<=70,$BH$10,$BH$11)))))))*'Retirement Dashboard'!$C$12,0) -> 2055.592 | U14: =IF(B14<($BH$57+$BH$30),$BH$56*12,0) -> 0 | V14: =IF(B14<=34,$AN$31,IF(B14<=39,$AN$32,IF(B14<=44,$AN$33,IF(B14<=49,$AN$34,IF(B14<=54,$AN$35,IF(B14<=59,$AN$36,IF(B14<=69,$AN$37,0))))))) -> 298 | W14: =Z13+T14-U14-V14 -> 93817.371 | X14: =IF(B14<=55,$AL$3,$AN$3)*(IF(W14>=20000,20000,W14)) -> 1200 | Y14: =$AL$4*IF(W14>=20000,W14-20000,W14) -> 1845.4343 | Z14: =W14+X14+Y14 -> 96862.805 | AK14: <=20 | AL14: 145 | AM14: 300 | AR14: =AR13+1 -> 36 | AS14: =AS13+1 -> 2034 | AT14: =(AT13*103.5%) -> 145124.99 | AU14: =AU13*103.5% -> 290334.13 | AV14: =AV13*103.5% -> 580668.26 | AW14: =AW13+30 -> 1100 | AX14: =AX13+60 -> 2080 | AY14: =AY13*103.31% -> 4458.8708 | BA14: 39 | BB14: =(100%+$BB$3)*BB13 -> 302.35842 | BC14: =(100%+$BB$3)*BC13 -> 246.18907 | BD14: =(100%+$BD$3)*BD13 -> 791.15128
B15: =B14+1 -> 62 | C15: =IF(B15>=67,$BI$55,C14+(1.0244%*C14)) -> 433.09892 | D15: =IF(B15<=20,$AL$14,IF(B15<=30,$AL$15,IF(B15<=40,$AL$16,IF(B15<=50,$AL$17,IF(B15<=60,$AL$18,IF(B15<=65,$AL$19,IF(B15<=70,$AL$20, IF(B15<=73,$AL$21,IF(B15<=75,$AL$22,IF(B15<=78,$AL$23,IF(B15<=80,$AL$24,IF(B15<=83,$AL$25,IF(B15<=85,$AL$26,IF(B15<=90,$AL$27,$AL$28)))))))))))))) -> 1020 | E15: =IF(B15<=20,$AM$14,IF(B15<=30,$AM$15,IF(B15<=40,$AM$16,IF(B15<=50,$AM$17,IF(B15<=60,$AM$18,IF(B15<=65,$AM$19,IF(B15<=70,$AM$20, IF(B15<=73,$AM$21,IF(B15<=75,$AM$22,IF(B15<=78,$AM$23,IF(B15<=80,$AM$24,IF(B15<=83,$AM$25,IF(B15<=85,$AM$26,IF(B15<=90,$AM$27,$AM$28)))))))))))))) -> 600 | F15: =IF(AND('Retirement Dashboard'!$C$42="Yes", B15<= 'Retirement Dashboard'!$E$42), 600, 0) -> 600 | G15: =IF(B15<'Retirement Dashboard'!$E$6,IF(B15<=35,$BJ$4,IF(B15<=45,$BJ$5,IF(B15<=50,$BJ$6,IF(B15<=55,$BJ$7,IF(B15<=60,$BJ$8,IF(B15<=65,$BJ$9,IF(B15<=70,$BJ$10,$BJ$11)))))))*'Retirement Dashboard'!$C$12,0) -> 6279.952 | H15: =K14-C15-D15-E15-F15+G15 -> 79126.853 | I15: =$AL$8*H15 -> 3165.0741 | J15: =IF(I15+H15-$AL$35>0,I15+H15-$AL$35,0) -> 6791.9272 | K15: =H15+I15-J15 -> 75500 | M15: =IF(J15>=0,J15,0) -> 6791.9272 | N15: =IF(B15<$BH$31,IF(B16<=35,$BI$4,IF(B16<=45,$BI$5,IF(B16<=50,$BI$6,IF(B16<=55,$BI$7,IF(B16<=60,$BI$8,IF(B16<=65,$BI$9,IF(B16<=70,$BI$10,$BI$11)))))))*'Retirement Dashboard'!$C$12,0) -> 4784.976 | O15: =R14+N15+M15 -> 215034.17 | P15: =IF(B15<=55,$AL$5,$AN$6)*(IF(O15>=40000,40000,O15)) -> 2400 | Q15: =$AN$7*IF(O15>=40000,O15-40000,0) -> 8751.7087 | R15: =O15+P15+Q15 -> 226185.88 | T15: =IF(B15<$BH$31,IF(B15<=35,$BH$4,IF(B16<=45,$BH$5,IF(B16<=50,$BH$6,IF(B16<=55,$BH$7,IF(B16<=60,$BH$8,IF(B16<=65,$BH$9,IF(B16<=70,$BH$10,$BH$11)))))))*'Retirement Dashboard'!$C$12,0) -> 2055.592 | U15: =IF(B15<($BH$57+$BH$30),$BH$56*12,0) -> 0 | V15: =IF(B15<=34,$AN$31,IF(B15<=39,$AN$32,IF(B15<=44,$AN$33,IF(B15<=49,$AN$34,IF(B15<=54,$AN$35,IF(B15<=59,$AN$36,IF(B15<=69,$AN$37,0))))))) -> 298 | W15: =Z14+T15-U15-V15 -> 98620.397 | X15: =IF(B15<=55,$AL$3,$AN$3)*(IF(W15>=20000,20000,W15)) -> 1200 | Y15: =$AL$4*IF(W15>=20000,W15-20000,W15) -> 1965.5099 | Z15: =W15+X15+Y15 -> 101785.91 | AK15: <=30 | AL15: 250 | AM15: 300 | AR15: =AR14+1 -> 37 | AS15: =AS14+1 -> 2035 | AT15: =(AT14*103.5%) -> 150204.36 | AU15: =AU14*103.5% -> 300495.82 | AV15: =AV14*103.5% -> 600991.64 | AW15: =AW14+30 -> 1130 | AX15: =AX14+60 -> 2140 | AY15: =AY14*103.31% -> 4606.4594 | BA15: 40 | BB15: =(100%+$BB$3)*BB14 -> 308.40559 | BC15: =(100%+$BB$3)*BC14 -> 251.11285 | BD15: =(100%+$BD$3)*BD14 -> 806.97431
B16: =B15+1 -> 63 | C16: =IF(B16>=67,$BI$55,C15+(1.0244%*C15)) -> 437.53558 | D16: =IF(B16<=20,$AL$14,IF(B16<=30,$AL$15,IF(B16<=40,$AL$16,IF(B16<=50,$AL$17,IF(B16<=60,$AL$18,IF(B16<=65,$AL$19,IF(B16<=70,$AL$20, IF(B16<=73,$AL$21,IF(B16<=75,$AL$22,IF(B16<=78,$AL$23,IF(B16<=80,$AL$24,IF(B16<=83,$AL$25,IF(B16<=85,$AL$26,IF(B16<=90,$AL$27,$AL$28)))))))))))))) -> 1020 | E16: =IF(B16<=20,$AM$14,IF(B16<=30,$AM$15,IF(B16<=40,$AM$16,IF(B16<=50,$AM$17,IF(B16<=60,$AM$18,IF(B16<=65,$AM$19,IF(B16<=70,$AM$20, IF(B16<=73,$AM$21,IF(B16<=75,$AM$22,IF(B16<=78,$AM$23,IF(B16<=80,$AM$24,IF(B16<=83,$AM$25,IF(B16<=85,$AM$26,IF(B16<=90,$AM$27,$AM$28)))))))))))))) -> 600 | F16: =IF(AND('Retirement Dashboard'!$C$42="Yes", B16<= 'Retirement Dashboard'!$E$42), 600, 0) -> 600 | G16: =IF(B16<'Retirement Dashboard'!$E$6,IF(B16<=35,$BJ$4,IF(B16<=45,$BJ$5,IF(B16<=50,$BJ$6,IF(B16<=55,$BJ$7,IF(B16<=60,$BJ$8,IF(B16<=65,$BJ$9,IF(B16<=70,$BJ$10,$BJ$11)))))))*'Retirement Dashboard'!$C$12,0) -> 6279.952 | H16: =K15-C16-D16-E16-F16+G16 -> 79122.416 | I16: =$AL$8*H16 -> 3164.8967 | J16: =IF(I16+H16-$AL$35>0,I16+H16-$AL$35,0) -> 6787.3131 | K16: =H16+I16-J16 -> 75500 | M16: =IF(J16>=0,J16,0) -> 6787.3131 | N16: =IF(B16<$BH$31,IF(B17<=35,$BI$4,IF(B17<=45,$BI$5,IF(B17<=50,$BI$6,IF(B17<=55,$BI$7,IF(B17<=60,$BI$8,IF(B17<=65,$BI$9,IF(B17<=70,$BI$10,$BI$11)))))))*'Retirement Dashboard'!$C$12,0) -> 4784.976 | O16: =R15+N16+M16 -> 237758.17 | P16: =IF(B16<=55,$AL$5,$AN$6)*(IF(O16>=40000,40000,O16)) -> 2400 | Q16: =$AN$7*IF(O16>=40000,O16-40000,0) -> 9887.9086 | R16: =O16+P16+Q16 -> 250046.08 | T16: =IF(B16<$BH$31,IF(B16<=35,$BH$4,IF(B17<=45,$BH$5,IF(B17<=50,$BH$6,IF(B17<=55,$BH$7,IF(B17<=60,$BH$8,IF(B17<=65,$BH$9,IF(B17<=70,$BH$10,$BH$11)))))))*'Retirement Dashboard'!$C$12,0) -> 2055.592 | U16: =IF(B16<($BH$57+$BH$30),$BH$56*12,0) -> 0 | V16: =IF(B16<=34,$AN$31,IF(B16<=39,$AN$32,IF(B16<=44,$AN$33,IF(B16<=49,$AN$34,IF(B16<=54,$AN$35,IF(B16<=59,$AN$36,IF(B16<=69,$AN$37,0))))))) -> 298 | W16: =Z15+T16-U16-V16 -> 103543.5 | X16: =IF(B16<=55,$AL$3,$AN$3)*(IF(W16>=20000,20000,W16)) -> 1200 | Y16: =$AL$4*IF(W16>=20000,W16-20000,W16) -> 2088.5875 | Z16: =W16+X16+Y16 -> 106832.09 | AK16: <=40 | AL16: 390 | AM16: 300 | AR16: =AR15+1 -> 38 | AS16: =AS15+1 -> 2036 | AT16: =(AT15*103.5%) -> 155461.51 | AU16: =AU15*103.5% -> 311013.18 | AV16: =AV15*103.5% -> 622026.35 | AW16: =AW15+30 -> 1160 | AX16: =AX15+60 -> 2200 | AY16: =AY15*103.31% -> 4758.9332 | BA16: 41 | BB16: =(100%+$BB$3)*BB15 -> 314.5737 | BC16: =(100%+$BB$3)*BC15 -> 256.13511 | BD16: =(100%+$BD$3)*BD15 -> 823.11379
B17: =B16+1 -> 64 | C17: =IF(B17>=67,$BI$55,C16+(1.0244%*C16)) -> 442.0177 | D17: =IF(B17<=20,$AL$14,IF(B17<=30,$AL$15,IF(B17<=40,$AL$16,IF(B17<=50,$AL$17,IF(B17<=60,$AL$18,IF(B17<=65,$AL$19,IF(B17<=70,$AL$20, IF(B17<=73,$AL$21,IF(B17<=75,$AL$22,IF(B17<=78,$AL$23,IF(B17<=80,$AL$24,IF(B17<=83,$AL$25,IF(B17<=85,$AL$26,IF(B17<=90,$AL$27,$AL$28)))))))))))))) -> 1020 | E17: =IF(B17<=20,$AM$14,IF(B17<=30,$AM$15,IF(B17<=40,$AM$16,IF(B17<=50,$AM$17,IF(B17<=60,$AM$18,IF(B17<=65,$AM$19,IF(B17<=70,$AM$20, IF(B17<=73,$AM$21,IF(B17<=75,$AM$22,IF(B17<=78,$AM$23,IF(B17<=80,$AM$24,IF(B17<=83,$AM$25,IF(B17<=85,$AM$26,IF(B17<=90,$AM$27,$AM$28)))))))))))))) -> 600 | F17: =IF(AND('Retirement Dashboard'!$C$42="Yes", B17<= 'Retirement Dashboard'!$E$42), 600, 0) -> 600 | G17: =IF(B17<'Retirement Dashboard'!$E$6,IF(B17<=35,$BJ$4,IF(B17<=45,$BJ$5,IF(B17<=50,$BJ$6,IF(B17<=55,$BJ$7,IF(B17<=60,$BJ$8,IF(B17<=65,$BJ$9,IF(B17<=70,$BJ$10,$BJ$11)))))))*'Retirement Dashboard'!$C$12,0) -> 6279.952 | H17: =K16-C17-D17-E17-F17+G17 -> 79117.934 | I17: =$AL$8*H17 -> 3164.7174 | J17: =IF(I17+H17-$AL$35>0,I17+H17-$AL$35,0) -> 6782.6517 | K17: =H17+I17-J17 -> 75500 | M17: =IF(J17>=0,J17,0) -> 6782.6517 | N17: =IF(B17<$BH$31,IF(B18<=35,$BI$4,IF(B18<=45,$BI$5,IF(B18<=50,$BI$6,IF(B18<=55,$BI$7,IF(B18<=60,$BI$8,IF(B18<=65,$BI$9,IF(B18<=70,$BI$10,$BI$11)))))))*'Retirement Dashboard'!$C$12,0) -> 4784.976 | O17: =R16+N17+M17 -> 261613.71 | P17: =IF(B17<=55,$AL$5,$AN$6)*(IF(O17>=40000,40000,O17)) -> 2400 | Q17: =$AN$7*IF(O17>=40000,O17-40000,0) -> 11080.685 | R17: =O17+P17+Q17 -> 275094.39 | T17: =IF(B17<$BH$31,IF(B17<=35,$BH$4,IF(B18<=45,$BH$5,IF(B18<=50,$BH$6,IF(B18<=55,$BH$7,IF(B18<=60,$BH$8,IF(B18<=65,$BH$9,IF(B18<=70,$BH$10,$BH$11)))))))*'Retirement Dashboard'!$C$12,0) -> 2055.592 | U17: =IF(B17<($BH$57+$BH$30),$BH$56*12,0) -> 0 | V17: =IF(B17<=34,$AN$31,IF(B17<=39,$AN$32,IF(B17<=44,$AN$33,IF(B17<=49,$AN$34,IF(B17<=54,$AN$35,IF(B17<=59,$AN$36,IF(B17<=69,$AN$37,0))))))) -> 298 | W17: =Z16+T17-U17-V17 -> 108589.68 | X17: =IF(B17<=55,$AL$3,$AN$3)*(IF(W17>=20000,20000,W17)) -> 1200 | Y17: =$AL$4*IF(W17>=20000,W17-20000,W17) -> 2214.742 | Z17: =W17+X17+Y17 -> 112004.42 | AK17: <=50 | AL17: 525 | AM17: 600 | AR17: =AR16+1 -> 39 | AS17: =AS16+1 -> 2037 | AT17: =(AT16*103.5%) -> 160902.67 | AU17: =AU16*103.5% -> 321898.64 | AV17: =AV16*103.5% -> 643797.27 | AW17: =AW16+30 -> 1190 | AX17: =AX16+60 -> 2260 | AY17: =AY16*103.31% -> 4916.4539 | BA17: 42 | BB17: =(100%+$BB$3)*BB16 -> 320.86517 | BC17: =(100%+$BB$3)*BC16 -> 261.25781 | BD17: =(100%+$BD$3)*BD16 -> 839.57607
B18: =B17+1 -> 65 | C18: =IF(B18>=67,$BI$55,C17+(1.0244%*C17)) -> 446.54573 | D18: =IF(B18<=20,$AL$14,IF(B18<=30,$AL$15,IF(B18<=40,$AL$16,IF(B18<=50,$AL$17,IF(B18<=60,$AL$18,IF(B18<=65,$AL$19,IF(B18<=70,$AL$20, IF(B18<=73,$AL$21,IF(B18<=75,$AL$22,IF(B18<=78,$AL$23,IF(B18<=80,$AL$24,IF(B18<=83,$AL$25,IF(B18<=85,$AL$26,IF(B18<=90,$AL$27,$AL$28)))))))))))))) -> 1020 | E18: =IF(B18<=20,$AM$14,IF(B18<=30,$AM$15,IF(B18<=40,$AM$16,IF(B18<=50,$AM$17,IF(B18<=60,$AM$18,IF(B18<=65,$AM$19,IF(B18<=70,$AM$20, IF(B18<=73,$AM$21,IF(B18<=75,$AM$22,IF(B18<=78,$AM$23,IF(B18<=80,$AM$24,IF(B18<=83,$AM$25,IF(B18<=85,$AM$26,IF(B18<=90,$AM$27,$AM$28)))))))))))))) -> 600 | F18: =IF(AND('Retirement Dashboard'!$C$42="Yes", B18<= 'Retirement Dashboard'!$E$42), 600, 0) -> 600 | G18: =IF(B18<'Retirement Dashboard'!$E$6,IF(B18<=35,$BJ$4,IF(B18<=45,$BJ$5,IF(B18<=50,$BJ$6,IF(B18<=55,$BJ$7,IF(B18<=60,$BJ$8,IF(B18<=65,$BJ$9,IF(B18<=70,$BJ$10,$BJ$11)))))))*'Retirement Dashboard'!$C$12,0) -> 0 | H18: =K17-C18-D18-E18-F18+G18 -> 72833.454 | I18: =$AL$8*H18 -> 2913.3382 | J18: =IF(I18+H18-$AL$35>0,I18+H18-$AL$35,0) -> 246.79244 | K18: =H18+I18-J18 -> 75500 | M18: =IF(J18>=0,J18,0) -> 246.79244 | N18: =IF(B18<$BH$31,IF(B19<=35,$BI$4,IF(B19<=45,$BI$5,IF(B19<=50,$BI$6,IF(B19<=55,$BI$7,IF(B19<=60,$BI$8,IF(B19<=65,$BI$9,IF(B19<=70,$BI$10,$BI$11)))))))*'Retirement Dashboard'!$C$12,0) -> 0 | O18: =R17+N18+M18 -> 275341.19 | P18: =IF(B18<=55,$AL$5,$AN$6)*(IF(O18>=40000,40000,O18)) -> 2400 | Q18: =$AN$7*IF(O18>=40000,O18-40000,0) -> 11767.059 | R18: =O18+P18+Q18 -> 289508.25 | T18: =IF(B18<$BH$31,IF(B18<=35,$BH$4,IF(B19<=45,$BH$5,IF(B19<=50,$BH$6,IF(B19<=55,$BH$7,IF(B19<=60,$BH$8,IF(B19<=65,$BH$9,IF(B19<=70,$BH$10,$BH$11)))))))*'Retirement Dashboard'!$C$12,0) -> 0 | U18: =IF(B18<($BH$57+$BH$30),$BH$56*12,0) -> 0 | V18: =IF(B18<=34,$AN$31,IF(B18<=39,$AN$32,IF(B18<=44,$AN$33,IF(B18<=49,$AN$34,IF(B18<=54,$AN$35,IF(B18<=59,$AN$36,IF(B18<=69,$AN$37,0))))))) -> 298 | W18: =Z17+T18-U18-V18 -> 111706.42 | X18: =IF(B18<=55,$AL$3,$AN$3)*(IF(W18>=20000,20000,W18)) -> 1200 | Y18: =$AL$4*IF(W18>=20000,W18-20000,W18) -> 2292.6605 | Z18: =W18+X18+Y18 -> 115199.08 | AK18: <=60 | AL18: 800 | AM18: 600 | AR18: =AR17+1 -> 40 | AS18: =AS17+1 -> 2038 | AT18: =(AT17*103.5%) -> 166534.26 | AU18: =AU17*103.5% -> 333165.09 | AV18: =AV17*103.5% -> 666330.18 | AW18: =AW17+30 -> 1220 | AX18: =AX17+60 -> 2320 | AY18: =AY17*103.31% -> 5079.1885 | BA18: 43 | BB18: =(100%+$BB$3)*BB17 -> 327.28248 | BC18: =(100%+$BB$3)*BC17 -> 266.48297 | BD18: =(100%+$BD$3)*BD17 -> 856.36759
B19: =B18+1 -> 66 | C19: =IF(B19>=67,$BI$55,C18+(1.0244%*C18)) -> 451.12014 | D19: =IF(B19<=20,$AL$14,IF(B19<=30,$AL$15,IF(B19<=40,$AL$16,IF(B19<=50,$AL$17,IF(B19<=60,$AL$18,IF(B19<=65,$AL$19,IF(B19<=70,$AL$20, IF(B19<=73,$AL$21,IF(B19<=75,$AL$22,IF(B19<=78,$AL$23,IF(B19<=80,$AL$24,IF(B19<=83,$AL$25,IF(B19<=85,$AL$26,IF(B19<=90,$AL$27,$AL$28)))))))))))))) -> 1100 | E19: =IF(B19<=20,$AM$14,IF(B19<=30,$AM$15,IF(B19<=40,$AM$16,IF(B19<=50,$AM$17,IF(B19<=60,$AM$18,IF(B19<=65,$AM$19,IF(B19<=70,$AM$20, IF(B19<=73,$AM$21,IF(B19<=75,$AM$22,IF(B19<=78,$AM$23,IF(B19<=80,$AM$24,IF(B19<=83,$AM$25,IF(B19<=85,$AM$26,IF(B19<=90,$AM$27,$AM$28)))))))))))))) -> 600 | F19: =IF(AND('Retirement Dashboard'!$C$42="Yes", B19<= 'Retirement Dashboard'!$E$42), 600, 0) -> 600 | G19: =IF(B19<'Retirement Dashboard'!$E$6,IF(B19<=35,$BJ$4,IF(B19<=45,$BJ$5,IF(B19<=50,$BJ$6,IF(B19<=55,$BJ$7,IF(B19<=60,$BJ$8,IF(B19<=65,$BJ$9,IF(B19<=70,$BJ$10,$BJ$11)))))))*'Retirement Dashboard'!$C$12,0) -> 0 | H19: =K18-C19-D19-E19-F19+G19 -> 72748.88 | I19: =$AL$8*H19 -> 2909.9552 | J19: =IF(I19+H19-$AL$35>0,I19+H19-$AL$35,0) -> 158.83505 | K19: =H19+I19-J19 -> 75500 | M19: =IF(J19>=0,J19,0) -> 158.83505 | N19: =IF(B19<$BH$31,IF(B20<=35,$BI$4,IF(B20<=45,$BI$5,IF(B20<=50,$BI$6,IF(B20<=55,$BI$7,IF(B20<=60,$BI$8,IF(B20<=65,$BI$9,IF(B20<=70,$BI$10,$BI$11)))))))*'Retirement Dashboard'!$C$12,0) -> 0 | O19: =R18+N19+M19 -> 289667.08 | P19: =IF(B19<=55,$AL$5,$AN$6)*(IF(O19>=40000,40000,O19)) -> 2400 | Q19: =$AN$7*IF(O19>=40000,O19-40000,0) -> 12483.354 | R19: =O19+P19+Q19 -> 304550.44 | T19: =IF(B19<$BH$31,IF(B19<=35,$BH$4,IF(B20<=45,$BH$5,IF(B20<=50,$BH$6,IF(B20<=55,$BH$7,IF(B20<=60,$BH$8,IF(B20<=65,$BH$9,IF(B20<=70,$BH$10,$BH$11)))))))*'Retirement Dashboard'!$C$12,0) -> 0 | U19: =IF(B19<($BH$57+$BH$30),$BH$56*12,0) -> 0 | V19: =IF(B19<=34,$AN$31,IF(B19<=39,$AN$32,IF(B19<=44,$AN$33,IF(B19<=49,$AN$34,IF(B19<=54,$AN$35,IF(B19<=59,$AN$36,IF(B19<=69,$AN$37,0))))))) -> 298 | W19: =Z18+T19-U19-V19 -> 114901.08 | X19: =IF(B19<=55,$AL$3,$AN$3)*(IF(W19>=20000,20000,W19)) -> 1200 | Y19: =$AL$4*IF(W19>=20000,W19-20000,W19) -> 2372.527 | Z19: =W19+X19+Y19 -> 118473.61 | AK19: <=65 | AL19: 1020 | AM19: 600 | AR19: =AR18+1 -> 41 | AS19: =AS18+1 -> 2039 | AT19: =(AT18*103.5%) -> 172362.96 | AU19: =AU18*103.5% -> 344825.87 | AV19: =AV18*103.5% -> 689651.74 | AW19: =AW18+30 -> 1250 | AX19: =AX18+60 -> 2380 | AY19: =AY18*103.31% -> 5247.3096 | BA19: 44 | BB19: =(100%+$BB$3)*BB18 -> 333.82813 | BC19: =(100%+$BB$3)*BC18 -> 271.81263 | BD19: =(100%+$BD$3)*BD18 -> 873.49494
B20: =B19+1 -> 67 | C20: =IF(B20>=67,$BI$55,C19+(1.0244%*C19)) -> 0 | D20: =IF(B20<=20,$AL$14,IF(B20<=30,$AL$15,IF(B20<=40,$AL$16,IF(B20<=50,$AL$17,IF(B20<=60,$AL$18,IF(B20<=65,$AL$19,IF(B20<=70,$AL$20, IF(B20<=73,$AL$21,IF(B20<=75,$AL$22,IF(B20<=78,$AL$23,IF(B20<=80,$AL$24,IF(B20<=83,$AL$25,IF(B20<=85,$AL$26,IF(B20<=90,$AL$27,$AL$28)))))))))))))) -> 1100 | E20: =IF(B20<=20,$AM$14,IF(B20<=30,$AM$15,IF(B20<=40,$AM$16,IF(B20<=50,$AM$17,IF(B20<=60,$AM$18,IF(B20<=65,$AM$19,IF(B20<=70,$AM$20, IF(B20<=73,$AM$21,IF(B20<=75,$AM$22,IF(B20<=78,$AM$23,IF(B20<=80,$AM$24,IF(B20<=83,$AM$25,IF(B20<=85,$AM$26,IF(B20<=90,$AM$27,$AM$28)))))))))))))) -> 600 | F20: =IF(AND('Retirement Dashboard'!$C$42="Yes", B20<= 'Retirement Dashboard'!$E$42), 600, 0) -> 600 | G20: =IF(B20<'Retirement Dashboard'!$E$6,IF(B20<=35,$BJ$4,IF(B20<=45,$BJ$5,IF(B20<=50,$BJ$6,IF(B20<=55,$BJ$7,IF(B20<=60,$BJ$8,IF(B20<=65,$BJ$9,IF(B20<=70,$BJ$10,$BJ$11)))))))*'Retirement Dashboard'!$C$12,0) -> 0 | H20: =K19-C20-D20-E20-F20+G20 -> 73200 | I20: =$AL$8*H20 -> 2928 | J20: =IF(I20+H20-$AL$35>0,I20+H20-$AL$35,0) -> 628 | K20: =H20+I20-J20 -> 75500 | M20: =IF(J20>=0,J20,0) -> 628 | N20: =IF(B20<$BH$31,IF(B21<=35,$BI$4,IF(B21<=45,$BI$5,IF(B21<=50,$BI$6,IF(B21<=55,$BI$7,IF(B21<=60,$BI$8,IF(B21<=65,$BI$9,IF(B21<=70,$BI$10,$BI$11)))))))*'Retirement Dashboard'!$C$12,0) -> 0 | O20: =R19+N20+M20 -> 305178.44 | P20: =IF(B20<=55,$AL$5,$AN$6)*(IF(O20>=40000,40000,O20)) -> 2400 | Q20: =$AN$7*IF(O20>=40000,O20-40000,0) -> 13258.922 | R20: =O20+P20+Q20 -> 320837.36 | T20: =IF(B20<$BH$31,IF(B20<=35,$BH$4,IF(B21<=45,$BH$5,IF(B21<=50,$BH$6,IF(B21<=55,$BH$7,IF(B21<=60,$BH$8,IF(B21<=65,$BH$9,IF(B21<=70,$BH$10,$BH$11)))))))*'Retirement Dashboard'!$C$12,0) -> 0 | U20: =IF(B20<($BH$57+$BH$30),$BH$56*12,0) -> 0 | V20: =IF(B20<=34,$AN$31,IF(B20<=39,$AN$32,IF(B20<=44,$AN$33,IF(B20<=49,$AN$34,IF(B20<=54,$AN$35,IF(B20<=59,$AN$36,IF(B20<=69,$AN$37,0))))))) -> 298 | W20: =Z19+T20-U20-V20 -> 118175.61 | X20: =IF(B20<=55,$AL$3,$AN$3)*(IF(W20>=20000,20000,W20)) -> 1200 | Y20: =$AL$4*IF(W20>=20000,W20-20000,W20) -> 2454.3902 | Z20: =W20+X20+Y20 -> 121830 | AK20: <=70 | AL20: 1100 | AM20: 600 | AR20: =AR19+1 -> 42 | AS20: =AS19+1 -> 2040 | AT20: =(AT19*103.5%) -> 178395.66 | AU20: =AU19*103.5% -> 356894.77 | AV20: =AV19*103.5% -> 713789.55 | AW20: =AW19+30 -> 1280 | AX20: =AX19+60 -> 2440 | AY20: =AY19*103.31% -> 5420.9956 | BA20: 45 | BB20: =(100%+$BB$3)*BB19 -> 340.50469 | BC20: =(100%+$BB$3)*BC19 -> 277.24888 | BD20: =(100%+$BD$3)*BD19 -> 890.96484
B21: =B20+1 -> 68 | C21: =IF(B21>=67,$BI$55,C20+(1.0244%*C20)) -> 0 | D21: =IF(B21<=20,$AL$14,IF(B21<=30,$AL$15,IF(B21<=40,$AL$16,IF(B21<=50,$AL$17,IF(B21<=60,$AL$18,IF(B21<=65,$AL$19,IF(B21<=70,$AL$20, IF(B21<=73,$AL$21,IF(B21<=75,$AL$22,IF(B21<=78,$AL$23,IF(B21<=80,$AL$24,IF(B21<=83,$AL$25,IF(B21<=85,$AL$26,IF(B21<=90,$AL$27,$AL$28)))))))))))))) -> 1100 | E21: =IF(B21<=20,$AM$14,IF(B21<=30,$AM$15,IF(B21<=40,$AM$16,IF(B21<=50,$AM$17,IF(B21<=60,$AM$18,IF(B21<=65,$AM$19,IF(B21<=70,$AM$20, IF(B21<=73,$AM$21,IF(B21<=75,$AM$22,IF(B21<=78,$AM$23,IF(B21<=80,$AM$24,IF(B21<=83,$AM$25,IF(B21<=85,$AM$26,IF(B21<=90,$AM$27,$AM$28)))))))))))))) -> 600 | F21: =IF(AND('Retirement Dashboard'!$C$42="Yes", B21<= 'Retirement Dashboard'!$E$42), 600, 0) -> 0 | G21: =IF(B21<'Retirement Dashboard'!$E$6,IF(B21<=35,$BJ$4,IF(B21<=45,$BJ$5,IF(B21<=50,$BJ$6,IF(B21<=55,$BJ$7,IF(B21<=60,$BJ$8,IF(B21<=65,$BJ$9,IF(B21<=70,$BJ$10,$BJ$11)))))))*'Retirement Dashboard'!$C$12,0) -> 0 | H21: =K20-C21-D21-E21-F21+G21 -> 73800 | I21: =$AL$8*H21 -> 2952 | J21: =IF(I21+H21-$AL$35>0,I21+H21-$AL$35,0) -> 1252 | K21: =H21+I21-J21 -> 75500 | M21: =IF(J21>=0,J21,0) -> 1252 | N21: =IF(B21<$BH$31,IF(B22<=35,$BI$4,IF(B22<=45,$BI$5,IF(B22<=50,$BI$6,IF(B22<=55,$BI$7,IF(B22<=60,$BI$8,IF(B22<=65,$BI$9,IF(B22<=70,$BI$10,$BI$11)))))))*'Retirement Dashboard'!$C$12,0) -> 0 | O21: =R20+N21+M21 -> 322089.36 | P21: =IF(B21<=55,$AL$5,$AN$6)*(IF(O21>=40000,40000,O21)) -> 2400 | Q21: =$AN$7*IF(O21>=40000,O21-40000,0) -> 14104.468 | R21: =O21+P21+Q21 -> 338593.82 | T21: =IF(B21<$BH$31,IF(B21<=35,$BH$4,IF(B22<=45,$BH$5,IF(B22<=50,$BH$6,IF(B22<=55,$BH$7,IF(B22<=60,$BH$8,IF(B22<=65,$BH$9,IF(B22<=70,$BH$10,$BH$11)))))))*'Retirement Dashboard'!$C$12,0) -> 0 | U21: =IF(B21<($BH$57+$BH$30),$BH$56*12,0) -> 0 | V21: =IF(B21<=34,$AN$31,IF(B21<=39,$AN$32,IF(B21<=44,$AN$33,IF(B21<=49,$AN$34,IF(B21<=54,$AN$35,IF(B21<=59,$AN$36,IF(B21<=69,$AN$37,0))))))) -> 298 | W21: =Z20+T21-U21-V21 -> 121532 | X21: =IF(B21<=55,$AL$3,$AN$3)*(IF(W21>=20000,20000,W21)) -> 1200 | Y21: =$AL$4*IF(W21>=20000,W21-20000,W21) -> 2538.3 | Z21: =W21+X21+Y21 -> 125270.3 | AK21: <=73 | AL21: 1195 | AM21: 900 | AR21: =AR20+1 -> 43 | AS21: =AS20+1 -> 2041 | AT21: =(AT20*103.5%) -> 184639.51 | AU21: =AU20*103.5% -> 369386.09 | AV21: =AV20*103.5% -> 738772.18 | AW21: =AW20+30 -> 1310 | AX21: =AX20+60 -> 2500 | AY21: =AY20*103.31% -> 5600.4305 | BA21: 46 | BB21: =(100%+$BB$3)*BB20 -> 347.31478 | BC21: =(100%+$BB$3)*BC20 -> 282.79386 | BD21: =(100%+$BD$3)*BD20 -> 908.78414
B22: =B21+1 -> 69 | C22: =IF(B22>=67,$BI$55,C21+(1.0244%*C21)) -> 0 | D22: =IF(B22<=20,$AL$14,IF(B22<=30,$AL$15,IF(B22<=40,$AL$16,IF(B22<=50,$AL$17,IF(B22<=60,$AL$18,IF(B22<=65,$AL$19,IF(B22<=70,$AL$20, IF(B22<=73,$AL$21,IF(B22<=75,$AL$22,IF(B22<=78,$AL$23,IF(B22<=80,$AL$24,IF(B22<=83,$AL$25,IF(B22<=85,$AL$26,IF(B22<=90,$AL$27,$AL$28)))))))))))))) -> 1100 | E22: =IF(B22<=20,$AM$14,IF(B22<=30,$AM$15,IF(B22<=40,$AM$16,IF(B22<=50,$AM$17,IF(B22<=60,$AM$18,IF(B22<=65,$AM$19,IF(B22<=70,$AM$20, IF(B22<=73,$AM$21,IF(B22<=75,$AM$22,IF(B22<=78,$AM$23,IF(B22<=80,$AM$24,IF(B22<=83,$AM$25,IF(B22<=85,$AM$26,IF(B22<=90,$AM$27,$AM$28)))))))))))))) -> 600 | F22: =IF(AND('Retirement Dashboard'!$C$42="Yes", B22<= 'Retirement Dashboard'!$E$42), 600, 0) -> 0 | G22: =IF(B22<'Retirement Dashboard'!$E$6,IF(B22<=35,$BJ$4,IF(B22<=45,$BJ$5,IF(B22<=50,$BJ$6,IF(B22<=55,$BJ$7,IF(B22<=60,$BJ$8,IF(B22<=65,$BJ$9,IF(B22<=70,$BJ$10,$BJ$11)))))))*'Retirement Dashboard'!$C$12,0) -> 0 | H22: =K21-C22-D22-E22-F22+G22 -> 73800 | I22: =$AL$8*H22 -> 2952 | J22: =IF(I22+H22-$AL$35>0,I22+H22-$AL$35,0) -> 1252 | K22: =H22+I22-J22 -> 75500 | M22: =IF(J22>=0,J22,0) -> 1252 | N22: =IF(B22<$BH$31,IF(B23<=35,$BI$4,IF(B23<=45,$BI$5,IF(B23<=50,$BI$6,IF(B23<=55,$BI$7,IF(B23<=60,$BI$8,IF(B23<=65,$BI$9,IF(B23<=70,$BI$10,$BI$11)))))))*'Retirement Dashboard'!$C$12,0) -> 0 | O22: =R21+N22+M22 -> 339845.82 | P22: =IF(B22<=55,$AL$5,$AN$6)*(IF(O22>=40000,40000,O22)) -> 2400 | Q22: =$AN$7*IF(O22>=40000,O22-40000,0) -> 14992.291 | R22: =O22+P22+Q22 -> 357238.12 | T22: =IF(B22<$BH$31,IF(B22<=35,$BH$4,IF(B23<=45,$BH$5,IF(B23<=50,$BH$6,IF(B23<=55,$BH$7,IF(B23<=60,$BH$8,IF(B23<=65,$BH$9,IF(B23<=70,$BH$10,$BH$11)))))))*'Retirement Dashboard'!$C$12,0) -> 0 | U22: =IF(B22<($BH$57+$BH$30),$BH$56*12,0) -> 0 | V22: =IF(B22<=34,$AN$31,IF(B22<=39,$AN$32,IF(B22<=44,$AN$33,IF(B22<=49,$AN$34,IF(B22<=54,$AN$35,IF(B22<=59,$AN$36,IF(B22<=69,$AN$37,0))))))) -> 298 | W22: =Z21+T22-U22-V22 -> 124972.3 | X22: =IF(B22<=55,$AL$3,$AN$3)*(IF(W22>=20000,20000,W22)) -> 1200 | Y22: =$AL$4*IF(W22>=20000,W22-20000,W22) -> 2624.3075 | Z22: =W22+X22+Y22 -> 128796.61 | AK22: <=75 | AL22: 1320 | AM22: 900 | AR22: =AR21+1 -> 44 | AS22: =AS21+1 -> 2042 | AT22: =(AT21*103.5%) -> 191101.89 | AU22: =AU21*103.5% -> 382314.6 | AV22: =AV21*103.5% -> 764629.21 | AW22: =AW21+30 -> 1340 | AX22: =AX21+60 -> 2560 | AY22: =AY21*103.31% -> 5785.8048 | BA22: 47 | BB22: =(100%+$BB$3)*BB21 -> 354.26108 | BC22: =(100%+$BB$3)*BC21 -> 288.44973 | BD22: =(100%+$BD$3)*BD21 -> 926.95982
B23: =B22+1 -> 70 | C23: =IF(B23>=67,$BI$55,C22+(1.0244%*C22)) -> 0 | D23: =IF(B23<=20,$AL$14,IF(B23<=30,$AL$15,IF(B23<=40,$AL$16,IF(B23<=50,$AL$17,IF(B23<=60,$AL$18,IF(B23<=65,$AL$19,IF(B23<=70,$AL$20, IF(B23<=73,$AL$21,IF(B23<=75,$AL$22,IF(B23<=78,$AL$23,IF(B23<=80,$AL$24,IF(B23<=83,$AL$25,IF(B23<=85,$AL$26,IF(B23<=90,$AL$27,$AL$28)))))))))))))) -> 1100 | E23: =IF(B23<=20,$AM$14,IF(B23<=30,$AM$15,IF(B23<=40,$AM$16,IF(B23<=50,$AM$17,IF(B23<=60,$AM$18,IF(B23<=65,$AM$19,IF(B23<=70,$AM$20, IF(B23<=73,$AM$21,IF(B23<=75,$AM$22,IF(B23<=78,$AM$23,IF(B23<=80,$AM$24,IF(B23<=83,$AM$25,IF(B23<=85,$AM$26,IF(B23<=90,$AM$27,$AM$28)))))))))))))) -> 600 | F23: =IF(AND('Retirement Dashboard'!$C$42="Yes", B23<= 'Retirement Dashboard'!$E$42), 600, 0) -> 0 | G23: =IF(B23<'Retirement Dashboard'!$E$6,IF(B23<=35,$BJ$4,IF(B23<=45,$BJ$5,IF(B23<=50,$BJ$6,IF(B23<=55,$BJ$7,IF(B23<=60,$BJ$8,IF(B23<=65,$BJ$9,IF(B23<=70,$BJ$10,$BJ$11)))))))*'Retirement Dashboard'!$C$12,0) -> 0 | H23: =K22-C23-D23-E23-F23+G23 -> 73800 | I23: =$AL$8*H23 -> 2952 | J23: =IF(I23+H23-$AL$35>0,I23+H23-$AL$35,0) -> 1252 | K23: =H23+I23-J23 -> 75500 | M23: =IF(J23>=0,J23,0) -> 1252 | N23: =IF(B23<$BH$31,IF(B24<=35,$BI$4,IF(B24<=45,$BI$5,IF(B24<=50,$BI$6,IF(B24<=55,$BI$7,IF(B24<=60,$BI$8,IF(B24<=65,$BI$9,IF(B24<=70,$BI$10,$BI$11)))))))*'Retirement Dashboard'!$C$12,0) -> 0 | O23: =R22+N23+M23 -> 358490.12 | P23: =IF(B23<=55,$AL$5,$AN$6)*(IF(O23>=40000,40000,O23)) -> 2400 | Q23: =$AN$7*IF(O23>=40000,O23-40000,0) -> 15924.506 | R23: =O23+P23+Q23 -> 376814.62 | T23: =IF(B23<$BH$31,IF(B23<=35,$BH$4,IF(B24<=45,$BH$5,IF(B24<=50,$BH$6,IF(B24<=55,$BH$7,IF(B24<=60,$BH$8,IF(B24<=65,$BH$9,IF(B24<=70,$BH$10,$BH$11)))))))*'Retirement Dashboard'!$C$12,0) -> 0 | U23: =IF(B23<($BH$57+$BH$30),$BH$56*12,0) -> 0 | V23: =IF(B23<=34,$AN$31,IF(B23<=39,$AN$32,IF(B23<=44,$AN$33,IF(B23<=49,$AN$34,IF(B23<=54,$AN$35,IF(B23<=59,$AN$36,IF(B23<=69,$AN$37,0))))))) -> 0 | W23: =Z22+T23-U23-V23 -> 128796.61 | X23: =IF(B23<=55,$AL$3,$AN$3)*(IF(W23>=20000,20000,W23)) -> 1200 | Y23: =$AL$4*IF(W23>=20000,W23-20000,W23) -> 2719.9151 | Z23: =W23+X23+Y23 -> 132716.52 | AK23: <=78 | AL23: 1530 | AM23: 900 | AR23: =AR22+1 -> 45 | AS23: =AS22+1 -> 2043 | AT23: =(AT22*103.5%) -> 197790.46 | AU23: =AU22*103.5% -> 395695.61 | AV23: =AV22*103.5% -> 791391.23 | AW23: =AW22+30 -> 1370 | AX23: =AX22+60 -> 2620 | AY23: =AY22*103.31% -> 5977.3149 | BA23: 48 | BB23: =(100%+$BB$3)*BB22 -> 361.3463 | BC23: =(100%+$BB$3)*BC22 -> 294.21873 | BD23: =(100%+$BD$3)*BD22 -> 945.49902
B24: =B23+1 -> 71 | C24: =IF(B24>=67,$BI$55,C23+(1.0244%*C23)) -> 0 | D24: =IF(B24<=20,$AL$14,IF(B24<=30,$AL$15,IF(B24<=40,$AL$16,IF(B24<=50,$AL$17,IF(B24<=60,$AL$18,IF(B24<=65,$AL$19,IF(B24<=70,$AL$20, IF(B24<=73,$AL$21,IF(B24<=75,$AL$22,IF(B24<=78,$AL$23,IF(B24<=80,$AL$24,IF(B24<=83,$AL$25,IF(B24<=85,$AL$26,IF(B24<=90,$AL$27,$AL$28)))))))))))))) -> 1195 | E24: =IF(B24<=20,$AM$14,IF(B24<=30,$AM$15,IF(B24<=40,$AM$16,IF(B24<=50,$AM$17,IF(B24<=60,$AM$18,IF(B24<=65,$AM$19,IF(B24<=70,$AM$20, IF(B24<=73,$AM$21,IF(B24<=75,$AM$22,IF(B24<=78,$AM$23,IF(B24<=80,$AM$24,IF(B24<=83,$AM$25,IF(B24<=85,$AM$26,IF(B24<=90,$AM$27,$AM$28)))))))))))))) -> 900 | F24: =IF(AND('Retirement Dashboard'!$C$42="Yes", B24<= 'Retirement Dashboard'!$E$42), 600, 0) -> 0 | G24: =IF(B24<'Retirement Dashboard'!$E$6,IF(B24<=35,$BJ$4,IF(B24<=45,$BJ$5,IF(B24<=50,$BJ$6,IF(B24<=55,$BJ$7,IF(B24<=60,$BJ$8,IF(B24<=65,$BJ$9,IF(B24<=70,$BJ$10,$BJ$11)))))))*'Retirement Dashboard'!$C$12,0) -> 0 | H24: =K23-C24-D24-E24-F24+G24 -> 73405 | I24: =$AL$8*H24 -> 2936.2 | J24: =IF(I24+H24-$AL$35>0,I24+H24-$AL$35,0) -> 841.2 | K24: =H24+I24-J24 -> 75500 | M24: =IF(J24>=0,J24,0) -> 841.2 | N24: =IF(B24<$BH$31,IF(B25<=35,$BI$4,IF(B25<=45,$BI$5,IF(B25<=50,$BI$6,IF(B25<=55,$BI$7,IF(B25<=60,$BI$8,IF(B25<=65,$BI$9,IF(B25<=70,$BI$10,$BI$11)))))))*'Retirement Dashboard'!$C$12,0) -> 0 | O24: =R23+N24+M24 -> 377655.82 | P24: =IF(B24<=55,$AL$5,$AN$6)*(IF(O24>=40000,40000,O24)) -> 2400 | Q24: =$AN$7*IF(O24>=40000,O24-40000,0) -> 16882.791 | R24: =O24+P24+Q24 -> 396938.61 | T24: =IF(B24<$BH$31,IF(B24<=35,$BH$4,IF(B25<=45,$BH$5,IF(B25<=50,$BH$6,IF(B25<=55,$BH$7,IF(B25<=60,$BH$8,IF(B25<=65,$BH$9,IF(B25<=70,$BH$10,$BH$11)))))))*'Retirement Dashboard'!$C$12,0) -> 0 | U24: =IF(B24<($BH$57+$BH$30),$BH$56*12,0) -> 0 | V24: =IF(B24<=34,$AN$31,IF(B24<=39,$AN$32,IF(B24<=44,$AN$33,IF(B24<=49,$AN$34,IF(B24<=54,$AN$35,IF(B24<=59,$AN$36,IF(B24<=69,$AN$37,0))))))) -> 0 | W24: =Z23+T24-U24-V24 -> 132716.52 | X24: =IF(B24<=55,$AL$3,$AN$3)*(IF(W24>=20000,20000,W24)) -> 1200 | Y24: =$AL$4*IF(W24>=20000,W24-20000,W24) -> 2817.913 | Z24: =W24+X24+Y24 -> 136734.43 | AK24: <=80 | AL24: 1590 | AM24: 900 | AR24: =AR23+1 -> 46 | AS24: =AS23+1 -> 2044 | AT24: =(AT23*103.5%) -> 204713.13 | AU24: =AU23*103.5% -> 409544.96 | AV24: =AV23*103.5% -> 819089.92 | AW24: =AW23+30 -> 1400 | AX24: =AX23+60 -> 2680 | AY24: =AY23*103.31% -> 6175.164 | BA24: 49 | BB24: =(100%+$BB$3)*BB23 -> 368.57323 | BC24: =(100%+$BB$3)*BC23 -> 300.1031 | BD24: =(100%+$BD$3)*BD23 -> 964.409
B25: =B24+1 -> 72 | C25: =IF(B25>=67,$BI$55,C24+(1.0244%*C24)) -> 0 | D25: =IF(B25<=20,$AL$14,IF(B25<=30,$AL$15,IF(B25<=40,$AL$16,IF(B25<=50,$AL$17,IF(B25<=60,$AL$18,IF(B25<=65,$AL$19,IF(B25<=70,$AL$20, IF(B25<=73,$AL$21,IF(B25<=75,$AL$22,IF(B25<=78,$AL$23,IF(B25<=80,$AL$24,IF(B25<=83,$AL$25,IF(B25<=85,$AL$26,IF(B25<=90,$AL$27,$AL$28)))))))))))))) -> 1195 | E25: =IF(B25<=20,$AM$14,IF(B25<=30,$AM$15,IF(B25<=40,$AM$16,IF(B25<=50,$AM$17,IF(B25<=60,$AM$18,IF(B25<=65,$AM$19,IF(B25<=70,$AM$20, IF(B25<=73,$AM$21,IF(B25<=75,$AM$22,IF(B25<=78,$AM$23,IF(B25<=80,$AM$24,IF(B25<=83,$AM$25,IF(B25<=85,$AM$26,IF(B25<=90,$AM$27,$AM$28)))))))))))))) -> 900 | F25: =IF(AND('Retirement Dashboard'!$C$42="Yes", B25<= 'Retirement Dashboard'!$E$42), 600, 0) -> 0 | G25: =IF(B25<'Retirement Dashboard'!$E$6,IF(B25<=35,$BJ$4,IF(B25<=45,$BJ$5,IF(B25<=50,$BJ$6,IF(B25<=55,$BJ$7,IF(B25<=60,$BJ$8,IF(B25<=65,$BJ$9,IF(B25<=70,$BJ$10,$BJ$11)))))))*'Retirement Dashboard'!$C$12,0) -> 0 | H25: =K24-C25-D25-E25-F25+G25 -> 73405 | I25: =$AL$8*H25 -> 2936.2 | J25: =IF(I25+H25-$AL$35>0,I25+H25-$AL$35,0) -> 841.2 | K25: =H25+I25-J25 -> 75500 | M25: =IF(J25>=0,J25,0) -> 841.2 | N25: =IF(B25<$BH$31,IF(B26<=35,$BI$4,IF(B26<=45,$BI$5,IF(B26<=50,$BI$6,IF(B26<=55,$BI$7,IF(B26<=60,$BI$8,IF(B26<=65,$BI$9,IF(B26<=70,$BI$10,$BI$11)))))))*'Retirement Dashboard'!$C$12,0) -> 0 | O25: =R24+N25+M25 -> 397779.81 | P25: =IF(B25<=55,$AL$5,$AN$6)*(IF(O25>=40000,40000,O25)) -> 2400 | Q25: =$AN$7*IF(O25>=40000,O25-40000,0) -> 17888.991 | R25: =O25+P25+Q25 -> 418068.8 | T25: =IF(B25<$BH$31,IF(B25<=35,$BH$4,IF(B26<=45,$BH$5,IF(B26<=50,$BH$6,IF(B26<=55,$BH$7,IF(B26<=60,$BH$8,IF(B26<=65,$BH$9,IF(B26<=70,$BH$10,$BH$11)))))))*'Retirement Dashboard'!$C$12,0) -> 0 | U25: =IF(B25<($BH$57+$BH$30),$BH$56*12,0) -> 0 | V25: =IF(B25<=34,$AN$31,IF(B25<=39,$AN$32,IF(B25<=44,$AN$33,IF(B25<=49,$AN$34,IF(B25<=54,$AN$35,IF(B25<=59,$AN$36,IF(B25<=69,$AN$37,0))))))) -> 0 | W25: =Z24+T25-U25-V25 -> 136734.43 | X25: =IF(B25<=55,$AL$3,$AN$3)*(IF(W25>=20000,20000,W25)) -> 1200 | Y25: =$AL$4*IF(W25>=20000,W25-20000,W25) -> 2918.3608 | Z25: =W25+X25+Y25 -> 140852.79 | AK25: <=83 | AL25: 1675 | AM25: 900 | AR25: =AR24+1 -> 47 | AS25: =AS24+1 -> 2045 | AT25: =(AT24*103.5%) -> 211878.09 | AU25: =AU24*103.5% -> 423879.03 | AV25: =AV24*103.5% -> 847758.07 | AW25: =AW24+30 -> 1430 | AX25: =AX24+60 -> 2740 | AY25: =AY24*103.31% -> 6379.562 | BA25: 50 | BB25: =(100%+$BB$3)*BB24 -> 375.94469 | BC25: =(100%+$BB$3)*BC24 -> 306.10516 | BD25: =(100%+$BD$3)*BD24 -> 983.69718
B26: =B25+1 -> 73 | C26: =IF(B26>=67,$BI$55,C25+(1.0244%*C25)) -> 0 | D26: =IF(B26<=20,$AL$14,IF(B26<=30,$AL$15,IF(B26<=40,$AL$16,IF(B26<=50,$AL$17,IF(B26<=60,$AL$18,IF(B26<=65,$AL$19,IF(B26<=70,$AL$20, IF(B26<=73,$AL$21,IF(B26<=75,$AL$22,IF(B26<=78,$AL$23,IF(B26<=80,$AL$24,IF(B26<=83,$AL$25,IF(B26<=85,$AL$26,IF(B26<=90,$AL$27,$AL$28)))))))))))))) -> 1195 | E26: =IF(B26<=20,$AM$14,IF(B26<=30,$AM$15,IF(B26<=40,$AM$16,IF(B26<=50,$AM$17,IF(B26<=60,$AM$18,IF(B26<=65,$AM$19,IF(B26<=70,$AM$20, IF(B26<=73,$AM$21,IF(B26<=75,$AM$22,IF(B26<=78,$AM$23,IF(B26<=80,$AM$24,IF(B26<=83,$AM$25,IF(B26<=85,$AM$26,IF(B26<=90,$AM$27,$AM$28)))))))))))))) -> 900 | F26: =IF(AND('Retirement Dashboard'!$C$42="Yes", B26<= 'Retirement Dashboard'!$E$42), 600, 0) -> 0 | G26: =IF(B26<'Retirement Dashboard'!$E$6,IF(B26<=35,$BJ$4,IF(B26<=45,$BJ$5,IF(B26<=50,$BJ$6,IF(B26<=55,$BJ$7,IF(B26<=60,$BJ$8,IF(B26<=65,$BJ$9,IF(B26<=70,$BJ$10,$BJ$11)))))))*'Retirement Dashboard'!$C$12,0) -> 0 | H26: =K25-C26-D26-E26-F26+G26 -> 73405 | I26: =$AL$8*H26 -> 2936.2 | J26: =IF(I26+H26-$AL$35>0,I26+H26-$AL$35,0) -> 841.2 | K26: =H26+I26-J26 -> 75500 | M26: =IF(J26>=0,J26,0) -> 841.2 | N26: =IF(B26<$BH$31,IF(B27<=35,$BI$4,IF(B27<=45,$BI$5,IF(B27<=50,$BI$6,IF(B27<=55,$BI$7,IF(B27<=60,$BI$8,IF(B27<=65,$BI$9,IF(B27<=70,$BI$10,$BI$11)))))))*'Retirement Dashboard'!$C$12,0) -> 0 | O26: =R25+N26+M26 -> 418910 | P26: =IF(B26<=55,$AL$5,$AN$6)*(IF(O26>=40000,40000,O26)) -> 2400 | Q26: =$AN$7*IF(O26>=40000,O26-40000,0) -> 18945.5 | R26: =O26+P26+Q26 -> 440255.5 | T26: =IF(B26<$BH$31,IF(B26<=35,$BH$4,IF(B27<=45,$BH$5,IF(B27<=50,$BH$6,IF(B27<=55,$BH$7,IF(B27<=60,$BH$8,IF(B27<=65,$BH$9,IF(B27<=70,$BH$10,$BH$11)))))))*'Retirement Dashboard'!$C$12,0) -> 0 | U26: =IF(B26<($BH$57+$BH$30),$BH$56*12,0) -> 0 | V26: =IF(B26<=34,$AN$31,IF(B26<=39,$AN$32,IF(B26<=44,$AN$33,IF(B26<=49,$AN$34,IF(B26<=54,$AN$35,IF(B26<=59,$AN$36,IF(B26<=69,$AN$37,0))))))) -> 0 | W26: =Z25+T26-U26-V26 -> 140852.79 | X26: =IF(B26<=55,$AL$3,$AN$3)*(IF(W26>=20000,20000,W26)) -> 1200 | Y26: =$AL$4*IF(W26>=20000,W26-20000,W26) -> 3021.3199 | Z26: =W26+X26+Y26 -> 145074.11 | AK26: <=85 | AL26: 1935 | AM26: 900 | AR26: =AR25+1 -> 48 | AS26: =AS25+1 -> 2046 | AT26: =(AT25*103.5%) -> 219293.82 | AU26: =AU25*103.5% -> 438714.8 | AV26: =AV25*103.5% -> 877429.6 | AW26: =AW25+30 -> 1460 | AX26: =AX25+60 -> 2800 | AY26: =AY25*103.31% -> 6590.7255 | BA26: 51 | BB26: =(100%+$BB$3)*BB25 -> 383.46359 | BC26: =(100%+$BB$3)*BC25 -> 312.22727 | BD26: =(100%+$BD$3)*BD25 -> 1003.3711
B27: =B26+1 -> 74 | C27: =IF(B27>=67,$BI$55,C26+(1.0244%*C26)) -> 0 | D27: =IF(B27<=20,$AL$14,IF(B27<=30,$AL$15,IF(B27<=40,$AL$16,IF(B27<=50,$AL$17,IF(B27<=60,$AL$18,IF(B27<=65,$AL$19,IF(B27<=70,$AL$20, IF(B27<=73,$AL$21,IF(B27<=75,$AL$22,IF(B27<=78,$AL$23,IF(B27<=80,$AL$24,IF(B27<=83,$AL$25,IF(B27<=85,$AL$26,IF(B27<=90,$AL$27,$AL$28)))))))))))))) -> 1320 | E27: =IF(B27<=20,$AM$14,IF(B27<=30,$AM$15,IF(B27<=40,$AM$16,IF(B27<=50,$AM$17,IF(B27<=60,$AM$18,IF(B27<=65,$AM$19,IF(B27<=70,$AM$20, IF(B27<=73,$AM$21,IF(B27<=75,$AM$22,IF(B27<=78,$AM$23,IF(B27<=80,$AM$24,IF(B27<=83,$AM$25,IF(B27<=85,$AM$26,IF(B27<=90,$AM$27,$AM$28)))))))))))))) -> 900 | F27: =IF(AND('Retirement Dashboard'!$C$42="Yes", B27<= 'Retirement Dashboard'!$E$42), 600, 0) -> 0 | G27: =IF(B27<'Retirement Dashboard'!$E$6,IF(B27<=35,$BJ$4,IF(B27<=45,$BJ$5,IF(B27<=50,$BJ$6,IF(B27<=55,$BJ$7,IF(B27<=60,$BJ$8,IF(B27<=65,$BJ$9,IF(B27<=70,$BJ$10,$BJ$11)))))))*'Retirement Dashboard'!$C$12,0) -> 0 | H27: =K26-C27-D27-E27-F27+G27 -> 73280 | I27: =$AL$8*H27 -> 2931.2 | J27: =IF(I27+H27-$AL$35>0,I27+H27-$AL$35,0) -> 711.2 | K27: =H27+I27-J27 -> 75500 | M27: =IF(J27>=0,J27,0) -> 711.2 | N27: =IF(B27<$BH$31,IF(B28<=35,$BI$4,IF(B28<=45,$BI$5,IF(B28<=50,$BI$6,IF(B28<=55,$BI$7,IF(B28<=60,$BI$8,IF(B28<=65,$BI$9,IF(B28<=70,$BI$10,$BI$11)))))))*'Retirement Dashboard'!$C$12,0) -> 0 | O27: =R26+N27+M27 -> 440966.7 | P27: =IF(B27<=55,$AL$5,$AN$6)*(IF(O27>=40000,40000,O27)) -> 2400 | Q27: =$AN$7*IF(O27>=40000,O27-40000,0) -> 20048.335 | R27: =O27+P27+Q27 -> 463415.04 | T27: =IF(B27<$BH$31,IF(B27<=35,$BH$4,IF(B28<=45,$BH$5,IF(B28<=50,$BH$6,IF(B28<=55,$BH$7,IF(B28<=60,$BH$8,IF(B28<=65,$BH$9,IF(B28<=70,$BH$10,$BH$11)))))))*'Retirement Dashboard'!$C$12,0) -> 0 | U27: =IF(B27<($BH$57+$BH$30),$BH$56*12,0) -> 0 | V27: =IF(B27<=34,$AN$31,IF(B27<=39,$AN$32,IF(B27<=44,$AN$33,IF(B27<=49,$AN$34,IF(B27<=54,$AN$35,IF(B27<=59,$AN$36,IF(B27<=69,$AN$37,0))))))) -> 0 | W27: =Z26+T27-U27-V27 -> 145074.11 | X27: =IF(B27<=55,$AL$3,$AN$3)*(IF(W27>=20000,20000,W27)) -> 1200 | Y27: =$AL$4*IF(W27>=20000,W27-20000,W27) -> 3126.8529 | Z27: =W27+X27+Y27 -> 149400.97 | AK27: <=90 | AL27: 2025 | AM27: 900 | AR27: =AR26+1 -> 49 | AS27: =AS26+1 -> 2047 | AT27: =(AT26*103.5%) -> 226969.1 | AU27: =AU26*103.5% -> 454069.82 | AV27: =AV26*103.5% -> 908139.64 | AW27: =AW26+30 -> 1490 | AX27: =AX26+60 -> 2860 | AY27: =AY26*103.31% -> 6808.8785 | BA27: 52 | BB27: =(100%+$BB$3)*BB26 -> 391.13286 | BC27: =(100%+$BB$3)*BC26 -> 318.47181 | BD27: =(100%+$BD$3)*BD26 -> 1023.4385 | BG27: Current Year | BH27: 2025
B28: =B27+1 -> 75 | C28: =IF(B28>=67,$BI$55,C27+(1.0244%*C27)) -> 0 | D28: =IF(B28<=20,$AL$14,IF(B28<=30,$AL$15,IF(B28<=40,$AL$16,IF(B28<=50,$AL$17,IF(B28<=60,$AL$18,IF(B28<=65,$AL$19,IF(B28<=70,$AL$20, IF(B28<=73,$AL$21,IF(B28<=75,$AL$22,IF(B28<=78,$AL$23,IF(B28<=80,$AL$24,IF(B28<=83,$AL$25,IF(B28<=85,$AL$26,IF(B28<=90,$AL$27,$AL$28)))))))))))))) -> 1320 | E28: =IF(B28<=20,$AM$14,IF(B28<=30,$AM$15,IF(B28<=40,$AM$16,IF(B28<=50,$AM$17,IF(B28<=60,$AM$18,IF(B28<=65,$AM$19,IF(B28<=70,$AM$20, IF(B28<=73,$AM$21,IF(B28<=75,$AM$22,IF(B28<=78,$AM$23,IF(B28<=80,$AM$24,IF(B28<=83,$AM$25,IF(B28<=85,$AM$26,IF(B28<=90,$AM$27,$AM$28)))))))))))))) -> 900 | F28: =IF(AND('Retirement Dashboard'!$C$42="Yes", B28<= 'Retirement Dashboard'!$E$42), 600, 0) -> 0 | G28: =IF(B28<'Retirement Dashboard'!$E$6,IF(B28<=35,$BJ$4,IF(B28<=45,$BJ$5,IF(B28<=50,$BJ$6,IF(B28<=55,$BJ$7,IF(B28<=60,$BJ$8,IF(B28<=65,$BJ$9,IF(B28<=70,$BJ$10,$BJ$11)))))))*'Retirement Dashboard'!$C$12,0) -> 0 | H28: =K27-C28-D28-E28-F28+G28 -> 73280 | I28: =$AL$8*H28 -> 2931.2 | J28: =IF(I28+H28-$AL$35>0,I28+H28-$AL$35,0) -> 711.2 | K28: =H28+I28-J28 -> 75500 | M28: =IF(J28>=0,J28,0) -> 711.2 | N28: =IF(B28<$BH$31,IF(B29<=35,$BI$4,IF(B29<=45,$BI$5,IF(B29<=50,$BI$6,IF(B29<=55,$BI$7,IF(B29<=60,$BI$8,IF(B29<=65,$BI$9,IF(B29<=70,$BI$10,$BI$11)))))))*'Retirement Dashboard'!$C$12,0) -> 0 | O28: =R27+N28+M28 -> 464126.24 | P28: =IF(B28<=55,$AL$5,$AN$6)*(IF(O28>=40000,40000,O28)) -> 2400 | Q28: =$AN$7*IF(O28>=40000,O28-40000,0) -> 21206.312 | R28: =O28+P28+Q28 -> 487732.55 | T28: =IF(B28<$BH$31,IF(B28<=35,$BH$4,IF(B29<=45,$BH$5,IF(B29<=50,$BH$6,IF(B29<=55,$BH$7,IF(B29<=60,$BH$8,IF(B29<=65,$BH$9,IF(B29<=70,$BH$10,$BH$11)))))))*'Retirement Dashboard'!$C$12,0) -> 0 | U28: =IF(B28<($BH$57+$BH$30),$BH$56*12,0) -> 0 | V28: =IF(B28<=34,$AN$31,IF(B28<=39,$AN$32,IF(B28<=44,$AN$33,IF(B28<=49,$AN$34,IF(B28<=54,$AN$35,IF(B28<=59,$AN$36,IF(B28<=69,$AN$37,0))))))) -> 0 | W28: =Z27+T28-U28-V28 -> 149400.97 | X28: =IF(B28<=55,$AL$3,$AN$3)*(IF(W28>=20000,20000,W28)) -> 1200 | Y28: =$AL$4*IF(W28>=20000,W28-20000,W28) -> 3235.0242 | Z28: =W28+X28+Y28 -> 153835.99 | AK28: <=100 | AL28: 2055 | AM28: 900 | AR28: =AR27+1 -> 50 | AS28: =AS27+1 -> 2048 | AT28: =(AT27*103.5%) -> 234913.02 | AU28: =AU27*103.5% -> 469962.26 | AV28: =AV27*103.5% -> 939924.52 | AW28: =AW27+30 -> 1520 | AX28: =AX27+60 -> 2920 | AY28: =AY27*103.31% -> 7034.2524 | BA28: 53 | BB28: =(100%+$BB$3)*BB27 -> 398.95551 | BC28: =(100%+$BB$3)*BC27 -> 324.84125 | BD28: =(100%+$BD$3)*BD27 -> 1043.9073 | BG28: Name | BH28: Siti
B29: =B28+1 -> 76 | C29: =IF(B29>=67,$BI$55,C28+(1.0244%*C28)) -> 0 | D29: =IF(B29<=20,$AL$14,IF(B29<=30,$AL$15,IF(B29<=40,$AL$16,IF(B29<=50,$AL$17,IF(B29<=60,$AL$18,IF(B29<=65,$AL$19,IF(B29<=70,$AL$20, IF(B29<=73,$AL$21,IF(B29<=75,$AL$22,IF(B29<=78,$AL$23,IF(B29<=80,$AL$24,IF(B29<=83,$AL$25,IF(B29<=85,$AL$26,IF(B29<=90,$AL$27,$AL$28)))))))))))))) -> 1530 | E29: =IF(B29<=20,$AM$14,IF(B29<=30,$AM$15,IF(B29<=40,$AM$16,IF(B29<=50,$AM$17,IF(B29<=60,$AM$18,IF(B29<=65,$AM$19,IF(B29<=70,$AM$20, IF(B29<=73,$AM$21,IF(B29<=75,$AM$22,IF(B29<=78,$AM$23,IF(B29<=80,$AM$24,IF(B29<=83,$AM$25,IF(B29<=85,$AM$26,IF(B29<=90,$AM$27,$AM$28)))))))))))))) -> 900 | F29: =IF(AND('Retirement Dashboard'!$C$42="Yes", B29<= 'Retirement Dashboard'!$E$42), 600, 0) -> 0 | G29: =IF(B29<'Retirement Dashboard'!$E$6,IF(B29<=35,$BJ$4,IF(B29<=45,$BJ$5,IF(B29<=50,$BJ$6,IF(B29<=55,$BJ$7,IF(B29<=60,$BJ$8,IF(B29<=65,$BJ$9,IF(B29<=70,$BJ$10,$BJ$11)))))))*'Retirement Dashboard'!$C$12,0) -> 0 | H29: =K28-C29-D29-E29-F29+G29 -> 73070 | I29: =$AL$8*H29 -> 2922.8 | J29: =IF(I29+H29-$AL$35>0,I29+H29-$AL$35,0) -> 492.8 | K29: =H29+I29-J29 -> 75500 | M29: =IF(J29>=0,J29,0) -> 492.8 | N29: =IF(B29<$BH$31,IF(B30<=35,$BI$4,IF(B30<=45,$BI$5,IF(B30<=50,$BI$6,IF(B30<=55,$BI$7,IF(B30<=60,$BI$8,IF(B30<=65,$BI$9,IF(B30<=70,$BI$10,$BI$11)))))))*'Retirement Dashboard'!$C$12,0) -> 0 | O29: =R28+N29+M29 -> 488225.35 | P29: =IF(B29<=55,$AL$5,$AN$6)*(IF(O29>=40000,40000,O29)) -> 2400 | Q29: =$AN$7*IF(O29>=40000,O29-40000,0) -> 22411.268 | R29: =O29+P29+Q29 -> 513036.62 | T29: =IF(B29<$BH$31,IF(B29<=35,$BH$4,IF(B30<=45,$BH$5,IF(B30<=50,$BH$6,IF(B30<=55,$BH$7,IF(B30<=60,$BH$8,IF(B30<=65,$BH$9,IF(B30<=70,$BH$10,$BH$11)))))))*'Retirement Dashboard'!$C$12,0) -> 0 | U29: =IF(B29<($BH$57+$BH$30),$BH$56*12,0) -> 0 | V29: =IF(B29<=34,$AN$31,IF(B29<=39,$AN$32,IF(B29<=44,$AN$33,IF(B29<=49,$AN$34,IF(B29<=54,$AN$35,IF(B29<=59,$AN$36,IF(B29<=69,$AN$37,0))))))) -> 0 | W29: =Z28+T29-U29-V29 -> 153835.99 | X29: =IF(B29<=55,$AL$3,$AN$3)*(IF(W29>=20000,20000,W29)) -> 1200 | Y29: =$AL$4*IF(W29>=20000,W29-20000,W29) -> 3345.8998 | Z29: =W29+X29+Y29 -> 158381.89 | AR29: =AR28+1 -> 51 | AS29: =AS28+1 -> 2049 | AT29: =(AT28*103.5%) -> 243134.98 | AU29: =AU28*103.5% -> 486410.94 | AV29: =AV28*103.5% -> 972821.88 | AW29: =AW28+30 -> 1550 | AX29: =AX28+60 -> 2980 | AY29: =AY28*103.31% -> 7267.0861 | BA29: 54 | BB29: =(100%+$BB$3)*BB28 -> 406.93462 | BC29: =(100%+$BB$3)*BC28 -> 331.33807 | BD29: =(100%+$BD$3)*BD28 -> 1064.7855 | BG29: Birthday | BH29: =[11]Siti!D3 -> 27716
B30: =B29+1 -> 77 | C30: =IF(B30>=67,$BI$55,C29+(1.0244%*C29)) -> 0 | D30: =IF(B30<=20,$AL$14,IF(B30<=30,$AL$15,IF(B30<=40,$AL$16,IF(B30<=50,$AL$17,IF(B30<=60,$AL$18,IF(B30<=65,$AL$19,IF(B30<=70,$AL$20, IF(B30<=73,$AL$21,IF(B30<=75,$AL$22,IF(B30<=78,$AL$23,IF(B30<=80,$AL$24,IF(B30<=83,$AL$25,IF(B30<=85,$AL$26,IF(B30<=90,$AL$27,$AL$28)))))))))))))) -> 1530 | E30: =IF(B30<=20,$AM$14,IF(B30<=30,$AM$15,IF(B30<=40,$AM$16,IF(B30<=50,$AM$17,IF(B30<=60,$AM$18,IF(B30<=65,$AM$19,IF(B30<=70,$AM$20, IF(B30<=73,$AM$21,IF(B30<=75,$AM$22,IF(B30<=78,$AM$23,IF(B30<=80,$AM$24,IF(B30<=83,$AM$25,IF(B30<=85,$AM$26,IF(B30<=90,$AM$27,$AM$28)))))))))))))) -> 900 | F30: =IF(AND('Retirement Dashboard'!$C$42="Yes", B30<= 'Retirement Dashboard'!$E$42), 600, 0) -> 0 | G30: =IF(B30<'Retirement Dashboard'!$E$6,IF(B30<=35,$BJ$4,IF(B30<=45,$BJ$5,IF(B30<=50,$BJ$6,IF(B30<=55,$BJ$7,IF(B30<=60,$BJ$8,IF(B30<=65,$BJ$9,IF(B30<=70,$BJ$10,$BJ$11)))))))*'Retirement Dashboard'!$C$12,0) -> 0 | H30: =K29-C30-D30-E30-F30+G30 -> 73070 | I30: =$AL$8*H30 -> 2922.8 | J30: =IF(I30+H30-$AL$35>0,I30+H30-$AL$35,0) -> 492.8 | K30: =H30+I30-J30 -> 75500 | M30: =IF(J30>=0,J30,0) -> 492.8 | N30: =IF(B30<$BH$31,IF(B31<=35,$BI$4,IF(B31<=45,$BI$5,IF(B31<=50,$BI$6,IF(B31<=55,$BI$7,IF(B31<=60,$BI$8,IF(B31<=65,$BI$9,IF(B31<=70,$BI$10,$BI$11)))))))*'Retirement Dashboard'!$C$12,0) -> 0 | O30: =R29+N30+M30 -> 513529.42 | P30: =IF(B30<=55,$AL$5,$AN$6)*(IF(O30>=40000,40000,O30)) -> 2400 | Q30: =$AN$7*IF(O30>=40000,O30-40000,0) -> 23676.471 | R30: =O30+P30+Q30 -> 539605.89 | T30: =IF(B30<$BH$31,IF(B30<=35,$BH$4,IF(B31<=45,$BH$5,IF(B31<=50,$BH$6,IF(B31<=55,$BH$7,IF(B31<=60,$BH$8,IF(B31<=65,$BH$9,IF(B31<=70,$BH$10,$BH$11)))))))*'Retirement Dashboard'!$C$12,0) -> 0 | U30: =IF(B30<($BH$57+$BH$30),$BH$56*12,0) -> 0 | V30: =IF(B30<=34,$AN$31,IF(B30<=39,$AN$32,IF(B30<=44,$AN$33,IF(B30<=49,$AN$34,IF(B30<=54,$AN$35,IF(B30<=59,$AN$36,IF(B30<=69,$AN$37,0))))))) -> 0 | W30: =Z29+T30-U30-V30 -> 158381.89 | X30: =IF(B30<=55,$AL$3,$AN$3)*(IF(W30>=20000,20000,W30)) -> 1200 | Y30: =$AL$4*IF(W30>=20000,W30-20000,W30) -> 3459.5473 | Z30: =W30+X30+Y30 -> 163041.44 | AK30: CPF Limit 2025 | AM30: Age (years)$70K sum assured/Yr | AN30: DPS Annual Premium | AR30: =AR29+1 -> 52 | AS30: =AS29+1 -> 2050 | AT30: =(AT29*103.5%) -> 251644.7 | AU30: =AU29*103.5% -> 503435.32 | AV30: =AV29*103.5% -> 1006870.6 | AW30: =AW29+30 -> 1580 | AX30: =AX29+60 -> 3040 | AY30: =AY29*103.31% -> 7507.6267 | BA30: 55 | BB30: =(100%+$BB$3)*BB29 -> 415.07332 | BC30: =(100%+$BB$3)*BC29 -> 337.96483 | BD30: =(100%+$BD$3)*BD29 -> 1086.0812 | BG30: Age Next Birthday | BH30: =ROUND(1+(TODAY()-BH29)/365,0) -> 52
B31: =B30+1 -> 78 | C31: =IF(B31>=67,$BI$55,C30+(1.0244%*C30)) -> 0 | D31: =IF(B31<=20,$AL$14,IF(B31<=30,$AL$15,IF(B31<=40,$AL$16,IF(B31<=50,$AL$17,IF(B31<=60,$AL$18,IF(B31<=65,$AL$19,IF(B31<=70,$AL$20, IF(B31<=73,$AL$21,IF(B31<=75,$AL$22,IF(B31<=78,$AL$23,IF(B31<=80,$AL$24,IF(B31<=83,$AL$25,IF(B31<=85,$AL$26,IF(B31<=90,$AL$27,$AL$28)))))))))))))) -> 1530 | E31: =IF(B31<=20,$AM$14,IF(B31<=30,$AM$15,IF(B31<=40,$AM$16,IF(B31<=50,$AM$17,IF(B31<=60,$AM$18,IF(B31<=65,$AM$19,IF(B31<=70,$AM$20, IF(B31<=73,$AM$21,IF(B31<=75,$AM$22,IF(B31<=78,$AM$23,IF(B31<=80,$AM$24,IF(B31<=83,$AM$25,IF(B31<=85,$AM$26,IF(B31<=90,$AM$27,$AM$28)))))))))))))) -> 900 | F31: =IF(AND('Retirement Dashboard'!$C$42="Yes", B31<= 'Retirement Dashboard'!$E$42), 600, 0) -> 0 | G31: =IF(B31<'Retirement Dashboard'!$E$6,IF(B31<=35,$BJ$4,IF(B31<=45,$BJ$5,IF(B31<=50,$BJ$6,IF(B31<=55,$BJ$7,IF(B31<=60,$BJ$8,IF(B31<=65,$BJ$9,IF(B31<=70,$BJ$10,$BJ$11)))))))*'Retirement Dashboard'!$C$12,0) -> 0 | H31: =K30-C31-D31-E31-F31+G31 -> 73070 | I31: =$AL$8*H31 -> 2922.8 | J31: =IF(I31+H31-$AL$35>0,I31+H31-$AL$35,0) -> 492.8 | K31: =H31+I31-J31 -> 75500 | M31: =IF(J31>=0,J31,0) -> 492.8 | N31: =IF(B31<$BH$31,IF(B32<=35,$BI$4,IF(B32<=45,$BI$5,IF(B32<=50,$BI$6,IF(B32<=55,$BI$7,IF(B32<=60,$BI$8,IF(B32<=65,$BI$9,IF(B32<=70,$BI$10,$BI$11)))))))*'Retirement Dashboard'!$C$12,0) -> 0 | O31: =R30+N31+M31 -> 540098.69 | P31: =IF(B31<=55,$AL$5,$AN$6)*(IF(O31>=40000,40000,O31)) -> 2400 | Q31: =$AN$7*IF(O31>=40000,O31-40000,0) -> 25004.934 | R31: =O31+P31+Q31 -> 567503.62 | T31: =IF(B31<$BH$31,IF(B31<=35,$BH$4,IF(B32<=45,$BH$5,IF(B32<=50,$BH$6,IF(B32<=55,$BH$7,IF(B32<=60,$BH$8,IF(B32<=65,$BH$9,IF(B32<=70,$BH$10,$BH$11)))))))*'Retirement Dashboard'!$C$12,0) -> 0 | U31: =IF(B31<($BH$57+$BH$30),$BH$56*12,0) -> 0 | V31: =IF(B31<=34,$AN$31,IF(B31<=39,$AN$32,IF(B31<=44,$AN$33,IF(B31<=49,$AN$34,IF(B31<=54,$AN$35,IF(B31<=59,$AN$36,IF(B31<=69,$AN$37,0))))))) -> 0 | W31: =Z30+T31-U31-V31 -> 163041.44 | X31: =IF(B31<=55,$AL$3,$AN$3)*(IF(W31>=20000,20000,W31)) -> 1200 | Y31: =$AL$4*IF(W31>=20000,W31-20000,W31) -> 3576.036 | Z31: =W31+X31+Y31 -> 167817.47 | AK31: CPF Mth Gross Wage Cap | AL31: 8000 | AM31: 34 and below | AN31: 18 | AR31: =AR30+1 -> 53 | AS31: =AS30+1 -> 2051 | AT31: =(AT30*103.5%) -> 260452.27 | AU31: =AU30*103.5% -> 521055.56 | AV31: =AV30*103.5% -> 1042111.1 | AW31: =AW30+30 -> 1610 | AX31: =AX30+60 -> 3100 | AY31: =AY30*103.31% -> 7756.1291 | BA31: 56 | BB31: =(100%+$BB$3)*BB30 -> 423.37478 | BC31: =(100%+$BB$3)*BC30 -> 344.72413 | BD31: =(100%+$BD$3)*BD30 -> 1107.8028 | BG31: Retirement Age | BH31: ='[10]Retirement Dashboard'!D38 -> 65
B32: =B31+1 -> 79 | C32: =IF(B32>=67,$BI$55,C31+(1.0244%*C31)) -> 0 | D32: =IF(B32<=20,$AL$14,IF(B32<=30,$AL$15,IF(B32<=40,$AL$16,IF(B32<=50,$AL$17,IF(B32<=60,$AL$18,IF(B32<=65,$AL$19,IF(B32<=70,$AL$20, IF(B32<=73,$AL$21,IF(B32<=75,$AL$22,IF(B32<=78,$AL$23,IF(B32<=80,$AL$24,IF(B32<=83,$AL$25,IF(B32<=85,$AL$26,IF(B32<=90,$AL$27,$AL$28)))))))))))))) -> 1590 | E32: =IF(B32<=20,$AM$14,IF(B32<=30,$AM$15,IF(B32<=40,$AM$16,IF(B32<=50,$AM$17,IF(B32<=60,$AM$18,IF(B32<=65,$AM$19,IF(B32<=70,$AM$20, IF(B32<=73,$AM$21,IF(B32<=75,$AM$22,IF(B32<=78,$AM$23,IF(B32<=80,$AM$24,IF(B32<=83,$AM$25,IF(B32<=85,$AM$26,IF(B32<=90,$AM$27,$AM$28)))))))))))))) -> 900 | F32: =IF(AND('Retirement Dashboard'!$C$42="Yes", B32<= 'Retirement Dashboard'!$E$42), 600, 0) -> 0 | G32: =IF(B32<'Retirement Dashboard'!$E$6,IF(B32<=35,$BJ$4,IF(B32<=45,$BJ$5,IF(B32<=50,$BJ$6,IF(B32<=55,$BJ$7,IF(B32<=60,$BJ$8,IF(B32<=65,$BJ$9,IF(B32<=70,$BJ$10,$BJ$11)))))))*'Retirement Dashboard'!$C$12,0) -> 0 | H32: =K31-C32-D32-E32-F32+G32 -> 73010 | I32: =$AL$8*H32 -> 2920.4 | J32: =IF(I32+H32-$AL$35>0,I32+H32-$AL$35,0) -> 430.4 | K32: =H32+I32-J32 -> 75500 | M32: =IF(J32>=0,J32,0) -> 430.4 | N32: =IF(B32<$BH$31,IF(B33<=35,$BI$4,IF(B33<=45,$BI$5,IF(B33<=50,$BI$6,IF(B33<=55,$BI$7,IF(B33<=60,$BI$8,IF(B33<=65,$BI$9,IF(B33<=70,$BI$10,$BI$11)))))))*'Retirement Dashboard'!$C$12,0) -> 0 | O32: =R31+N32+M32 -> 567934.02 | P32: =IF(B32<=55,$AL$5,$AN$6)*(IF(O32>=40000,40000,O32)) -> 2400 | Q32: =$AN$7*IF(O32>=40000,O32-40000,0) -> 26396.701 | R32: =O32+P32+Q32 -> 596730.73 | T32: =IF(B32<$BH$31,IF(B32<=35,$BH$4,IF(B33<=45,$BH$5,IF(B33<=50,$BH$6,IF(B33<=55,$BH$7,IF(B33<=60,$BH$8,IF(B33<=65,$BH$9,IF(B33<=70,$BH$10,$BH$11)))))))*'Retirement Dashboard'!$C$12,0) -> 0 | U32: =IF(B32<($BH$57+$BH$30),$BH$56*12,0) -> 0 | V32: =IF(B32<=34,$AN$31,IF(B32<=39,$AN$32,IF(B32<=44,$AN$33,IF(B32<=49,$AN$34,IF(B32<=54,$AN$35,IF(B32<=59,$AN$36,IF(B32<=69,$AN$37,0))))))) -> 0 | W32: =Z31+T32-U32-V32 -> 167817.47 | X32: =IF(B32<=55,$AL$3,$AN$3)*(IF(W32>=20000,20000,W32)) -> 1200 | Y32: =$AL$4*IF(W32>=20000,W32-20000,W32) -> 3695.4369 | Z32: =W32+X32+Y32 -> 172712.91 | AK32: Additional Wage Ceiling | AL32: =102000 -> 102000 | AM32: 35 to 39 | AN32: 30 | AR32: =AR31+1 -> 54 | AS32: =AS31+1 -> 2052 | AT32: =(AT31*103.5%) -> 269568.09 | AU32: =AU31*103.5% -> 539292.51 | AV32: =AV31*103.5% -> 1078585 | AW32: =AW31+30 -> 1640 | AX32: =AX31+60 -> 3160 | AY32: =AY31*103.31% -> 8012.857 | BA32: 57 | BB32: =(100%+$BB$3)*BB31 -> 431.84228 | BC32: =(100%+$BB$3)*BC31 -> 351.61861 | BD32: =(100%+$BD$3)*BD31 -> 1129.9588 | BG32: How many years to retirement savings you wished to have | BH32: 25
B33: =B32+1 -> 80 | C33: =IF(B33>=67,$BI$55,C32+(1.0244%*C32)) -> 0 | D33: =IF(B33<=20,$AL$14,IF(B33<=30,$AL$15,IF(B33<=40,$AL$16,IF(B33<=50,$AL$17,IF(B33<=60,$AL$18,IF(B33<=65,$AL$19,IF(B33<=70,$AL$20, IF(B33<=73,$AL$21,IF(B33<=75,$AL$22,IF(B33<=78,$AL$23,IF(B33<=80,$AL$24,IF(B33<=83,$AL$25,IF(B33<=85,$AL$26,IF(B33<=90,$AL$27,$AL$28)))))))))))))) -> 1590 | E33: =IF(B33<=20,$AM$14,IF(B33<=30,$AM$15,IF(B33<=40,$AM$16,IF(B33<=50,$AM$17,IF(B33<=60,$AM$18,IF(B33<=65,$AM$19,IF(B33<=70,$AM$20, IF(B33<=73,$AM$21,IF(B33<=75,$AM$22,IF(B33<=78,$AM$23,IF(B33<=80,$AM$24,IF(B33<=83,$AM$25,IF(B33<=85,$AM$26,IF(B33<=90,$AM$27,$AM$28)))))))))))))) -> 900 | F33: =IF(AND('Retirement Dashboard'!$C$42="Yes", B33<= 'Retirement Dashboard'!$E$42), 600, 0) -> 0 | G33: =IF(B33<'Retirement Dashboard'!$E$6,IF(B33<=35,$BJ$4,IF(B33<=45,$BJ$5,IF(B33<=50,$BJ$6,IF(B33<=55,$BJ$7,IF(B33<=60,$BJ$8,IF(B33<=65,$BJ$9,IF(B33<=70,$BJ$10,$BJ$11)))))))*'Retirement Dashboard'!$C$12,0) -> 0 | H33: =K32-C33-D33-E33-F33+G33 -> 73010 | I33: =$AL$8*H33 -> 2920.4 | J33: =IF(I33+H33-$AL$35>0,I33+H33-$AL$35,0) -> 430.4 | K33: =H33+I33-J33 -> 75500 | M33: =IF(J33>=0,J33,0) -> 430.4 | N33: =IF(B33<$BH$31,IF(B34<=35,$BI$4,IF(B34<=45,$BI$5,IF(B34<=50,$BI$6,IF(B34<=55,$BI$7,IF(B34<=60,$BI$8,IF(B34<=65,$BI$9,IF(B34<=70,$BI$10,$BI$11)))))))*'Retirement Dashboard'!$C$12,0) -> 0 | O33: =R32+N33+M33 -> 597161.13 | P33: =IF(B33<=55,$AL$5,$AN$6)*(IF(O33>=40000,40000,O33)) -> 2400 | Q33: =$AN$7*IF(O33>=40000,O33-40000,0) -> 27858.056 | R33: =O33+P33+Q33 -> 627419.18 | T33: =IF(B33<$BH$31,IF(B33<=35,$BH$4,IF(B34<=45,$BH$5,IF(B34<=50,$BH$6,IF(B34<=55,$BH$7,IF(B34<=60,$BH$8,IF(B34<=65,$BH$9,IF(B34<=70,$BH$10,$BH$11)))))))*'Retirement Dashboard'!$C$12,0) -> 0 | U33: =IF(B33<($BH$57+$BH$30),$BH$56*12,0) -> 0 | V33: =IF(B33<=34,$AN$31,IF(B33<=39,$AN$32,IF(B33<=44,$AN$33,IF(B33<=49,$AN$34,IF(B33<=54,$AN$35,IF(B33<=59,$AN$36,IF(B33<=69,$AN$37,0))))))) -> 0 | W33: =Z32+T33-U33-V33 -> 172712.91 | X33: =IF(B33<=55,$AL$3,$AN$3)*(IF(W33>=20000,20000,W33)) -> 1200 | Y33: =$AL$4*IF(W33>=20000,W33-20000,W33) -> 3817.8228 | Z33: =W33+X33+Y33 -> 177730.73 | AK33: Total CPF Contribution Ceiling | AL33: =(AL31*12)+AL32 -> 198000 | AM33: 40 to 44 | AN33: 50 | AR33: =AR32+1 -> 55 | AS33: =AS32+1 -> 2053 | AT33: =(AT32*103.5%) -> 279002.98 | AU33: =AU32*103.5% -> 558167.74 | AV33: =AV32*103.5% -> 1116335.5 | AW33: =AW32+30 -> 1670 | AX33: =AX32+60 -> 3220 | AY33: =AY32*103.31% -> 8278.0826 | BA33: 58 | BB33: =(100%+$BB$3)*BB32 -> 440.47912 | BC33: =(100%+$BB$3)*BC32 -> 358.65099 | BD33: =(100%+$BD$3)*BD32 -> 1152.558 | BG33: How old you will be then | BH33: =BH31+BH32 -> 90
B34: =B33+1 -> 81 | C34: =IF(B34>=67,$BI$55,C33+(1.0244%*C33)) -> 0 | D34: =IF(B34<=20,$AL$14,IF(B34<=30,$AL$15,IF(B34<=40,$AL$16,IF(B34<=50,$AL$17,IF(B34<=60,$AL$18,IF(B34<=65,$AL$19,IF(B34<=70,$AL$20, IF(B34<=73,$AL$21,IF(B34<=75,$AL$22,IF(B34<=78,$AL$23,IF(B34<=80,$AL$24,IF(B34<=83,$AL$25,IF(B34<=85,$AL$26,IF(B34<=90,$AL$27,$AL$28)))))))))))))) -> 1675 | E34: =IF(B34<=20,$AM$14,IF(B34<=30,$AM$15,IF(B34<=40,$AM$16,IF(B34<=50,$AM$17,IF(B34<=60,$AM$18,IF(B34<=65,$AM$19,IF(B34<=70,$AM$20, IF(B34<=73,$AM$21,IF(B34<=75,$AM$22,IF(B34<=78,$AM$23,IF(B34<=80,$AM$24,IF(B34<=83,$AM$25,IF(B34<=85,$AM$26,IF(B34<=90,$AM$27,$AM$28)))))))))))))) -> 900 | F34: =IF(AND('Retirement Dashboard'!$C$42="Yes", B34<= 'Retirement Dashboard'!$E$42), 600, 0) -> 0 | G34: =IF(B34<'Retirement Dashboard'!$E$6,IF(B34<=35,$BJ$4,IF(B34<=45,$BJ$5,IF(B34<=50,$BJ$6,IF(B34<=55,$BJ$7,IF(B34<=60,$BJ$8,IF(B34<=65,$BJ$9,IF(B34<=70,$BJ$10,$BJ$11)))))))*'Retirement Dashboard'!$C$12,0) -> 0 | H34: =K33-C34-D34-E34-F34+G34 -> 72925 | I34: =$AL$8*H34 -> 2917 | J34: =IF(I34+H34-$AL$35>0,I34+H34-$AL$35,0) -> 342 | K34: =H34+I34-J34 -> 75500 | M34: =IF(J34>=0,J34,0) -> 342 | N34: =IF(B34<$BH$31,IF(B35<=35,$BI$4,IF(B35<=45,$BI$5,IF(B35<=50,$BI$6,IF(B35<=55,$BI$7,IF(B35<=60,$BI$8,IF(B35<=65,$BI$9,IF(B35<=70,$BI$10,$BI$11)))))))*'Retirement Dashboard'!$C$12,0) -> 0 | O34: =R33+N34+M34 -> 627761.18 | P34: =IF(B34<=55,$AL$5,$AN$6)*(IF(O34>=40000,40000,O34)) -> 2400 | Q34: =$AN$7*IF(O34>=40000,O34-40000,0) -> 29388.059 | R34: =O34+P34+Q34 -> 659549.24 | T34: =IF(B34<$BH$31,IF(B34<=35,$BH$4,IF(B35<=45,$BH$5,IF(B35<=50,$BH$6,IF(B35<=55,$BH$7,IF(B35<=60,$BH$8,IF(B35<=65,$BH$9,IF(B35<=70,$BH$10,$BH$11)))))))*'Retirement Dashboard'!$C$12,0) -> 0 | U34: =IF(B34<($BH$57+$BH$30),$BH$56*12,0) -> 0 | V34: =IF(B34<=34,$AN$31,IF(B34<=39,$AN$32,IF(B34<=44,$AN$33,IF(B34<=49,$AN$34,IF(B34<=54,$AN$35,IF(B34<=59,$AN$36,IF(B34<=69,$AN$37,0))))))) -> 0 | W34: =Z33+T34-U34-V34 -> 177730.73 | X34: =IF(B34<=55,$AL$3,$AN$3)*(IF(W34>=20000,20000,W34)) -> 1200 | Y34: =$AL$4*IF(W34>=20000,W34-20000,W34) -> 3943.2684 | Z34: =W34+X34+Y34 -> 182874 | AK34: CPF Cap Annual | AL34: 37740 | AM34: 45 to 49 | AN34: 93 | AR34: =AR33+1 -> 56 | AS34: =AS33+1 -> 2054 | AT34: =(AT33*103.5%) -> 288768.08 | AU34: =AU33*103.5% -> 577703.61 | AV34: =AV33*103.5% -> 1155407.2 | AW34: =AW33+30 -> 1700 | AX34: =AX33+60 -> 3280 | AY34: =AY33*103.31% -> 8552.0871 | BA34: 59 | BB34: =(100%+$BB$3)*BB33 -> 449.28871 | BC34: =(100%+$BB$3)*BC33 -> 365.82401 | BD34: =(100%+$BD$3)*BD33 -> 1175.6092 | BG34: How much will you like to receive per month after retirement | BH34: 4000
B35: =B34+1 -> 82 | C35: =IF(B35>=67,$BI$55,C34+(1.0244%*C34)) -> 0 | D35: =IF(B35<=20,$AL$14,IF(B35<=30,$AL$15,IF(B35<=40,$AL$16,IF(B35<=50,$AL$17,IF(B35<=60,$AL$18,IF(B35<=65,$AL$19,IF(B35<=70,$AL$20, IF(B35<=73,$AL$21,IF(B35<=75,$AL$22,IF(B35<=78,$AL$23,IF(B35<=80,$AL$24,IF(B35<=83,$AL$25,IF(B35<=85,$AL$26,IF(B35<=90,$AL$27,$AL$28)))))))))))))) -> 1675 | E35: =IF(B35<=20,$AM$14,IF(B35<=30,$AM$15,IF(B35<=40,$AM$16,IF(B35<=50,$AM$17,IF(B35<=60,$AM$18,IF(B35<=65,$AM$19,IF(B35<=70,$AM$20, IF(B35<=73,$AM$21,IF(B35<=75,$AM$22,IF(B35<=78,$AM$23,IF(B35<=80,$AM$24,IF(B35<=83,$AM$25,IF(B35<=85,$AM$26,IF(B35<=90,$AM$27,$AM$28)))))))))))))) -> 900 | F35: =IF(AND('Retirement Dashboard'!$C$42="Yes", B35<= 'Retirement Dashboard'!$E$42), 600, 0) -> 0 | G35: =IF(B35<'Retirement Dashboard'!$E$6,IF(B35<=35,$BJ$4,IF(B35<=45,$BJ$5,IF(B35<=50,$BJ$6,IF(B35<=55,$BJ$7,IF(B35<=60,$BJ$8,IF(B35<=65,$BJ$9,IF(B35<=70,$BJ$10,$BJ$11)))))))*'Retirement Dashboard'!$C$12,0) -> 0 | H35: =K34-C35-D35-E35-F35+G35 -> 72925 | I35: =$AL$8*H35 -> 2917 | J35: =IF(I35+H35-$AL$35>0,I35+H35-$AL$35,0) -> 342 | K35: =H35+I35-J35 -> 75500 | M35: =IF(J35>=0,J35,0) -> 342 | N35: =IF(B35<$BH$31,IF(B36<=35,$BI$4,IF(B36<=45,$BI$5,IF(B36<=50,$BI$6,IF(B36<=55,$BI$7,IF(B36<=60,$BI$8,IF(B36<=65,$BI$9,IF(B36<=70,$BI$10,$BI$11)))))))*'Retirement Dashboard'!$C$12,0) -> 0 | O35: =R34+N35+M35 -> 659891.24 | P35: =IF(B35<=55,$AL$5,$AN$6)*(IF(O35>=40000,40000,O35)) -> 2400 | Q35: =$AN$7*IF(O35>=40000,O35-40000,0) -> 30994.562 | R35: =O35+P35+Q35 -> 693285.8 | T35: =IF(B35<$BH$31,IF(B35<=35,$BH$4,IF(B36<=45,$BH$5,IF(B36<=50,$BH$6,IF(B36<=55,$BH$7,IF(B36<=60,$BH$8,IF(B36<=65,$BH$9,IF(B36<=70,$BH$10,$BH$11)))))))*'Retirement Dashboard'!$C$12,0) -> 0 | U35: =IF(B35<($BH$57+$BH$30),$BH$56*12,0) -> 0 | V35: =IF(B35<=34,$AN$31,IF(B35<=39,$AN$32,IF(B35<=44,$AN$33,IF(B35<=49,$AN$34,IF(B35<=54,$AN$35,IF(B35<=59,$AN$36,IF(B35<=69,$AN$37,0))))))) -> 0 | W35: =Z34+T35-U35-V35 -> 182874 | X35: =IF(B35<=55,$AL$3,$AN$3)*(IF(W35>=20000,20000,W35)) -> 1200 | Y35: =$AL$4*IF(W35>=20000,W35-20000,W35) -> 4071.8501 | Z35: =W35+X35+Y35 -> 188145.85 | AK35: MA (BHS) Cap | AL35: 75500 | AM35: 50 to 54 | AN35: 188 | AR35: =AR34+1 -> 57 | AS35: =AS34+1 -> 2055 | AT35: =(AT34*103.5%) -> 298874.96 | AU35: =AU34*103.5% -> 597923.24 | AV35: =AV34*103.5% -> 1195846.5 | AW35: =AW34+30 -> 1730 | AX35: =AX34+60 -> 3340 | AY35: =AY34*103.31% -> 8835.1612 | BA35: 60 | BB35: =(100%+$BB$3)*BB34 -> 458.27448 | BC35: =(100%+$BB$3)*BC34 -> 373.14049 | BD35: =(100%+$BD$3)*BD34 -> 1199.1214 | BG35: Current Gross Wage per Month | BH35: ='[10]Retirement Dashboard'!D9 -> 4300
B36: =B35+1 -> 83 | C36: =IF(B36>=67,$BI$55,C35+(1.0244%*C35)) -> 0 | D36: =IF(B36<=20,$AL$14,IF(B36<=30,$AL$15,IF(B36<=40,$AL$16,IF(B36<=50,$AL$17,IF(B36<=60,$AL$18,IF(B36<=65,$AL$19,IF(B36<=70,$AL$20, IF(B36<=73,$AL$21,IF(B36<=75,$AL$22,IF(B36<=78,$AL$23,IF(B36<=80,$AL$24,IF(B36<=83,$AL$25,IF(B36<=85,$AL$26,IF(B36<=90,$AL$27,$AL$28)))))))))))))) -> 1675 | E36: =IF(B36<=20,$AM$14,IF(B36<=30,$AM$15,IF(B36<=40,$AM$16,IF(B36<=50,$AM$17,IF(B36<=60,$AM$18,IF(B36<=65,$AM$19,IF(B36<=70,$AM$20, IF(B36<=73,$AM$21,IF(B36<=75,$AM$22,IF(B36<=78,$AM$23,IF(B36<=80,$AM$24,IF(B36<=83,$AM$25,IF(B36<=85,$AM$26,IF(B36<=90,$AM$27,$AM$28)))))))))))))) -> 900 | F36: =IF(AND('Retirement Dashboard'!$C$42="Yes", B36<= 'Retirement Dashboard'!$E$42), 600, 0) -> 0 | G36: =IF(B36<'Retirement Dashboard'!$E$6,IF(B36<=35,$BJ$4,IF(B36<=45,$BJ$5,IF(B36<=50,$BJ$6,IF(B36<=55,$BJ$7,IF(B36<=60,$BJ$8,IF(B36<=65,$BJ$9,IF(B36<=70,$BJ$10,$BJ$11)))))))*'Retirement Dashboard'!$C$12,0) -> 0 | H36: =K35-C36-D36-E36-F36+G36 -> 72925 | I36: =$AL$8*H36 -> 2917 | J36: =IF(I36+H36-$AL$35>0,I36+H36-$AL$35,0) -> 342 | K36: =H36+I36-J36 -> 75500 | M36: =IF(J36>=0,J36,0) -> 342 | N36: =IF(B36<$BH$31,IF(B37<=35,$BI$4,IF(B37<=45,$BI$5,IF(B37<=50,$BI$6,IF(B37<=55,$BI$7,IF(B37<=60,$BI$8,IF(B37<=65,$BI$9,IF(B37<=70,$BI$10,$BI$11)))))))*'Retirement Dashboard'!$C$12,0) -> 0 | O36: =R35+N36+M36 -> 693627.8 | P36: =IF(B36<=55,$AL$5,$AN$6)*(IF(O36>=40000,40000,O36)) -> 2400 | Q36: =$AN$7*IF(O36>=40000,O36-40000,0) -> 32681.39 | R36: =O36+P36+Q36 -> 728709.19 | T36: =IF(B36<$BH$31,IF(B36<=35,$BH$4,IF(B37<=45,$BH$5,IF(B37<=50,$BH$6,IF(B37<=55,$BH$7,IF(B37<=60,$BH$8,IF(B37<=65,$BH$9,IF(B37<=70,$BH$10,$BH$11)))))))*'Retirement Dashboard'!$C$12,0) -> 0 | U36: =IF(B36<($BH$57+$BH$30),$BH$56*12,0) -> 0 | V36: =IF(B36<=34,$AN$31,IF(B36<=39,$AN$32,IF(B36<=44,$AN$33,IF(B36<=49,$AN$34,IF(B36<=54,$AN$35,IF(B36<=59,$AN$36,IF(B36<=69,$AN$37,0))))))) -> 0 | W36: =Z35+T36-U36-V36 -> 188145.85 | X36: =IF(B36<=55,$AL$3,$AN$3)*(IF(W36>=20000,20000,W36)) -> 1200 | Y36: =$AL$4*IF(W36>=20000,W36-20000,W36) -> 4203.6463 | Z36: =W36+X36+Y36 -> 193549.5 | AM36: 55 to 59 | AN36: 298 | AR36: =AR35+1 -> 58 | AS36: =AS35+1 -> 2056 | AT36: =(AT35*103.5%) -> 309335.59 | AU36: =AU35*103.5% -> 618850.55 | AV36: =AV35*103.5% -> 1237701.1 | AW36: =AW35+30 -> 1760 | AX36: =AX35+60 -> 3400 | AY36: =AY35*103.31% -> 9127.605 | BA36: 61 | BB36: =(100%+$BB$3)*BB35 -> 467.43997 | BC36: =(100%+$BB$3)*BC35 -> 380.6033 | BD36: =(100%+$BD$3)*BD35 -> 1223.1038 | BG36: TTL mths of salary +AWS+Bonus | BH36: ='[10]Retirement Dashboard'!D10 -> 14
B37: =B36+1 -> 84 | C37: =IF(B37>=67,$BI$55,C36+(1.0244%*C36)) -> 0 | D37: =IF(B37<=20,$AL$14,IF(B37<=30,$AL$15,IF(B37<=40,$AL$16,IF(B37<=50,$AL$17,IF(B37<=60,$AL$18,IF(B37<=65,$AL$19,IF(B37<=70,$AL$20, IF(B37<=73,$AL$21,IF(B37<=75,$AL$22,IF(B37<=78,$AL$23,IF(B37<=80,$AL$24,IF(B37<=83,$AL$25,IF(B37<=85,$AL$26,IF(B37<=90,$AL$27,$AL$28)))))))))))))) -> 1935 | E37: =IF(B37<=20,$AM$14,IF(B37<=30,$AM$15,IF(B37<=40,$AM$16,IF(B37<=50,$AM$17,IF(B37<=60,$AM$18,IF(B37<=65,$AM$19,IF(B37<=70,$AM$20, IF(B37<=73,$AM$21,IF(B37<=75,$AM$22,IF(B37<=78,$AM$23,IF(B37<=80,$AM$24,IF(B37<=83,$AM$25,IF(B37<=85,$AM$26,IF(B37<=90,$AM$27,$AM$28)))))))))))))) -> 900 | F37: =IF(AND('Retirement Dashboard'!$C$42="Yes", B37<= 'Retirement Dashboard'!$E$42), 600, 0) -> 0 | G37: =IF(B37<'Retirement Dashboard'!$E$6,IF(B37<=35,$BJ$4,IF(B37<=45,$BJ$5,IF(B37<=50,$BJ$6,IF(B37<=55,$BJ$7,IF(B37<=60,$BJ$8,IF(B37<=65,$BJ$9,IF(B37<=70,$BJ$10,$BJ$11)))))))*'Retirement Dashboard'!$C$12,0) -> 0 | H37: =K36-C37-D37-E37-F37+G37 -> 72665 | I37: =$AL$8*H37 -> 2906.6 | J37: =IF(I37+H37-$AL$35>0,I37+H37-$AL$35,0) -> 71.6 | K37: =H37+I37-J37 -> 75500 | M37: =IF(J37>=0,J37,0) -> 71.6 | N37: =IF(B37<$BH$31,IF(B38<=35,$BI$4,IF(B38<=45,$BI$5,IF(B38<=50,$BI$6,IF(B38<=55,$BI$7,IF(B38<=60,$BI$8,IF(B38<=65,$BI$9,IF(B38<=70,$BI$10,$BI$11)))))))*'Retirement Dashboard'!$C$12,0) -> 0 | O37: =R36+N37+M37 -> 728780.79 | P37: =IF(B37<=55,$AL$5,$AN$6)*(IF(O37>=40000,40000,O37)) -> 2400 | Q37: =$AN$7*IF(O37>=40000,O37-40000,0) -> 34439.04 | R37: =O37+P37+Q37 -> 765619.83 | T37: =IF(B37<$BH$31,IF(B37<=35,$BH$4,IF(B38<=45,$BH$5,IF(B38<=50,$BH$6,IF(B38<=55,$BH$7,IF(B38<=60,$BH$8,IF(B38<=65,$BH$9,IF(B38<=70,$BH$10,$BH$11)))))))*'Retirement Dashboard'!$C$12,0) -> 0 | U37: =IF(B37<($BH$57+$BH$30),$BH$56*12,0) -> 0 | V37: =IF(B37<=34,$AN$31,IF(B37<=39,$AN$32,IF(B37<=44,$AN$33,IF(B37<=49,$AN$34,IF(B37<=54,$AN$35,IF(B37<=59,$AN$36,IF(B37<=69,$AN$37,0))))))) -> 0 | W37: =Z36+T37-U37-V37 -> 193549.5 | X37: =IF(B37<=55,$AL$3,$AN$3)*(IF(W37>=20000,20000,W37)) -> 1200 | Y37: =$AL$4*IF(W37>=20000,W37-20000,W37) -> 4338.7375 | Z37: =W37+X37+Y37 -> 199088.24 | AM37: 60 to 64 | AN37: 298 | AR37: =AR36+1 -> 59 | AS37: =AS36+1 -> 2057 | AT37: =(AT36*103.5%) -> 320162.33 | AU37: =AU36*103.5% -> 640510.32 | AV37: =AV36*103.5% -> 1281020.6 | AW37: =AW36+30 -> 1790 | AX37: =AX36+60 -> 3460 | AY37: =AY36*103.31% -> 9429.7287 | BA37: 62 | BB37: =(100%+$BB$3)*BB36 -> 476.78877 | BC37: =(100%+$BB$3)*BC36 -> 388.21536 | BD37: =(100%+$BD$3)*BD36 -> 1247.5659 | BG37: Current Gross Wage per Year | BH37: =BH35*BH36 -> 60200
B38: =B37+1 -> 85 | C38: =IF(B38>=67,$BI$55,C37+(1.0244%*C37)) -> 0 | D38: =IF(B38<=20,$AL$14,IF(B38<=30,$AL$15,IF(B38<=40,$AL$16,IF(B38<=50,$AL$17,IF(B38<=60,$AL$18,IF(B38<=65,$AL$19,IF(B38<=70,$AL$20, IF(B38<=73,$AL$21,IF(B38<=75,$AL$22,IF(B38<=78,$AL$23,IF(B38<=80,$AL$24,IF(B38<=83,$AL$25,IF(B38<=85,$AL$26,IF(B38<=90,$AL$27,$AL$28)))))))))))))) -> 1935 | E38: =IF(B38<=20,$AM$14,IF(B38<=30,$AM$15,IF(B38<=40,$AM$16,IF(B38<=50,$AM$17,IF(B38<=60,$AM$18,IF(B38<=65,$AM$19,IF(B38<=70,$AM$20, IF(B38<=73,$AM$21,IF(B38<=75,$AM$22,IF(B38<=78,$AM$23,IF(B38<=80,$AM$24,IF(B38<=83,$AM$25,IF(B38<=85,$AM$26,IF(B38<=90,$AM$27,$AM$28)))))))))))))) -> 900 | F38: =IF(AND('Retirement Dashboard'!$C$42="Yes", B38<= 'Retirement Dashboard'!$E$42), 600, 0) -> 0 | G38: =IF(B38<'Retirement Dashboard'!$E$6,IF(B38<=35,$BJ$4,IF(B38<=45,$BJ$5,IF(B38<=50,$BJ$6,IF(B38<=55,$BJ$7,IF(B38<=60,$BJ$8,IF(B38<=65,$BJ$9,IF(B38<=70,$BJ$10,$BJ$11)))))))*'Retirement Dashboard'!$C$12,0) -> 0 | H38: =K37-C38-D38-E38-F38+G38 -> 72665 | I38: =$AL$8*H38 -> 2906.6 | J38: =IF(I38+H38-$AL$35>0,I38+H38-$AL$35,0) -> 71.6 | K38: =H38+I38-J38 -> 75500 | M38: =IF(J38>=0,J38,0) -> 71.6 | N38: =IF(B38<$BH$31,IF(B39<=35,$BI$4,IF(B39<=45,$BI$5,IF(B39<=50,$BI$6,IF(B39<=55,$BI$7,IF(B39<=60,$BI$8,IF(B39<=65,$BI$9,IF(B39<=70,$BI$10,$BI$11)))))))*'Retirement Dashboard'!$C$12,0) -> 0 | O38: =R37+N38+M38 -> 765691.43 | P38: =IF(B38<=55,$AL$5,$AN$6)*(IF(O38>=40000,40000,O38)) -> 2400 | Q38: =$AN$7*IF(O38>=40000,O38-40000,0) -> 36284.572 | R38: =O38+P38+Q38 -> 804376 | T38: =IF(B38<$BH$31,IF(B38<=35,$BH$4,IF(B39<=45,$BH$5,IF(B39<=50,$BH$6,IF(B39<=55,$BH$7,IF(B39<=60,$BH$8,IF(B39<=65,$BH$9,IF(B39<=70,$BH$10,$BH$11)))))))*'Retirement Dashboard'!$C$12,0) -> 0 | U38: =IF(B38<($BH$57+$BH$30),$BH$56*12,0) -> 0 | V38: =IF(B38<=34,$AN$31,IF(B38<=39,$AN$32,IF(B38<=44,$AN$33,IF(B38<=49,$AN$34,IF(B38<=54,$AN$35,IF(B38<=59,$AN$36,IF(B38<=69,$AN$37,0))))))) -> 0 | W38: =Z37+T38-U38-V38 -> 199088.24 | X38: =IF(B38<=55,$AL$3,$AN$3)*(IF(W38>=20000,20000,W38)) -> 1200 | Y38: =$AL$4*IF(W38>=20000,W38-20000,W38) -> 4477.2059 | Z38: =W38+X38+Y38 -> 204765.44 | AR38: =AR37+1 -> 60 | AS38: =AS37+1 -> 2058 | AT38: =(AT37*103.5%) -> 331368.02 | AU38: =AU37*103.5% -> 662928.18 | AV38: =AV37*103.5% -> 1325856.4 | AW38: =AW37+30 -> 1820 | AX38: =AX37+60 -> 3520 | AY38: =AY37*103.31% -> 9741.8528 | BA38: 63 | BB38: =(100%+$BB$3)*BB37 -> 486.32455 | BC38: =(100%+$BB$3)*BC37 -> 395.97967 | BD38: =(100%+$BD$3)*BD37 -> 1272.5172 | BG38: Years to save till retirement | BH38: =BH31-BH30 -> 13
B39: =B38+1 -> 86 | C39: =IF(B39>=67,$BI$55,C38+(1.0244%*C38)) -> 0 | D39: =IF(B39<=20,$AL$14,IF(B39<=30,$AL$15,IF(B39<=40,$AL$16,IF(B39<=50,$AL$17,IF(B39<=60,$AL$18,IF(B39<=65,$AL$19,IF(B39<=70,$AL$20, IF(B39<=73,$AL$21,IF(B39<=75,$AL$22,IF(B39<=78,$AL$23,IF(B39<=80,$AL$24,IF(B39<=83,$AL$25,IF(B39<=85,$AL$26,IF(B39<=90,$AL$27,$AL$28)))))))))))))) -> 2025 | E39: =IF(B39<=20,$AM$14,IF(B39<=30,$AM$15,IF(B39<=40,$AM$16,IF(B39<=50,$AM$17,IF(B39<=60,$AM$18,IF(B39<=65,$AM$19,IF(B39<=70,$AM$20, IF(B39<=73,$AM$21,IF(B39<=75,$AM$22,IF(B39<=78,$AM$23,IF(B39<=80,$AM$24,IF(B39<=83,$AM$25,IF(B39<=85,$AM$26,IF(B39<=90,$AM$27,$AM$28)))))))))))))) -> 900 | F39: =IF(AND('Retirement Dashboard'!$C$42="Yes", B39<= 'Retirement Dashboard'!$E$42), 600, 0) -> 0 | G39: =IF(B39<'Retirement Dashboard'!$E$6,IF(B39<=35,$BJ$4,IF(B39<=45,$BJ$5,IF(B39<=50,$BJ$6,IF(B39<=55,$BJ$7,IF(B39<=60,$BJ$8,IF(B39<=65,$BJ$9,IF(B39<=70,$BJ$10,$BJ$11)))))))*'Retirement Dashboard'!$C$12,0) -> 0 | H39: =K38-C39-D39-E39-F39+G39 -> 72575 | I39: =$AL$8*H39 -> 2903 | J39: =IF(I39+H39-$AL$35>0,I39+H39-$AL$35,0) -> 0 | K39: =H39+I39-J39 -> 75478 | M39: =IF(J39>=0,J39,0) -> 0 | N39: =IF(B39<$BH$31,IF(B40<=35,$BI$4,IF(B40<=45,$BI$5,IF(B40<=50,$BI$6,IF(B40<=55,$BI$7,IF(B40<=60,$BI$8,IF(B40<=65,$BI$9,IF(B40<=70,$BI$10,$BI$11)))))))*'Retirement Dashboard'!$C$12,0) -> 0 | O39: =R38+N39+M39 -> 804376 | P39: =IF(B39<=55,$AL$5,$AN$6)*(IF(O39>=40000,40000,O39)) -> 2400 | Q39: =$AN$7*IF(O39>=40000,O39-40000,0) -> 38218.8 | R39: =O39+P39+Q39 -> 844994.8 | T39: =IF(B39<$BH$31,IF(B39<=35,$BH$4,IF(B40<=45,$BH$5,IF(B40<=50,$BH$6,IF(B40<=55,$BH$7,IF(B40<=60,$BH$8,IF(B40<=65,$BH$9,IF(B40<=70,$BH$10,$BH$11)))))))*'Retirement Dashboard'!$C$12,0) -> 0 | U39: =IF(B39<($BH$57+$BH$30),$BH$56*12,0) -> 0 | V39: =IF(B39<=34,$AN$31,IF(B39<=39,$AN$32,IF(B39<=44,$AN$33,IF(B39<=49,$AN$34,IF(B39<=54,$AN$35,IF(B39<=59,$AN$36,IF(B39<=69,$AN$37,0))))))) -> 0 | W39: =Z38+T39-U39-V39 -> 204765.44 | X39: =IF(B39<=55,$AL$3,$AN$3)*(IF(W39>=20000,20000,W39)) -> 1200 | Y39: =$AL$4*IF(W39>=20000,W39-20000,W39) -> 4619.1361 | Z39: =W39+X39+Y39 -> 210584.58 | AR39: =AR38+1 -> 61 | AS39: =AS38+1 -> 2059 | AT39: =(AT38*103.5%) -> 342965.9 | AU39: =AU38*103.5% -> 686130.67 | AV39: =AV38*103.5% -> 1372261.3 | AW39: =AW38+30 -> 1850 | AX39: =AX38+60 -> 3580 | AY39: =AY38*103.31% -> 10064.308 | BA39: 64 | BB39: =(100%+$BB$3)*BB38 -> 496.05104 | BC39: =(100%+$BB$3)*BC38 -> 403.89926 | BD39: =(100%+$BD$3)*BD38 -> 1297.9675 | BG39: OA Band | BH39: =IF(BH30<=35,BH4,IF(BH30<=45,BH5,IF(BH30<=50,BH6,IF(BH30<=55,BH7,IF(BH30<=60,BH8,IF(BH30<=65,BH9,IF(BH30<=70,BH10,BH11))))))) -> 0.150035
B40: =B39+1 -> 87 | C40: =IF(B40>=67,$BI$55,C39+(1.0244%*C39)) -> 0 | D40: =IF(B40<=20,$AL$14,IF(B40<=30,$AL$15,IF(B40<=40,$AL$16,IF(B40<=50,$AL$17,IF(B40<=60,$AL$18,IF(B40<=65,$AL$19,IF(B40<=70,$AL$20, IF(B40<=73,$AL$21,IF(B40<=75,$AL$22,IF(B40<=78,$AL$23,IF(B40<=80,$AL$24,IF(B40<=83,$AL$25,IF(B40<=85,$AL$26,IF(B40<=90,$AL$27,$AL$28)))))))))))))) -> 2025 | E40: =IF(B40<=20,$AM$14,IF(B40<=30,$AM$15,IF(B40<=40,$AM$16,IF(B40<=50,$AM$17,IF(B40<=60,$AM$18,IF(B40<=65,$AM$19,IF(B40<=70,$AM$20, IF(B40<=73,$AM$21,IF(B40<=75,$AM$22,IF(B40<=78,$AM$23,IF(B40<=80,$AM$24,IF(B40<=83,$AM$25,IF(B40<=85,$AM$26,IF(B40<=90,$AM$27,$AM$28)))))))))))))) -> 900 | F40: =IF(AND('Retirement Dashboard'!$C$42="Yes", B40<= 'Retirement Dashboard'!$E$42), 600, 0) -> 0 | G40: =IF(B40<'Retirement Dashboard'!$E$6,IF(B40<=35,$BJ$4,IF(B40<=45,$BJ$5,IF(B40<=50,$BJ$6,IF(B40<=55,$BJ$7,IF(B40<=60,$BJ$8,IF(B40<=65,$BJ$9,IF(B40<=70,$BJ$10,$BJ$11)))))))*'Retirement Dashboard'!$C$12,0) -> 0 | H40: =K39-C40-D40-E40-F40+G40 -> 72553 | I40: =$AL$8*H40 -> 2902.12 | J40: =IF(I40+H40-$AL$35>0,I40+H40-$AL$35,0) -> 0 | K40: =H40+I40-J40 -> 75455.12 | M40: =IF(J40>=0,J40,0) -> 0 | N40: =IF(B40<$BH$31,IF(B41<=35,$BI$4,IF(B41<=45,$BI$5,IF(B41<=50,$BI$6,IF(B41<=55,$BI$7,IF(B41<=60,$BI$8,IF(B41<=65,$BI$9,IF(B41<=70,$BI$10,$BI$11)))))))*'Retirement Dashboard'!$C$12,0) -> 0 | O40: =R39+N40+M40 -> 844994.8 | P40: =IF(B40<=55,$AL$5,$AN$6)*(IF(O40>=40000,40000,O40)) -> 2400 | Q40: =$AN$7*IF(O40>=40000,O40-40000,0) -> 40249.74 | R40: =O40+P40+Q40 -> 887644.54 | T40: =IF(B40<$BH$31,IF(B40<=35,$BH$4,IF(B41<=45,$BH$5,IF(B41<=50,$BH$6,IF(B41<=55,$BH$7,IF(B41<=60,$BH$8,IF(B41<=65,$BH$9,IF(B41<=70,$BH$10,$BH$11)))))))*'Retirement Dashboard'!$C$12,0) -> 0 | U40: =IF(B40<($BH$57+$BH$30),$BH$56*12,0) -> 0 | V40: =IF(B40<=34,$AN$31,IF(B40<=39,$AN$32,IF(B40<=44,$AN$33,IF(B40<=49,$AN$34,IF(B40<=54,$AN$35,IF(B40<=59,$AN$36,IF(B40<=69,$AN$37,0))))))) -> 0 | W40: =Z39+T40-U40-V40 -> 210584.58 | X40: =IF(B40<=55,$AL$3,$AN$3)*(IF(W40>=20000,20000,W40)) -> 1200 | Y40: =$AL$4*IF(W40>=20000,W40-20000,W40) -> 4764.6145 | Z40: =W40+X40+Y40 -> 216549.19 | AR40: =AR39+1 -> 62 | AS40: =AS39+1 -> 2060 | AT40: =(AT39*103.5%) -> 354969.7 | AU40: =AU39*103.5% -> 710145.24 | AV40: =AV39*103.5% -> 1420290.5 | AW40: =AW39+30 -> 1880 | AX40: =AX39+60 -> 3640 | AY40: =AY39*103.31% -> 10397.437 | BA40: 65 | BB40: =(100%+$BB$3)*BB39 -> 505.97206 | BC40: =(100%+$BB$3)*BC39 -> 411.97725 | BD40: =(100%+$BD$3)*BD39 -> 1323.9269 | BG40: SA Band | BH40: =IF($BH$30<=35,BI4,IF($BH$30<=45,BI5,IF($BH$30<=50,BI6,IF($BH$30<=55,BI7,IF($BH$30<=60,BI8,IF($BH$30<=65,BI9,IF($BH$30<=70,BI10,BI11))))))) -> 0.114996
B41: =B40+1 -> 88 | C41: =IF(B41>=67,$BI$55,C40+(1.0244%*C40)) -> 0 | D41: =IF(B41<=20,$AL$14,IF(B41<=30,$AL$15,IF(B41<=40,$AL$16,IF(B41<=50,$AL$17,IF(B41<=60,$AL$18,IF(B41<=65,$AL$19,IF(B41<=70,$AL$20, IF(B41<=73,$AL$21,IF(B41<=75,$AL$22,IF(B41<=78,$AL$23,IF(B41<=80,$AL$24,IF(B41<=83,$AL$25,IF(B41<=85,$AL$26,IF(B41<=90,$AL$27,$AL$28)))))))))))))) -> 2025 | E41: =IF(B41<=20,$AM$14,IF(B41<=30,$AM$15,IF(B41<=40,$AM$16,IF(B41<=50,$AM$17,IF(B41<=60,$AM$18,IF(B41<=65,$AM$19,IF(B41<=70,$AM$20, IF(B41<=73,$AM$21,IF(B41<=75,$AM$22,IF(B41<=78,$AM$23,IF(B41<=80,$AM$24,IF(B41<=83,$AM$25,IF(B41<=85,$AM$26,IF(B41<=90,$AM$27,$AM$28)))))))))))))) -> 900 | F41: =IF(AND('Retirement Dashboard'!$C$42="Yes", B41<= 'Retirement Dashboard'!$E$42), 600, 0) -> 0 | G41: =IF(B41<'Retirement Dashboard'!$E$6,IF(B41<=35,$BJ$4,IF(B41<=45,$BJ$5,IF(B41<=50,$BJ$6,IF(B41<=55,$BJ$7,IF(B41<=60,$BJ$8,IF(B41<=65,$BJ$9,IF(B41<=70,$BJ$10,$BJ$11)))))))*'Retirement Dashboard'!$C$12,0) -> 0 | H41: =K40-C41-D41-E41-F41+G41 -> 72530.12 | I41: =$AL$8*H41 -> 2901.2048 | J41: =IF(I41+H41-$AL$35>0,I41+H41-$AL$35,0) -> 0 | K41: =H41+I41-J41 -> 75431.325 | M41: =IF(J41>=0,J41,0) -> 0 | N41: =IF(B41<$BH$31,IF(B42<=35,$BI$4,IF(B42<=45,$BI$5,IF(B42<=50,$BI$6,IF(B42<=55,$BI$7,IF(B42<=60,$BI$8,IF(B42<=65,$BI$9,IF(B42<=70,$BI$10,$BI$11)))))))*'Retirement Dashboard'!$C$12,0) -> 0 | O41: =R40+N41+M41 -> 887644.54 | P41: =IF(B41<=55,$AL$5,$AN$6)*(IF(O41>=40000,40000,O41)) -> 2400 | Q41: =$AN$7*IF(O41>=40000,O41-40000,0) -> 42382.227 | R41: =O41+P41+Q41 -> 932426.77 | T41: =IF(B41<$BH$31,IF(B41<=35,$BH$4,IF(B42<=45,$BH$5,IF(B42<=50,$BH$6,IF(B42<=55,$BH$7,IF(B42<=60,$BH$8,IF(B42<=65,$BH$9,IF(B42<=70,$BH$10,$BH$11)))))))*'Retirement Dashboard'!$C$12,0) -> 0 | U41: =IF(B41<($BH$57+$BH$30),$BH$56*12,0) -> 0 | V41: =IF(B41<=34,$AN$31,IF(B41<=39,$AN$32,IF(B41<=44,$AN$33,IF(B41<=49,$AN$34,IF(B41<=54,$AN$35,IF(B41<=59,$AN$36,IF(B41<=69,$AN$37,0))))))) -> 0 | W41: =Z40+T41-U41-V41 -> 216549.19 | X41: =IF(B41<=55,$AL$3,$AN$3)*(IF(W41>=20000,20000,W41)) -> 1200 | Y41: =$AL$4*IF(W41>=20000,W41-20000,W41) -> 4913.7298 | Z41: =W41+X41+Y41 -> 222662.92 | AR41: =AR40+1 -> 63 | AS41: =AS40+1 -> 2061 | AT41: =(AT40+3900) -> 358869.7 | AU41: =AU40*103.5% -> 735000.33 | AV41: =AV40*103.5% -> 1470000.7 | AW41: =AW40+30 -> 1910 | AX41: =AX40+60 -> 3700 | AY41: =AY40*103.31% -> 10741.592 | BA41: 66 | BB41: =(100%+$BB$3)*BB40 -> 516.0915 | BC41: =(100%+$BB$3)*BC40 -> 420.21679 | BD41: =(100%+$BD$3)*BD40 -> 1350.4054 | BG41: MA Band | BH41: =IF($BH$30<=35,BJ4,IF($BH$30<=45,BJ5,IF($BH$30<=50,BJ6,IF($BH$30<=55,BJ7,IF($BH$30<=60,BJ8,IF($BH$30<=65,BJ9,IF($BH$30<=70,BJ10,BJ11))))))) -> 0.104969
B42: =B41+1 -> 89 | C42: =IF(B42>=67,$BI$55,C41+(1.0244%*C41)) -> 0 | D42: =IF(B42<=20,$AL$14,IF(B42<=30,$AL$15,IF(B42<=40,$AL$16,IF(B42<=50,$AL$17,IF(B42<=60,$AL$18,IF(B42<=65,$AL$19,IF(B42<=70,$AL$20, IF(B42<=73,$AL$21,IF(B42<=75,$AL$22,IF(B42<=78,$AL$23,IF(B42<=80,$AL$24,IF(B42<=83,$AL$25,IF(B42<=85,$AL$26,IF(B42<=90,$AL$27,$AL$28)))))))))))))) -> 2025 | E42: =IF(B42<=20,$AM$14,IF(B42<=30,$AM$15,IF(B42<=40,$AM$16,IF(B42<=50,$AM$17,IF(B42<=60,$AM$18,IF(B42<=65,$AM$19,IF(B42<=70,$AM$20, IF(B42<=73,$AM$21,IF(B42<=75,$AM$22,IF(B42<=78,$AM$23,IF(B42<=80,$AM$24,IF(B42<=83,$AM$25,IF(B42<=85,$AM$26,IF(B42<=90,$AM$27,$AM$28)))))))))))))) -> 900 | F42: =IF(AND('Retirement Dashboard'!$C$42="Yes", B42<= 'Retirement Dashboard'!$E$42), 600, 0) -> 0 | G42: =IF(B42<'Retirement Dashboard'!$E$6,IF(B42<=35,$BJ$4,IF(B42<=45,$BJ$5,IF(B42<=50,$BJ$6,IF(B42<=55,$BJ$7,IF(B42<=60,$BJ$8,IF(B42<=65,$BJ$9,IF(B42<=70,$BJ$10,$BJ$11)))))))*'Retirement Dashboard'!$C$12,0) -> 0 | H42: =K41-C42-D42-E42-F42+G42 -> 72506.325 | I42: =$AL$8*H42 -> 2900.253 | J42: =IF(I42+H42-$AL$35>0,I42+H42-$AL$35,0) -> 0 | K42: =H42+I42-J42 -> 75406.578 | M42: =IF(J42>=0,J42,0) -> 0 | N42: =IF(B42<$BH$31,IF(B43<=35,$BI$4,IF(B43<=45,$BI$5,IF(B43<=50,$BI$6,IF(B43<=55,$BI$7,IF(B43<=60,$BI$8,IF(B43<=65,$BI$9,IF(B43<=70,$BI$10,$BI$11)))))))*'Retirement Dashboard'!$C$12,0) -> 0 | O42: =R41+N42+M42 -> 932426.77 | P42: =IF(B42<=55,$AL$5,$AN$6)*(IF(O42>=40000,40000,O42)) -> 2400 | Q42: =$AN$7*IF(O42>=40000,O42-40000,0) -> 44621.339 | R42: =O42+P42+Q42 -> 979448.11 | T42: =IF(B42<$BH$31,IF(B42<=35,$BH$4,IF(B43<=45,$BH$5,IF(B43<=50,$BH$6,IF(B43<=55,$BH$7,IF(B43<=60,$BH$8,IF(B43<=65,$BH$9,IF(B43<=70,$BH$10,$BH$11)))))))*'Retirement Dashboard'!$C$12,0) -> 0 | U42: =IF(B42<($BH$57+$BH$30),$BH$56*12,0) -> 0 | V42: =IF(B42<=34,$AN$31,IF(B42<=39,$AN$32,IF(B42<=44,$AN$33,IF(B42<=49,$AN$34,IF(B42<=54,$AN$35,IF(B42<=59,$AN$36,IF(B42<=69,$AN$37,0))))))) -> 0 | W42: =Z41+T42-U42-V42 -> 222662.92 | X42: =IF(B42<=55,$AL$3,$AN$3)*(IF(W42>=20000,20000,W42)) -> 1200 | Y42: =$AL$4*IF(W42>=20000,W42-20000,W42) -> 5066.5731 | Z42: =W42+X42+Y42 -> 228929.5 | BA42: 67 | BB42: =(100%+$BB$3)*BB41 -> 526.41333 | BC42: =(100%+$BB$3)*BC41 -> 428.62113 | BD42: =(100%+$BD$3)*BD41 -> 1377.4135 | BG42: Current MA | BH42: {='[10]Retirement Dashboard'!D17:F17} -> 70000 | BI42: 0 | BJ42: 0
B43: =B42+1 -> 90 | C43: =IF(B43>=67,$BI$55,C42+(1.0244%*C42)) -> 0 | D43: =IF(B43<=20,$AL$14,IF(B43<=30,$AL$15,IF(B43<=40,$AL$16,IF(B43<=50,$AL$17,IF(B43<=60,$AL$18,IF(B43<=65,$AL$19,IF(B43<=70,$AL$20, IF(B43<=73,$AL$21,IF(B43<=75,$AL$22,IF(B43<=78,$AL$23,IF(B43<=80,$AL$24,IF(B43<=83,$AL$25,IF(B43<=85,$AL$26,IF(B43<=90,$AL$27,$AL$28)))))))))))))) -> 2025 | E43: =IF(B43<=20,$AM$14,IF(B43<=30,$AM$15,IF(B43<=40,$AM$16,IF(B43<=50,$AM$17,IF(B43<=60,$AM$18,IF(B43<=65,$AM$19,IF(B43<=70,$AM$20, IF(B43<=73,$AM$21,IF(B43<=75,$AM$22,IF(B43<=78,$AM$23,IF(B43<=80,$AM$24,IF(B43<=83,$AM$25,IF(B43<=85,$AM$26,IF(B43<=90,$AM$27,$AM$28)))))))))))))) -> 900 | F43: =IF(AND('Retirement Dashboard'!$C$42="Yes", B43<= 'Retirement Dashboard'!$E$42), 600, 0) -> 0 | G43: =IF(B43<'Retirement Dashboard'!$E$6,IF(B43<=35,$BJ$4,IF(B43<=45,$BJ$5,IF(B43<=50,$BJ$6,IF(B43<=55,$BJ$7,IF(B43<=60,$BJ$8,IF(B43<=65,$BJ$9,IF(B43<=70,$BJ$10,$BJ$11)))))))*'Retirement Dashboard'!$C$12,0) -> 0 | H43: =K42-C43-D43-E43-F43+G43 -> 72481.578 | I43: =$AL$8*H43 -> 2899.2631 | J43: =IF(I43+H43-$AL$35>0,I43+H43-$AL$35,0) -> 0 | K43: =H43+I43-J43 -> 75380.841 | M43: =IF(J43>=0,J43,0) -> 0 | N43: =IF(B43<$BH$31,IF(B44<=35,$BI$4,IF(B44<=45,$BI$5,IF(B44<=50,$BI$6,IF(B44<=55,$BI$7,IF(B44<=60,$BI$8,IF(B44<=65,$BI$9,IF(B44<=70,$BI$10,$BI$11)))))))*'Retirement Dashboard'!$C$12,0) -> 0 | O43: =R42+N43+M43 -> 979448.11 | P43: =IF(B43<=55,$AL$5,$AN$6)*(IF(O43>=40000,40000,O43)) -> 2400 | Q43: =$AN$7*IF(O43>=40000,O43-40000,0) -> 46972.406 | R43: =O43+P43+Q43 -> 1028820.5 | T43: =IF(B43<$BH$31,IF(B43<=35,$BH$4,IF(B44<=45,$BH$5,IF(B44<=50,$BH$6,IF(B44<=55,$BH$7,IF(B44<=60,$BH$8,IF(B44<=65,$BH$9,IF(B44<=70,$BH$10,$BH$11)))))))*'Retirement Dashboard'!$C$12,0) -> 0 | U43: =IF(B43<($BH$57+$BH$30),$BH$56*12,0) -> 0 | V43: =IF(B43<=34,$AN$31,IF(B43<=39,$AN$32,IF(B43<=44,$AN$33,IF(B43<=49,$AN$34,IF(B43<=54,$AN$35,IF(B43<=59,$AN$36,IF(B43<=69,$AN$37,0))))))) -> 0 | W43: =Z42+T43-U43-V43 -> 228929.5 | X43: =IF(B43<=55,$AL$3,$AN$3)*(IF(W43>=20000,20000,W43)) -> 1200 | Y43: =$AL$4*IF(W43>=20000,W43-20000,W43) -> 5223.2374 | Z43: =W43+X43+Y43 -> 235352.73 | AR43: Age | AS43: MA | AT43: OA | AU43: SA | AV43: RA | AW43: BRS | AX43: FRS | AY43: ERS | BG43: Current OA | BH43: {='[10]Retirement Dashboard'!D15:F15} -> 20000 | BI43: 0 | BJ43: 0
B44: =B43+1 -> 91 | C44: =IF(B44>=67,$BI$55,C43+(1.0244%*C43)) -> 0 | D44: =IF(B44<=20,$AL$14,IF(B44<=30,$AL$15,IF(B44<=40,$AL$16,IF(B44<=50,$AL$17,IF(B44<=60,$AL$18,IF(B44<=65,$AL$19,IF(B44<=70,$AL$20, IF(B44<=73,$AL$21,IF(B44<=75,$AL$22,IF(B44<=78,$AL$23,IF(B44<=80,$AL$24,IF(B44<=83,$AL$25,IF(B44<=85,$AL$26,IF(B44<=90,$AL$27,$AL$28)))))))))))))) -> 2055 | E44: =IF(B44<=20,$AM$14,IF(B44<=30,$AM$15,IF(B44<=40,$AM$16,IF(B44<=50,$AM$17,IF(B44<=60,$AM$18,IF(B44<=65,$AM$19,IF(B44<=70,$AM$20, IF(B44<=73,$AM$21,IF(B44<=75,$AM$22,IF(B44<=78,$AM$23,IF(B44<=80,$AM$24,IF(B44<=83,$AM$25,IF(B44<=85,$AM$26,IF(B44<=90,$AM$27,$AM$28)))))))))))))) -> 900 | F44: =IF(AND('Retirement Dashboard'!$C$42="Yes", B44<= 'Retirement Dashboard'!$E$42), 600, 0) -> 0 | G44: =IF(B44<'Retirement Dashboard'!$E$6,IF(B44<=35,$BJ$4,IF(B44<=45,$BJ$5,IF(B44<=50,$BJ$6,IF(B44<=55,$BJ$7,IF(B44<=60,$BJ$8,IF(B44<=65,$BJ$9,IF(B44<=70,$BJ$10,$BJ$11)))))))*'Retirement Dashboard'!$C$12,0) -> 0 | H44: =K43-C44-D44-E44-F44+G44 -> 72425.841 | I44: =$AL$8*H44 -> 2897.0336 | J44: =IF(I44+H44-$AL$35>0,I44+H44-$AL$35,0) -> 0 | K44: =H44+I44-J44 -> 75322.875 | M44: =IF(J44>=0,J44,0) -> 0 | N44: =IF(B44<$BH$31,IF(B45<=35,$BI$4,IF(B45<=45,$BI$5,IF(B45<=50,$BI$6,IF(B45<=55,$BI$7,IF(B45<=60,$BI$8,IF(B45<=65,$BI$9,IF(B45<=70,$BI$10,$BI$11)))))))*'Retirement Dashboard'!$C$12,0) -> 0 | O44: =R43+N44+M44 -> 1028820.5 | P44: =IF(B44<=55,$AL$5,$AN$6)*(IF(O44>=40000,40000,O44)) -> 2400 | Q44: =$AN$7*IF(O44>=40000,O44-40000,0) -> 49441.026 | R44: =O44+P44+Q44 -> 1080661.5 | T44: =IF(B44<$BH$31,IF(B44<=35,$BH$4,IF(B45<=45,$BH$5,IF(B45<=50,$BH$6,IF(B45<=55,$BH$7,IF(B45<=60,$BH$8,IF(B45<=65,$BH$9,IF(B45<=70,$BH$10,$BH$11)))))))*'Retirement Dashboard'!$C$12,0) -> 0 | U44: =IF(B44<($BH$57+$BH$30),$BH$56*12,0) -> 0 | V44: =IF(B44<=34,$AN$31,IF(B44<=39,$AN$32,IF(B44<=44,$AN$33,IF(B44<=49,$AN$34,IF(B44<=54,$AN$35,IF(B44<=59,$AN$36,IF(B44<=69,$AN$37,0))))))) -> 0 | W44: =Z43+T44-U44-V44 -> 235352.73 | X44: =IF(B44<=55,$AL$3,$AN$3)*(IF(W44>=20000,20000,W44)) -> 1200 | Y44: =$AL$4*IF(W44>=20000,W44-20000,W44) -> 5383.8183 | Z44: =W44+X44+Y44 -> 241936.55 | AR44: =BH31 -> 65 | AS44: =VLOOKUP($AR$44,$B$3:$Z$56,10,) -> 75500 | AT44: =VLOOKUP(AR44,$B$3:$Z$56,25,) -> 115199.08 | AU44: =VLOOKUP(AR44,$B$3:$Z$56,17,) -> 289508.25 | BG44: Current SA | BH44: {='[10]Retirement Dashboard'!D16:F16} -> 200000 | BI44: 0 | BJ44: 0
B45: =B44+1 -> 92 | C45: =IF(B45>=67,$BI$55,C44+(1.0244%*C44)) -> 0 | D45: =IF(B45<=20,$AL$14,IF(B45<=30,$AL$15,IF(B45<=40,$AL$16,IF(B45<=50,$AL$17,IF(B45<=60,$AL$18,IF(B45<=65,$AL$19,IF(B45<=70,$AL$20, IF(B45<=73,$AL$21,IF(B45<=75,$AL$22,IF(B45<=78,$AL$23,IF(B45<=80,$AL$24,IF(B45<=83,$AL$25,IF(B45<=85,$AL$26,IF(B45<=90,$AL$27,$AL$28)))))))))))))) -> 2055 | E45: =IF(B45<=20,$AM$14,IF(B45<=30,$AM$15,IF(B45<=40,$AM$16,IF(B45<=50,$AM$17,IF(B45<=60,$AM$18,IF(B45<=65,$AM$19,IF(B45<=70,$AM$20, IF(B45<=73,$AM$21,IF(B45<=75,$AM$22,IF(B45<=78,$AM$23,IF(B45<=80,$AM$24,IF(B45<=83,$AM$25,IF(B45<=85,$AM$26,IF(B45<=90,$AM$27,$AM$28)))))))))))))) -> 900 | F45: =IF(AND('Retirement Dashboard'!$C$42="Yes", B45<= 'Retirement Dashboard'!$E$42), 600, 0) -> 0 | G45: =IF(B45<'Retirement Dashboard'!$E$6,IF(B45<=35,$BJ$4,IF(B45<=45,$BJ$5,IF(B45<=50,$BJ$6,IF(B45<=55,$BJ$7,IF(B45<=60,$BJ$8,IF(B45<=65,$BJ$9,IF(B45<=70,$BJ$10,$BJ$11)))))))*'Retirement Dashboard'!$C$12,0) -> 0 | H45: =K44-C45-D45-E45-F45+G45 -> 72367.875 | I45: =$AL$8*H45 -> 2894.715 | J45: =IF(I45+H45-$AL$35>0,I45+H45-$AL$35,0) -> 0 | K45: =H45+I45-J45 -> 75262.59 | M45: =IF(J45>=0,J45,0) -> 0 | N45: =IF(B45<$BH$31,IF(B46<=35,$BI$4,IF(B46<=45,$BI$5,IF(B46<=50,$BI$6,IF(B46<=55,$BI$7,IF(B46<=60,$BI$8,IF(B46<=65,$BI$9,IF(B46<=70,$BI$10,$BI$11)))))))*'Retirement Dashboard'!$C$12,0) -> 0 | O45: =R44+N45+M45 -> 1080661.5 | P45: =IF(B45<=55,$AL$5,$AN$6)*(IF(O45>=40000,40000,O45)) -> 2400 | Q45: =$AN$7*IF(O45>=40000,O45-40000,0) -> 52033.077 | R45: =O45+P45+Q45 -> 1135094.6 | T45: =IF(B45<$BH$31,IF(B45<=35,$BH$4,IF(B46<=45,$BH$5,IF(B46<=50,$BH$6,IF(B46<=55,$BH$7,IF(B46<=60,$BH$8,IF(B46<=65,$BH$9,IF(B46<=70,$BH$10,$BH$11)))))))*'Retirement Dashboard'!$C$12,0) -> 0 | U45: =IF(B45<($BH$57+$BH$30),$BH$56*12,0) -> 0 | V45: =IF(B45<=34,$AN$31,IF(B45<=39,$AN$32,IF(B45<=44,$AN$33,IF(B45<=49,$AN$34,IF(B45<=54,$AN$35,IF(B45<=59,$AN$36,IF(B45<=69,$AN$37,0))))))) -> 0 | W45: =Z44+T45-U45-V45 -> 241936.55 | X45: =IF(B45<=55,$AL$3,$AN$3)*(IF(W45>=20000,20000,W45)) -> 1200 | Y45: =$AL$4*IF(W45>=20000,W45-20000,W45) -> 5548.4138 | Z45: =W45+X45+Y45 -> 248684.97 | AR45: 55 | AS45: =VLOOKUP($AR$45,$B$3:$Z$56,10,) -> 62168.79 | AT45: =VLOOKUP(AR45,$B$3:$Z$56,25,) -> 56006.299 | AU45: =VLOOKUP(AR45,$B$3:$Z$56,17,) -> 100550.71 | AV45: =AU45+AT45 -> 156557.01 | AW45: =VLOOKUP(AR45,$AR$5:$AY$41,3,) -> 279002.98 | AX45: =VLOOKUP(AR45,$AR$5:$AY$41,4,) -> 558167.74 | AY45: =VLOOKUP(AR45,$AR$5:$AY$41,5,) -> 1116335.5 | BG45: CPFL Payout | BH45: =IF(AS51="Yes",AT51,0) -> 0
B46: =B45+1 -> 93 | C46: =IF(B46>=67,$BI$55,C45+(1.0244%*C45)) -> 0 | D46: =IF(B46<=20,$AL$14,IF(B46<=30,$AL$15,IF(B46<=40,$AL$16,IF(B46<=50,$AL$17,IF(B46<=60,$AL$18,IF(B46<=65,$AL$19,IF(B46<=70,$AL$20, IF(B46<=73,$AL$21,IF(B46<=75,$AL$22,IF(B46<=78,$AL$23,IF(B46<=80,$AL$24,IF(B46<=83,$AL$25,IF(B46<=85,$AL$26,IF(B46<=90,$AL$27,$AL$28)))))))))))))) -> 2055 | E46: =IF(B46<=20,$AM$14,IF(B46<=30,$AM$15,IF(B46<=40,$AM$16,IF(B46<=50,$AM$17,IF(B46<=60,$AM$18,IF(B46<=65,$AM$19,IF(B46<=70,$AM$20, IF(B46<=73,$AM$21,IF(B46<=75,$AM$22,IF(B46<=78,$AM$23,IF(B46<=80,$AM$24,IF(B46<=83,$AM$25,IF(B46<=85,$AM$26,IF(B46<=90,$AM$27,$AM$28)))))))))))))) -> 900 | F46: =IF(AND('Retirement Dashboard'!$C$42="Yes", B46<= 'Retirement Dashboard'!$E$42), 600, 0) -> 0 | G46: =IF(B46<'Retirement Dashboard'!$E$6,IF(B46<=35,$BJ$4,IF(B46<=45,$BJ$5,IF(B46<=50,$BJ$6,IF(B46<=55,$BJ$7,IF(B46<=60,$BJ$8,IF(B46<=65,$BJ$9,IF(B46<=70,$BJ$10,$BJ$11)))))))*'Retirement Dashboard'!$C$12,0) -> 0 | H46: =K45-C46-D46-E46-F46+G46 -> 72307.59 | I46: =$AL$8*H46 -> 2892.3036 | J46: =IF(I46+H46-$AL$35>0,I46+H46-$AL$35,0) -> 0 | K46: =H46+I46-J46 -> 75199.893 | M46: =IF(J46>=0,J46,0) -> 0 | N46: =IF(B46<$BH$31,IF(B47<=35,$BI$4,IF(B47<=45,$BI$5,IF(B47<=50,$BI$6,IF(B47<=55,$BI$7,IF(B47<=60,$BI$8,IF(B47<=65,$BI$9,IF(B47<=70,$BI$10,$BI$11)))))))*'Retirement Dashboard'!$C$12,0) -> 0 | O46: =R45+N46+M46 -> 1135094.6 | P46: =IF(B46<=55,$AL$5,$AN$6)*(IF(O46>=40000,40000,O46)) -> 2400 | Q46: =$AN$7*IF(O46>=40000,O46-40000,0) -> 54754.731 | R46: =O46+P46+Q46 -> 1192249.3 | T46: =IF(B46<$BH$31,IF(B46<=35,$BH$4,IF(B47<=45,$BH$5,IF(B47<=50,$BH$6,IF(B47<=55,$BH$7,IF(B47<=60,$BH$8,IF(B47<=65,$BH$9,IF(B47<=70,$BH$10,$BH$11)))))))*'Retirement Dashboard'!$C$12,0) -> 0 | U46: =IF(B46<($BH$57+$BH$30),$BH$56*12,0) -> 0 | V46: =IF(B46<=34,$AN$31,IF(B46<=39,$AN$32,IF(B46<=44,$AN$33,IF(B46<=49,$AN$34,IF(B46<=54,$AN$35,IF(B46<=59,$AN$36,IF(B46<=69,$AN$37,0))))))) -> 0 | W46: =Z45+T46-U46-V46 -> 248684.97 | X46: =IF(B46<=55,$AL$3,$AN$3)*(IF(W46>=20000,20000,W46)) -> 1200 | Y46: =$AL$4*IF(W46>=20000,W46-20000,W46) -> 5717.1241 | Z46: =W46+X46+Y46 -> 255602.09 | AR46: 65 | AS46: =VLOOKUP($AR$46,$B$59:$Z$106,10,) -> 75500 | AT46: =VLOOKUP(AR46,$B$3:$Z$56,25,) -> 115199.08 | AU46: =VLOOKUP(AR46,$B$3:$Z$56,17,) -> 289508.25 | AV46: =AU46+AT46 -> 404707.33
B47: =B46+1 -> 94 | C47: =IF(B47>=67,$BI$55,C46+(1.0244%*C46)) -> 0 | D47: =IF(B47<=20,$AL$14,IF(B47<=30,$AL$15,IF(B47<=40,$AL$16,IF(B47<=50,$AL$17,IF(B47<=60,$AL$18,IF(B47<=65,$AL$19,IF(B47<=70,$AL$20, IF(B47<=73,$AL$21,IF(B47<=75,$AL$22,IF(B47<=78,$AL$23,IF(B47<=80,$AL$24,IF(B47<=83,$AL$25,IF(B47<=85,$AL$26,IF(B47<=90,$AL$27,$AL$28)))))))))))))) -> 2055 | E47: =IF(B47<=20,$AM$14,IF(B47<=30,$AM$15,IF(B47<=40,$AM$16,IF(B47<=50,$AM$17,IF(B47<=60,$AM$18,IF(B47<=65,$AM$19,IF(B47<=70,$AM$20, IF(B47<=73,$AM$21,IF(B47<=75,$AM$22,IF(B47<=78,$AM$23,IF(B47<=80,$AM$24,IF(B47<=83,$AM$25,IF(B47<=85,$AM$26,IF(B47<=90,$AM$27,$AM$28)))))))))))))) -> 900 | F47: =IF(AND('Retirement Dashboard'!$C$42="Yes", B47<= 'Retirement Dashboard'!$E$42), 600, 0) -> 0 | G47: =IF(B47<'Retirement Dashboard'!$E$6,IF(B47<=35,$BJ$4,IF(B47<=45,$BJ$5,IF(B47<=50,$BJ$6,IF(B47<=55,$BJ$7,IF(B47<=60,$BJ$8,IF(B47<=65,$BJ$9,IF(B47<=70,$BJ$10,$BJ$11)))))))*'Retirement Dashboard'!$C$12,0) -> 0 | H47: =K46-C47-D47-E47-F47+G47 -> 72244.893 | I47: =$AL$8*H47 -> 2889.7957 | J47: =IF(I47+H47-$AL$35>0,I47+H47-$AL$35,0) -> 0 | K47: =H47+I47-J47 -> 75134.689 | M47: =IF(J47>=0,J47,0) -> 0 | N47: =IF(B47<$BH$31,IF(B48<=35,$BI$4,IF(B48<=45,$BI$5,IF(B48<=50,$BI$6,IF(B48<=55,$BI$7,IF(B48<=60,$BI$8,IF(B48<=65,$BI$9,IF(B48<=70,$BI$10,$BI$11)))))))*'Retirement Dashboard'!$C$12,0) -> 0 | O47: =R46+N47+M47 -> 1192249.3 | P47: =IF(B47<=55,$AL$5,$AN$6)*(IF(O47>=40000,40000,O47)) -> 2400 | Q47: =$AN$7*IF(O47>=40000,O47-40000,0) -> 57612.467 | R47: =O47+P47+Q47 -> 1252261.8 | T47: =IF(B47<$BH$31,IF(B47<=35,$BH$4,IF(B48<=45,$BH$5,IF(B48<=50,$BH$6,IF(B48<=55,$BH$7,IF(B48<=60,$BH$8,IF(B48<=65,$BH$9,IF(B48<=70,$BH$10,$BH$11)))))))*'Retirement Dashboard'!$C$12,0) -> 0 | U47: =IF(B47<($BH$57+$BH$30),$BH$56*12,0) -> 0 | V47: =IF(B47<=34,$AN$31,IF(B47<=39,$AN$32,IF(B47<=44,$AN$33,IF(B47<=49,$AN$34,IF(B47<=54,$AN$35,IF(B47<=59,$AN$36,IF(B47<=69,$AN$37,0))))))) -> 0 | W47: =Z46+T47-U47-V47 -> 255602.09 | X47: =IF(B47<=55,$AL$3,$AN$3)*(IF(W47>=20000,20000,W47)) -> 1200 | Y47: =$AL$4*IF(W47>=20000,W47-20000,W47) -> 5890.0522 | Z47: =W47+X47+Y47 -> 262692.14 | AR47: 75 | AS47: =VLOOKUP($AR$47,$B$59:$Z$106,10,) -> 75500 | AT47: =VLOOKUP(AR47,$B$3:$Z$56,25,) -> 153835.99 | AU47: =VLOOKUP(AR47,$B$3:$Z$56,17,) -> 487732.55 | AV47: =AU47+AT47 -> 641568.54 | BG47: Wipe out OA amount to | BH47: 0
B48: =B47+1 -> 95 | C48: =IF(B48>=67,$BI$55,C47+(1.0244%*C47)) -> 0 | D48: =IF(B48<=20,$AL$14,IF(B48<=30,$AL$15,IF(B48<=40,$AL$16,IF(B48<=50,$AL$17,IF(B48<=60,$AL$18,IF(B48<=65,$AL$19,IF(B48<=70,$AL$20, IF(B48<=73,$AL$21,IF(B48<=75,$AL$22,IF(B48<=78,$AL$23,IF(B48<=80,$AL$24,IF(B48<=83,$AL$25,IF(B48<=85,$AL$26,IF(B48<=90,$AL$27,$AL$28)))))))))))))) -> 2055 | E48: =IF(B48<=20,$AM$14,IF(B48<=30,$AM$15,IF(B48<=40,$AM$16,IF(B48<=50,$AM$17,IF(B48<=60,$AM$18,IF(B48<=65,$AM$19,IF(B48<=70,$AM$20, IF(B48<=73,$AM$21,IF(B48<=75,$AM$22,IF(B48<=78,$AM$23,IF(B48<=80,$AM$24,IF(B48<=83,$AM$25,IF(B48<=85,$AM$26,IF(B48<=90,$AM$27,$AM$28)))))))))))))) -> 900 | F48: =IF(AND('Retirement Dashboard'!$C$42="Yes", B48<= 'Retirement Dashboard'!$E$42), 600, 0) -> 0 | G48: =IF(B48<'Retirement Dashboard'!$E$6,IF(B48<=35,$BJ$4,IF(B48<=45,$BJ$5,IF(B48<=50,$BJ$6,IF(B48<=55,$BJ$7,IF(B48<=60,$BJ$8,IF(B48<=65,$BJ$9,IF(B48<=70,$BJ$10,$BJ$11)))))))*'Retirement Dashboard'!$C$12,0) -> 0 | H48: =K47-C48-D48-E48-F48+G48 -> 72179.689 | I48: =$AL$8*H48 -> 2887.1876 | J48: =IF(I48+H48-$AL$35>0,I48+H48-$AL$35,0) -> 0 | K48: =H48+I48-J48 -> 75066.876 | M48: =IF(J48>=0,J48,0) -> 0 | N48: =IF(B48<$BH$31,IF(B49<=35,$BI$4,IF(B49<=45,$BI$5,IF(B49<=50,$BI$6,IF(B49<=55,$BI$7,IF(B49<=60,$BI$8,IF(B49<=65,$BI$9,IF(B49<=70,$BI$10,$BI$11)))))))*'Retirement Dashboard'!$C$12,0) -> 0 | O48: =R47+N48+M48 -> 1252261.8 | P48: =IF(B48<=55,$AL$5,$AN$6)*(IF(O48>=40000,40000,O48)) -> 2400 | Q48: =$AN$7*IF(O48>=40000,O48-40000,0) -> 60613.091 | R48: =O48+P48+Q48 -> 1315274.9 | T48: =IF(B48<$BH$31,IF(B48<=35,$BH$4,IF(B49<=45,$BH$5,IF(B49<=50,$BH$6,IF(B49<=55,$BH$7,IF(B49<=60,$BH$8,IF(B49<=65,$BH$9,IF(B49<=70,$BH$10,$BH$11)))))))*'Retirement Dashboard'!$C$12,0) -> 0 | U48: =IF(B48<($BH$57+$BH$30),$BH$56*12,0) -> 0 | V48: =IF(B48<=34,$AN$31,IF(B48<=39,$AN$32,IF(B48<=44,$AN$33,IF(B48<=49,$AN$34,IF(B48<=54,$AN$35,IF(B48<=59,$AN$36,IF(B48<=69,$AN$37,0))))))) -> 0 | W48: =Z47+T48-U48-V48 -> 262692.14 | X48: =IF(B48<=55,$AL$3,$AN$3)*(IF(W48>=20000,20000,W48)) -> 1200 | Y48: =$AL$4*IF(W48>=20000,W48-20000,W48) -> 6067.3035 | Z48: =W48+X48+Y48 -> 269959.44 | AR48: ='[10]Retirement Dashboard'!E40 -> 90 | AS48: =VLOOKUP($AR$47,$B$59:$Z$106,10,) -> 75500 | AT48: =VLOOKUP(AR48,$B$3:$Z$56,25,) -> 235352.73 | AU48: =VLOOKUP(AR48,$B$3:$Z$56,17,) -> 1028820.5 | BG48: Cash Withdrawal at Age 56 | BH48: {='[10]Retirement Dashboard'!D42:F42*12} -> 24000 | BI48: 0 | BJ48: 0
B49: =B48+1 -> 96 | C49: =IF(B49>=67,$BI$55,C48+(1.0244%*C48)) -> 0 | D49: =IF(B49<=20,$AL$14,IF(B49<=30,$AL$15,IF(B49<=40,$AL$16,IF(B49<=50,$AL$17,IF(B49<=60,$AL$18,IF(B49<=65,$AL$19,IF(B49<=70,$AL$20, IF(B49<=73,$AL$21,IF(B49<=75,$AL$22,IF(B49<=78,$AL$23,IF(B49<=80,$AL$24,IF(B49<=83,$AL$25,IF(B49<=85,$AL$26,IF(B49<=90,$AL$27,$AL$28)))))))))))))) -> 2055 | E49: =IF(B49<=20,$AM$14,IF(B49<=30,$AM$15,IF(B49<=40,$AM$16,IF(B49<=50,$AM$17,IF(B49<=60,$AM$18,IF(B49<=65,$AM$19,IF(B49<=70,$AM$20, IF(B49<=73,$AM$21,IF(B49<=75,$AM$22,IF(B49<=78,$AM$23,IF(B49<=80,$AM$24,IF(B49<=83,$AM$25,IF(B49<=85,$AM$26,IF(B49<=90,$AM$27,$AM$28)))))))))))))) -> 900 | F49: =IF(AND('Retirement Dashboard'!$C$42="Yes", B49<= 'Retirement Dashboard'!$E$42), 600, 0) -> 0 | G49: =IF(B49<'Retirement Dashboard'!$E$6,IF(B49<=35,$BJ$4,IF(B49<=45,$BJ$5,IF(B49<=50,$BJ$6,IF(B49<=55,$BJ$7,IF(B49<=60,$BJ$8,IF(B49<=65,$BJ$9,IF(B49<=70,$BJ$10,$BJ$11)))))))*'Retirement Dashboard'!$C$12,0) -> 0 | H49: =K48-C49-D49-E49-F49+G49 -> 72111.876 | I49: =$AL$8*H49 -> 2884.4751 | J49: =IF(I49+H49-$AL$35>0,I49+H49-$AL$35,0) -> 0 | K49: =H49+I49-J49 -> 74996.351 | M49: =IF(J49>=0,J49,0) -> 0 | N49: =IF(B49<$BH$31,IF(B50<=35,$BI$4,IF(B50<=45,$BI$5,IF(B50<=50,$BI$6,IF(B50<=55,$BI$7,IF(B50<=60,$BI$8,IF(B50<=65,$BI$9,IF(B50<=70,$BI$10,$BI$11)))))))*'Retirement Dashboard'!$C$12,0) -> 0 | O49: =R48+N49+M49 -> 1315274.9 | P49: =IF(B49<=55,$AL$5,$AN$6)*(IF(O49>=40000,40000,O49)) -> 2400 | Q49: =$AN$7*IF(O49>=40000,O49-40000,0) -> 63763.745 | R49: =O49+P49+Q49 -> 1381438.7 | T49: =IF(B49<$BH$31,IF(B49<=35,$BH$4,IF(B50<=45,$BH$5,IF(B50<=50,$BH$6,IF(B50<=55,$BH$7,IF(B50<=60,$BH$8,IF(B50<=65,$BH$9,IF(B50<=70,$BH$10,$BH$11)))))))*'Retirement Dashboard'!$C$12,0) -> 0 | U49: =IF(B49<($BH$57+$BH$30),$BH$56*12,0) -> 0 | V49: =IF(B49<=34,$AN$31,IF(B49<=39,$AN$32,IF(B49<=44,$AN$33,IF(B49<=49,$AN$34,IF(B49<=54,$AN$35,IF(B49<=59,$AN$36,IF(B49<=69,$AN$37,0))))))) -> 0 | W49: =Z48+T49-U49-V49 -> 269959.44 | X49: =IF(B49<=55,$AL$3,$AN$3)*(IF(W49>=20000,20000,W49)) -> 1200 | Y49: =$AL$4*IF(W49>=20000,W49-20000,W49) -> 6248.9861 | Z49: =W49+X49+Y49 -> 277408.43 | AR49: CPFL Payout
B50: =B49+1 -> 97 | C50: =IF(B50>=67,$BI$55,C49+(1.0244%*C49)) -> 0 | D50: =IF(B50<=20,$AL$14,IF(B50<=30,$AL$15,IF(B50<=40,$AL$16,IF(B50<=50,$AL$17,IF(B50<=60,$AL$18,IF(B50<=65,$AL$19,IF(B50<=70,$AL$20, IF(B50<=73,$AL$21,IF(B50<=75,$AL$22,IF(B50<=78,$AL$23,IF(B50<=80,$AL$24,IF(B50<=83,$AL$25,IF(B50<=85,$AL$26,IF(B50<=90,$AL$27,$AL$28)))))))))))))) -> 2055 | E50: =IF(B50<=20,$AM$14,IF(B50<=30,$AM$15,IF(B50<=40,$AM$16,IF(B50<=50,$AM$17,IF(B50<=60,$AM$18,IF(B50<=65,$AM$19,IF(B50<=70,$AM$20, IF(B50<=73,$AM$21,IF(B50<=75,$AM$22,IF(B50<=78,$AM$23,IF(B50<=80,$AM$24,IF(B50<=83,$AM$25,IF(B50<=85,$AM$26,IF(B50<=90,$AM$27,$AM$28)))))))))))))) -> 900 | F50: =IF(AND('Retirement Dashboard'!$C$42="Yes", B50<= 'Retirement Dashboard'!$E$42), 600, 0) -> 0 | G50: =IF(B50<'Retirement Dashboard'!$E$6,IF(B50<=35,$BJ$4,IF(B50<=45,$BJ$5,IF(B50<=50,$BJ$6,IF(B50<=55,$BJ$7,IF(B50<=60,$BJ$8,IF(B50<=65,$BJ$9,IF(B50<=70,$BJ$10,$BJ$11)))))))*'Retirement Dashboard'!$C$12,0) -> 0 | H50: =K49-C50-D50-E50-F50+G50 -> 72041.351 | I50: =$AL$8*H50 -> 2881.6541 | J50: =IF(I50+H50-$AL$35>0,I50+H50-$AL$35,0) -> 0 | K50: =H50+I50-J50 -> 74923.005 | M50: =IF(J50>=0,J50,0) -> 0 | N50: =IF(B50<$BH$31,IF(B51<=35,$BI$4,IF(B51<=45,$BI$5,IF(B51<=50,$BI$6,IF(B51<=55,$BI$7,IF(B51<=60,$BI$8,IF(B51<=65,$BI$9,IF(B51<=70,$BI$10,$BI$11)))))))*'Retirement Dashboard'!$C$12,0) -> 0 | O50: =R49+N50+M50 -> 1381438.7 | P50: =IF(B50<=55,$AL$5,$AN$6)*(IF(O50>=40000,40000,O50)) -> 2400 | Q50: =$AN$7*IF(O50>=40000,O50-40000,0) -> 67071.933 | R50: =O50+P50+Q50 -> 1450910.6 | T50: =IF(B50<$BH$31,IF(B50<=35,$BH$4,IF(B51<=45,$BH$5,IF(B51<=50,$BH$6,IF(B51<=55,$BH$7,IF(B51<=60,$BH$8,IF(B51<=65,$BH$9,IF(B51<=70,$BH$10,$BH$11)))))))*'Retirement Dashboard'!$C$12,0) -> 0 | U50: =IF(B50<($BH$57+$BH$30),$BH$56*12,0) -> 0 | V50: =IF(B50<=34,$AN$31,IF(B50<=39,$AN$32,IF(B50<=44,$AN$33,IF(B50<=49,$AN$34,IF(B50<=54,$AN$35,IF(B50<=59,$AN$36,IF(B50<=69,$AN$37,0))))))) -> 0 | W50: =Z49+T50-U50-V50 -> 277408.43 | X50: =IF(B50<=55,$AL$3,$AN$3)*(IF(W50>=20000,20000,W50)) -> 1200 | Y50: =$AL$4*IF(W50>=20000,W50-20000,W50) -> 6435.2108 | Z50: =W50+X50+Y50 -> 285043.64 | AR50: Eligible for BRS | AS50: =IF($AV$45>=AX45,"Yes","No") -> No | AT50: =VLOOKUP($AR$45,$AR$4:$AY$41,6,) -> 1670 | BG50: Monthly additional OA from Wage | BH50: =BH39*BH35 -> 645.1505
B51: =B50+1 -> 98 | C51: =IF(B51>=67,$BI$55,C50+(1.0244%*C50)) -> 0 | D51: =IF(B51<=20,$AL$14,IF(B51<=30,$AL$15,IF(B51<=40,$AL$16,IF(B51<=50,$AL$17,IF(B51<=60,$AL$18,IF(B51<=65,$AL$19,IF(B51<=70,$AL$20, IF(B51<=73,$AL$21,IF(B51<=75,$AL$22,IF(B51<=78,$AL$23,IF(B51<=80,$AL$24,IF(B51<=83,$AL$25,IF(B51<=85,$AL$26,IF(B51<=90,$AL$27,$AL$28)))))))))))))) -> 2055 | E51: =IF(B51<=20,$AM$14,IF(B51<=30,$AM$15,IF(B51<=40,$AM$16,IF(B51<=50,$AM$17,IF(B51<=60,$AM$18,IF(B51<=65,$AM$19,IF(B51<=70,$AM$20, IF(B51<=73,$AM$21,IF(B51<=75,$AM$22,IF(B51<=78,$AM$23,IF(B51<=80,$AM$24,IF(B51<=83,$AM$25,IF(B51<=85,$AM$26,IF(B51<=90,$AM$27,$AM$28)))))))))))))) -> 900 | F51: =IF(AND('Retirement Dashboard'!$C$42="Yes", B51<= 'Retirement Dashboard'!$E$42), 600, 0) -> 0 | G51: =IF(B51<'Retirement Dashboard'!$E$6,IF(B51<=35,$BJ$4,IF(B51<=45,$BJ$5,IF(B51<=50,$BJ$6,IF(B51<=55,$BJ$7,IF(B51<=60,$BJ$8,IF(B51<=65,$BJ$9,IF(B51<=70,$BJ$10,$BJ$11)))))))*'Retirement Dashboard'!$C$12,0) -> 0 | H51: =K50-C51-D51-E51-F51+G51 -> 71968.005 | I51: =$AL$8*H51 -> 2878.7202 | J51: =IF(I51+H51-$AL$35>0,I51+H51-$AL$35,0) -> 0 | K51: =H51+I51-J51 -> 74846.726 | M51: =IF(J51>=0,J51,0) -> 0 | N51: =IF(B51<$BH$31,IF(B52<=35,$BI$4,IF(B52<=45,$BI$5,IF(B52<=50,$BI$6,IF(B52<=55,$BI$7,IF(B52<=60,$BI$8,IF(B52<=65,$BI$9,IF(B52<=70,$BI$10,$BI$11)))))))*'Retirement Dashboard'!$C$12,0) -> 0 | O51: =R50+N51+M51 -> 1450910.6 | P51: =IF(B51<=55,$AL$5,$AN$6)*(IF(O51>=40000,40000,O51)) -> 2400 | Q51: =$AN$7*IF(O51>=40000,O51-40000,0) -> 70545.529 | R51: =O51+P51+Q51 -> 1523856.1 | T51: =IF(B51<$BH$31,IF(B51<=35,$BH$4,IF(B52<=45,$BH$5,IF(B52<=50,$BH$6,IF(B52<=55,$BH$7,IF(B52<=60,$BH$8,IF(B52<=65,$BH$9,IF(B52<=70,$BH$10,$BH$11)))))))*'Retirement Dashboard'!$C$12,0) -> 0 | U51: =IF(B51<($BH$57+$BH$30),$BH$56*12,0) -> 0 | V51: =IF(B51<=34,$AN$31,IF(B51<=39,$AN$32,IF(B51<=44,$AN$33,IF(B51<=49,$AN$34,IF(B51<=54,$AN$35,IF(B51<=59,$AN$36,IF(B51<=69,$AN$37,0))))))) -> 0 | W51: =Z50+T51-U51-V51 -> 285043.64 | X51: =IF(B51<=55,$AL$3,$AN$3)*(IF(W51>=20000,20000,W51)) -> 1200 | Y51: =$AL$4*IF(W51>=20000,W51-20000,W51) -> 6626.091 | Z51: =W51+X51+Y51 -> 292869.73 | AR51: Eligible for FRS | AS51: =IF($AV$45>=AX45,"Yes","No") -> No | AT51: =VLOOKUP($AR$45,$AR$4:$AY$41,7,) -> 3220 | BG51: Monthly additional SA from Wage | BH51: =BH40*BH35 -> 494.4828
B52: =B51+1 -> 99 | C52: =IF(B52>=67,$BI$55,C51+(1.0244%*C51)) -> 0 | D52: =IF(B52<=20,$AL$14,IF(B52<=30,$AL$15,IF(B52<=40,$AL$16,IF(B52<=50,$AL$17,IF(B52<=60,$AL$18,IF(B52<=65,$AL$19,IF(B52<=70,$AL$20, IF(B52<=73,$AL$21,IF(B52<=75,$AL$22,IF(B52<=78,$AL$23,IF(B52<=80,$AL$24,IF(B52<=83,$AL$25,IF(B52<=85,$AL$26,IF(B52<=90,$AL$27,$AL$28)))))))))))))) -> 2055 | E52: =IF(B52<=20,$AM$14,IF(B52<=30,$AM$15,IF(B52<=40,$AM$16,IF(B52<=50,$AM$17,IF(B52<=60,$AM$18,IF(B52<=65,$AM$19,IF(B52<=70,$AM$20, IF(B52<=73,$AM$21,IF(B52<=75,$AM$22,IF(B52<=78,$AM$23,IF(B52<=80,$AM$24,IF(B52<=83,$AM$25,IF(B52<=85,$AM$26,IF(B52<=90,$AM$27,$AM$28)))))))))))))) -> 900 | F52: =IF(AND('Retirement Dashboard'!$C$42="Yes", B52<= 'Retirement Dashboard'!$E$42), 600, 0) -> 0 | G52: =IF(B52<'Retirement Dashboard'!$E$6,IF(B52<=35,$BJ$4,IF(B52<=45,$BJ$5,IF(B52<=50,$BJ$6,IF(B52<=55,$BJ$7,IF(B52<=60,$BJ$8,IF(B52<=65,$BJ$9,IF(B52<=70,$BJ$10,$BJ$11)))))))*'Retirement Dashboard'!$C$12,0) -> 0 | H52: =K51-C52-D52-E52-F52+G52 -> 71891.726 | I52: =$AL$8*H52 -> 2875.669 | J52: =IF(I52+H52-$AL$35>0,I52+H52-$AL$35,0) -> 0 | K52: =H52+I52-J52 -> 74767.395 | M52: =IF(J52>=0,J52,0) -> 0 | N52: =IF(B52<$BH$31,IF(B53<=35,$BI$4,IF(B53<=45,$BI$5,IF(B53<=50,$BI$6,IF(B53<=55,$BI$7,IF(B53<=60,$BI$8,IF(B53<=65,$BI$9,IF(B53<=70,$BI$10,$BI$11)))))))*'Retirement Dashboard'!$C$12,0) -> 0 | O52: =R51+N52+M52 -> 1523856.1 | P52: =IF(B52<=55,$AL$5,$AN$6)*(IF(O52>=40000,40000,O52)) -> 2400 | Q52: =$AN$7*IF(O52>=40000,O52-40000,0) -> 74192.806 | R52: =O52+P52+Q52 -> 1600448.9 | T52: =IF(B52<$BH$31,IF(B52<=35,$BH$4,IF(B53<=45,$BH$5,IF(B53<=50,$BH$6,IF(B53<=55,$BH$7,IF(B53<=60,$BH$8,IF(B53<=65,$BH$9,IF(B53<=70,$BH$10,$BH$11)))))))*'Retirement Dashboard'!$C$12,0) -> 0 | U52: =IF(B52<($BH$57+$BH$30),$BH$56*12,0) -> 0 | V52: =IF(B52<=34,$AN$31,IF(B52<=39,$AN$32,IF(B52<=44,$AN$33,IF(B52<=49,$AN$34,IF(B52<=54,$AN$35,IF(B52<=59,$AN$36,IF(B52<=69,$AN$37,0))))))) -> 0 | W52: =Z51+T52-U52-V52 -> 292869.73 | X52: =IF(B52<=55,$AL$3,$AN$3)*(IF(W52>=20000,20000,W52)) -> 1200 | Y52: =$AL$4*IF(W52>=20000,W52-20000,W52) -> 6821.7433 | Z52: =W52+X52+Y52 -> 300891.48 | AR52: Eligible for ERS | AS52: =IF($AV$45>=AY45,"Yes","No") -> No | AT52: =VLOOKUP($AR$45,$AR$4:$AY$41,8,) -> 8278.0826 | BG52: Monthly additional MA from Wage | BH52: =BH41*BH35 -> 451.3667
B53: =B52+1 -> 100 | C53: =IF(B53>=67,$BI$55,C52+(1.0244%*C52)) -> 0 | D53: =IF(B53<=20,$AL$14,IF(B53<=30,$AL$15,IF(B53<=40,$AL$16,IF(B53<=50,$AL$17,IF(B53<=60,$AL$18,IF(B53<=65,$AL$19,IF(B53<=70,$AL$20, IF(B53<=73,$AL$21,IF(B53<=75,$AL$22,IF(B53<=78,$AL$23,IF(B53<=80,$AL$24,IF(B53<=83,$AL$25,IF(B53<=85,$AL$26,IF(B53<=90,$AL$27,$AL$28)))))))))))))) -> 2055 | E53: =IF(B53<=20,$AM$14,IF(B53<=30,$AM$15,IF(B53<=40,$AM$16,IF(B53<=50,$AM$17,IF(B53<=60,$AM$18,IF(B53<=65,$AM$19,IF(B53<=70,$AM$20, IF(B53<=73,$AM$21,IF(B53<=75,$AM$22,IF(B53<=78,$AM$23,IF(B53<=80,$AM$24,IF(B53<=83,$AM$25,IF(B53<=85,$AM$26,IF(B53<=90,$AM$27,$AM$28)))))))))))))) -> 900 | F53: =IF(AND('Retirement Dashboard'!$C$42="Yes", B53<= 'Retirement Dashboard'!$E$42), 600, 0) -> 0 | G53: =IF(B53<'Retirement Dashboard'!$E$6,IF(B53<=35,$BJ$4,IF(B53<=45,$BJ$5,IF(B53<=50,$BJ$6,IF(B53<=55,$BJ$7,IF(B53<=60,$BJ$8,IF(B53<=65,$BJ$9,IF(B53<=70,$BJ$10,$BJ$11)))))))*'Retirement Dashboard'!$C$12,0) -> 0 | H53: =K52-C53-D53-E53-F53+G53 -> 71812.395 | I53: =$AL$8*H53 -> 2872.4958 | J53: =IF(I53+H53-$AL$35>0,I53+H53-$AL$35,0) -> 0 | K53: =H53+I53-J53 -> 74684.891 | M53: =IF(J53>=0,J53,0) -> 0 | N53: =IF(B53<$BH$31,IF(B54<=35,$BI$4,IF(B54<=45,$BI$5,IF(B54<=50,$BI$6,IF(B54<=55,$BI$7,IF(B54<=60,$BI$8,IF(B54<=65,$BI$9,IF(B54<=70,$BI$10,$BI$11)))))))*'Retirement Dashboard'!$C$12,0) -> 0 | O53: =R52+N53+M53 -> 1600448.9 | P53: =IF(B53<=55,$AL$5,$AN$6)*(IF(O53>=40000,40000,O53)) -> 2400 | Q53: =$AN$7*IF(O53>=40000,O53-40000,0) -> 78022.446 | R53: =O53+P53+Q53 -> 1680871.4 | T53: =IF(B53<$BH$31,IF(B53<=35,$BH$4,IF(B54<=45,$BH$5,IF(B54<=50,$BH$6,IF(B54<=55,$BH$7,IF(B54<=60,$BH$8,IF(B54<=65,$BH$9,IF(B54<=70,$BH$10,$BH$11)))))))*'Retirement Dashboard'!$C$12,0) -> 0 | U53: =IF(B53<($BH$57+$BH$30),$BH$56*12,0) -> 0 | V53: =IF(B53<=34,$AN$31,IF(B53<=39,$AN$32,IF(B53<=44,$AN$33,IF(B53<=49,$AN$34,IF(B53<=54,$AN$35,IF(B53<=59,$AN$36,IF(B53<=69,$AN$37,0))))))) -> 0 | W53: =Z52+T53-U53-V53 -> 300891.48 | X53: =IF(B53<=55,$AL$3,$AN$3)*(IF(W53>=20000,20000,W53)) -> 1200 | Y53: =$AL$4*IF(W53>=20000,W53-20000,W53) -> 7022.2869 | Z53: =W53+X53+Y53 -> 309113.76 | AR53: FRS Choice
B54: =B53+1 -> 101 | C54: =IF(B54>=67,$BI$55,C53+(1.0244%*C53)) -> 0 | D54: =IF(B54<=20,$AL$14,IF(B54<=30,$AL$15,IF(B54<=40,$AL$16,IF(B54<=50,$AL$17,IF(B54<=60,$AL$18,IF(B54<=65,$AL$19,IF(B54<=70,$AL$20, IF(B54<=73,$AL$21,IF(B54<=75,$AL$22,IF(B54<=78,$AL$23,IF(B54<=80,$AL$24,IF(B54<=83,$AL$25,IF(B54<=85,$AL$26,IF(B54<=90,$AL$27,$AL$28)))))))))))))) -> 2055 | E54: =IF(B54<=20,$AM$14,IF(B54<=30,$AM$15,IF(B54<=40,$AM$16,IF(B54<=50,$AM$17,IF(B54<=60,$AM$18,IF(B54<=65,$AM$19,IF(B54<=70,$AM$20, IF(B54<=73,$AM$21,IF(B54<=75,$AM$22,IF(B54<=78,$AM$23,IF(B54<=80,$AM$24,IF(B54<=83,$AM$25,IF(B54<=85,$AM$26,IF(B54<=90,$AM$27,$AM$28)))))))))))))) -> 900 | F54: =IF(AND('Retirement Dashboard'!$C$42="Yes", B54<= 'Retirement Dashboard'!$E$42), 600, 0) -> 0 | G54: =IF(B54<'Retirement Dashboard'!$E$6,IF(B54<=35,$BJ$4,IF(B54<=45,$BJ$5,IF(B54<=50,$BJ$6,IF(B54<=55,$BJ$7,IF(B54<=60,$BJ$8,IF(B54<=65,$BJ$9,IF(B54<=70,$BJ$10,$BJ$11)))))))*'Retirement Dashboard'!$C$12,0) -> 0 | H54: =K53-C54-D54-E54-F54+G54 -> 71729.891 | I54: =$AL$8*H54 -> 2869.1956 | J54: =IF(I54+H54-$AL$35>0,I54+H54-$AL$35,0) -> 0 | K54: =H54+I54-J54 -> 74599.086 | M54: =IF(J54>=0,J54,0) -> 0 | N54: =IF(B54<$BH$31,IF(B55<=35,$BI$4,IF(B55<=45,$BI$5,IF(B55<=50,$BI$6,IF(B55<=55,$BI$7,IF(B55<=60,$BI$8,IF(B55<=65,$BI$9,IF(B55<=70,$BI$10,$BI$11)))))))*'Retirement Dashboard'!$C$12,0) -> 0 | O54: =R53+N54+M54 -> 1680871.4 | P54: =IF(B54<=55,$AL$5,$AN$6)*(IF(O54>=40000,40000,O54)) -> 2400 | Q54: =$AN$7*IF(O54>=40000,O54-40000,0) -> 82043.568 | R54: =O54+P54+Q54 -> 1765314.9 | T54: =IF(B54<$BH$31,IF(B54<=35,$BH$4,IF(B55<=45,$BH$5,IF(B55<=50,$BH$6,IF(B55<=55,$BH$7,IF(B55<=60,$BH$8,IF(B55<=65,$BH$9,IF(B55<=70,$BH$10,$BH$11)))))))*'Retirement Dashboard'!$C$12,0) -> 0 | U54: =IF(B54<($BH$57+$BH$30),$BH$56*12,0) -> 0 | V54: =IF(B54<=34,$AN$31,IF(B54<=39,$AN$32,IF(B54<=44,$AN$33,IF(B54<=49,$AN$34,IF(B54<=54,$AN$35,IF(B54<=59,$AN$36,IF(B54<=69,$AN$37,0))))))) -> 0 | W54: =Z53+T54-U54-V54 -> 309113.76 | X54: =IF(B54<=55,$AL$3,$AN$3)*(IF(W54>=20000,20000,W54)) -> 1200 | Y54: =$AL$4*IF(W54>=20000,W54-20000,W54) -> 7227.8441 | Z54: =W54+X54+Y54 -> 317541.61 | AR54: Age | AS54: CPF Life Payout | AT54: SA | AU54: OA | AV54: MA | AW54: Total Portfolio | AX54: Cash Income | BG54: Annual Medishield -MA | BH54: =IF(BH30<=20,AL14,IF(BH30<=30,AL15,IF(BH30<=40,AL16,IF(BH30<=50,AL17,IF(BH30<=60,AL18,IF(BH30<=65,AL19,IF(BH30<=70,AL20, IF(BH30<=73,AL21,IF(BH30<=75,AL22,IF(BH30<=78,AL23,IF(BH30<=80,AL24,IF(BH30<=83,AL25,IF(BH30<=85,AL26,IF(BH30<=90,AL27,AL28)))))))))))))) -> 800 | BI54: 462
B55: =B54+1 -> 102 | C55: =IF(B55>=67,$BI$55,C54+(1.0244%*C54)) -> 0 | D55: =IF(B55<=20,$AL$14,IF(B55<=30,$AL$15,IF(B55<=40,$AL$16,IF(B55<=50,$AL$17,IF(B55<=60,$AL$18,IF(B55<=65,$AL$19,IF(B55<=70,$AL$20, IF(B55<=73,$AL$21,IF(B55<=75,$AL$22,IF(B55<=78,$AL$23,IF(B55<=80,$AL$24,IF(B55<=83,$AL$25,IF(B55<=85,$AL$26,IF(B55<=90,$AL$27,$AL$28)))))))))))))) -> 2055 | E55: =IF(B55<=20,$AM$14,IF(B55<=30,$AM$15,IF(B55<=40,$AM$16,IF(B55<=50,$AM$17,IF(B55<=60,$AM$18,IF(B55<=65,$AM$19,IF(B55<=70,$AM$20, IF(B55<=73,$AM$21,IF(B55<=75,$AM$22,IF(B55<=78,$AM$23,IF(B55<=80,$AM$24,IF(B55<=83,$AM$25,IF(B55<=85,$AM$26,IF(B55<=90,$AM$27,$AM$28)))))))))))))) -> 900 | F55: =IF(AND('Retirement Dashboard'!$C$42="Yes", B55<= 'Retirement Dashboard'!$E$42), 600, 0) -> 0 | G55: =IF(B55<'Retirement Dashboard'!$E$6,IF(B55<=35,$BJ$4,IF(B55<=45,$BJ$5,IF(B55<=50,$BJ$6,IF(B55<=55,$BJ$7,IF(B55<=60,$BJ$8,IF(B55<=65,$BJ$9,IF(B55<=70,$BJ$10,$BJ$11)))))))*'Retirement Dashboard'!$C$12,0) -> 0 | H55: =K54-C55-D55-E55-F55+G55 -> 71644.086 | I55: =$AL$8*H55 -> 2865.7634 | J55: =IF(I55+H55-$AL$35>0,I55+H55-$AL$35,0) -> 0 | K55: =H55+I55-J55 -> 74509.85 | M55: =IF(J55>=0,J55,0) -> 0 | N55: =IF(B55<$BH$31,IF(B56<=35,$BI$4,IF(B56<=45,$BI$5,IF(B56<=50,$BI$6,IF(B56<=55,$BI$7,IF(B56<=60,$BI$8,IF(B56<=65,$BI$9,IF(B56<=70,$BI$10,$BI$11)))))))*'Retirement Dashboard'!$C$12,0) -> 0 | O55: =R54+N55+M55 -> 1765314.9 | P55: =IF(B55<=55,$AL$5,$AN$6)*(IF(O55>=40000,40000,O55)) -> 2400 | Q55: =$AN$7*IF(O55>=40000,O55-40000,0) -> 86265.747 | R55: =O55+P55+Q55 -> 1853980.7 | T55: =IF(B55<$BH$31,IF(B55<=35,$BH$4,IF(B56<=45,$BH$5,IF(B56<=50,$BH$6,IF(B56<=55,$BH$7,IF(B56<=60,$BH$8,IF(B56<=65,$BH$9,IF(B56<=70,$BH$10,$BH$11)))))))*'Retirement Dashboard'!$C$12,0) -> 0 | U55: =IF(B55<($BH$57+$BH$30),$BH$56*12,0) -> 0 | V55: =IF(B55<=34,$AN$31,IF(B55<=39,$AN$32,IF(B55<=44,$AN$33,IF(B55<=49,$AN$34,IF(B55<=54,$AN$35,IF(B55<=59,$AN$36,IF(B55<=69,$AN$37,0))))))) -> 0 | W55: =Z54+T55-U55-V55 -> 317541.61 | X55: =IF(B55<=55,$AL$3,$AN$3)*(IF(W55>=20000,20000,W55)) -> 1200 | Y55: =$AL$4*IF(W55>=20000,W55-20000,W55) -> 7438.5402 | Z55: =W55+X55+Y55 -> 326180.15 | AR55: 55 | AS55: - | AT55: =IF(AU45-AX45>0,AU45-AX45,0) -> 0 | AU55: =IF(AU45-AX45>=0,AT45,AT45-(AX45-AU45)) -> -401610.73 | AV55: =AS45 -> 62168.79 | AW55: =SUM(AT55:AU55) -> -401610.73 | AX55: 0 | BG55: Annual CareShield -MA | BH55: ='[10]Retirement Dashboard'!D93 -> 0 | BI55: 0
B56: =B55+1 -> 103 | C56: =IF(B56>=67,$BI$55,C55+(1.0244%*C55)) -> 0 | D56: =IF(B56<=20,$AL$14,IF(B56<=30,$AL$15,IF(B56<=40,$AL$16,IF(B56<=50,$AL$17,IF(B56<=60,$AL$18,IF(B56<=65,$AL$19,IF(B56<=70,$AL$20, IF(B56<=73,$AL$21,IF(B56<=75,$AL$22,IF(B56<=78,$AL$23,IF(B56<=80,$AL$24,IF(B56<=83,$AL$25,IF(B56<=85,$AL$26,IF(B56<=90,$AL$27,$AL$28)))))))))))))) -> 2055 | E56: =IF(B56<=20,$AM$14,IF(B56<=30,$AM$15,IF(B56<=40,$AM$16,IF(B56<=50,$AM$17,IF(B56<=60,$AM$18,IF(B56<=65,$AM$19,IF(B56<=70,$AM$20, IF(B56<=73,$AM$21,IF(B56<=75,$AM$22,IF(B56<=78,$AM$23,IF(B56<=80,$AM$24,IF(B56<=83,$AM$25,IF(B56<=85,$AM$26,IF(B56<=90,$AM$27,$AM$28)))))))))))))) -> 900 | F56: =IF(AND('Retirement Dashboard'!$C$42="Yes", B56<= 'Retirement Dashboard'!$E$42), 600, 0) -> 0 | G56: =IF(B56<'Retirement Dashboard'!$E$6,IF(B56<=35,$BJ$4,IF(B56<=45,$BJ$5,IF(B56<=50,$BJ$6,IF(B56<=55,$BJ$7,IF(B56<=60,$BJ$8,IF(B56<=65,$BJ$9,IF(B56<=70,$BJ$10,$BJ$11)))))))*'Retirement Dashboard'!$C$12,0) -> 0 | H56: =K55-C56-D56-E56-F56+G56 -> 71554.85 | I56: =$AL$8*H56 -> 2862.194 | J56: =IF(I56+H56-$AL$35>0,I56+H56-$AL$35,0) -> 0 | K56: =H56+I56-J56 -> 74417.044 | M56: =IF(J56>=0,J56,0) -> 0 | N56: =IF(B56<$BH$31,IF(B57<=35,$BI$4,IF(B57<=45,$BI$5,IF(B57<=50,$BI$6,IF(B57<=55,$BI$7,IF(B57<=60,$BI$8,IF(B57<=65,$BI$9,IF(B57<=70,$BI$10,$BI$11)))))))*'Retirement Dashboard'!$C$12,0) -> 0 | O56: =R55+N56+M56 -> 1853980.7 | P56: =IF(B56<=55,$AL$5,$AN$6)*(IF(O56>=40000,40000,O56)) -> 2400 | Q56: =$AN$7*IF(O56>=40000,O56-40000,0) -> 90699.034 | R56: =O56+P56+Q56 -> 1947079.7 | T56: =IF(B56<$BH$31,IF(B56<=35,$BH$4,IF(B57<=45,$BH$5,IF(B57<=50,$BH$6,IF(B57<=55,$BH$7,IF(B57<=60,$BH$8,IF(B57<=65,$BH$9,IF(B57<=70,$BH$10,$BH$11)))))))*'Retirement Dashboard'!$C$12,0) -> 0 | U56: =IF(B56<($BH$57+$BH$30),$BH$56*12,0) -> 0 | V56: =IF(B56<=34,$AN$31,IF(B56<=39,$AN$32,IF(B56<=44,$AN$33,IF(B56<=49,$AN$34,IF(B56<=54,$AN$35,IF(B56<=59,$AN$36,IF(B56<=69,$AN$37,0))))))) -> 0 | W56: =Z55+T56-U56-V56 -> 326180.15 | X56: =IF(B56<=55,$AL$3,$AN$3)*(IF(W56>=20000,20000,W56)) -> 1200 | Y56: =$AL$4*IF(W56>=20000,W56-20000,W56) -> 7654.5037 | Z56: =W56+X56+Y56 -> 335034.65 | AR56: ='[10]Retirement Dashboard'!G72 -> 65 | AS56: =IF(AR46<=65,12,(AR56-65)*12)*AT51 -> 38640 | AT56: =VLOOKUP($AR$56,$B$59:$Z$106,17,) -> 72269.198 | AU56: =VLOOKUP($AR$56,$B$138:$AL$185,27) -> 0 | AV56: =VLOOKUP(AR56,$B$59:$Z$106,10,) -> 75500 | AW56: =SUM(AT56:AU56) -> 72269.198 | AX56: =$AT$51 -> 3220 | BG56: Monthly Housing Loan (OA) | BH56: ='[10]Retirement Dashboard'!D91 -> 817.1376
AR57: 75 | AS57: =IF(AR57<=65,12,(AR57-65)*12)*$AT$51 -> 386400 | AT57: =VLOOKUP($AR$57,$B$59:$Z$106,17,) -> 120564.03 | AU57: =VLOOKUP($AR$57,$B$138:$AL$185,27,) -> 0 | AV57: =VLOOKUP(AR57,$B$59:$Z$106,10,) -> 75500 | AW57: =SUM(AT57:AU57) -> 120564.03 | AX57: =$AT$51 -> 3220 | BG57: Remaining Years of HDB loan | BH57: ='[10]Retirement Dashboard'!D99 -> 0
B58: CPFL FRS Scenario | AR58: 85 | AS58: =IF(AR58<=65,12,(AR58-65)*12)*$AT$51 -> 772800 | AT58: =VLOOKUP($AR$58,$B$59:$Z$106,17,) -> #REF! | AU58: =VLOOKUP($AR$58,$B$138:$AL$185,27,) -> 0 | AV58: =VLOOKUP(AR58,$B$59:$Z$106,10,) -> 73025.526 | AW58: =SUM(AT58:AU58) -> #REF! | AX58: =$AT$51 -> 3220 | BG58: DPS Annual (OA) | BH58: =IF(BH30<=34,AN31,IF(BH30<=39,AN32,IF(BH30<=44,AN33,IF(BH30<=49,AN34,IF(BH30<=54,AN35,IF(BH30<=59,AN36,AN37)))))) -> 188
B59: MA Projection | M59: SA Projection FRS | T59: OA FRS Projection | AR59: ='[10]Retirement Dashboard'!E40 -> 90 | AS59: =IF(AR59<=65,12,(AR59-65)*12)*$AT$51 -> 966000 | AT59: =VLOOKUP($AR$58,$B$59:$Z$106,17,) -> #REF! | AU59: =VLOOKUP($AR$59,$B$138:$AL$185,27,) -> 0 | AV59: =VLOOKUP(AR59,$B$59:$Z$106,10,) -> 72370.265 | AW59: =SUM(AT59:AU59) -> #REF! | AX59: =$AT$51 -> 3220 | BG59: Annual Private Shield Withdrawal | BH59: =IF(BH30<=20,AM14,IF(BH30<=30,AM15,IF(BH30<=40,AM16,IF(BH30<=50,AM17,IF(BH30<=60,AM18,IF(BH30<=65,AM19,IF(BH30<=70,AM20, IF(BH30<=73,AM21,IF(BH30<=75,AM22,IF(BH30<=78,AM23,IF(BH30<=80,AM24,IF(BH30<=83,AM25,IF(BH30<=85,AM26,IF(BH30<=90,AM27,AM28)))))))))))))) -> 600
B60: Age | C60: CareShield Premium (0.0244%) | D60: Medishield Premium | E60: Private Shield Premium | F60: Care Secure Premium | G60: Additional MA by Salary | H60: YOY MA - Outflow | I60: MA earned Interest YoY | J60: Excess Transfer to OA | K60: Total MA After Cap | M60: Cash Withdrawal | N60: Additional SA from Salary | O60: SA Before Int Earned | P60: 1st 40K Interest Earned YoY | Q60: Remaining Int Earned YoY | R60: Total SA | T60: Transfer from MA | U60: Cash Withdrawal after Age 56 | V60: Additional OA from Salary | W60: Housing Loan | X60: DPS | Y60: OA before Int Earned | Z60: 1st 20K Interest Earned YoY | BG60: Care shield Rider (MA) | BH60: ='[10]Retirement Dashboard-Main'!D24 -> 500
B61: =AR45 -> 55 | C61: =VLOOKUP(B61,$B$3:$Z$56,2) -> 403.27671 | D61: =IF(B61<=20,$AL$14,IF(B61<=30,$AL$15,IF(B61<=40,$AL$16,IF(B61<=50,$AL$17,IF(B61<=60,$AL$18,IF(B61<=65,$AL$19,IF(B61<=70,$AL$20, IF(B61<=73,$AL$21,IF(B61<=75,$AL$22,IF(B61<=78,$AL$23,IF(B61<=80,$AL$24,IF(B61<=83,$AL$25,IF(B61<=85,$AL$26,IF(B61<=90,$AL$27,$AL$28)))))))))))))) -> 800 | E61: =IF(B61<=20,$AM$14,IF(B61<=30,$AM$15,IF(B61<=40,$AM$16,IF(B61<=50,$AM$17,IF(B61<=60,$AM$18,IF(B61<=65,$AM$19,IF(B61<=70,$AM$20, IF(B61<=73,$AM$21,IF(B61<=75,$AM$22,IF(B61<=78,$AM$23,IF(B61<=80,$AM$24,IF(B61<=83,$AM$25,IF(B61<=85,$AM$26,IF(B61<=90,$AM$27,$AM$28)))))))))))))) -> 600 | F61: 600 | G61: =IF(B61>=$BH$31,0,IF(B61<=35,$BJ$4,IF(B61<=45,$BJ$5,IF(B61<=50,$BJ$6,IF(B61<=55,$BJ$7,IF(B61<=60,$BJ$8,IF(B61<=65,$BJ$9,IF(B61<=70,$BJ$10,$BJ$11)))))))*$BH$37) -> 6319.1338 | H61: =$AS$45-C61-D61-E61-F61+G61 -> 66084.647 | I61: =$AL$8*H61 -> 2643.3859 | J61: =IF(I61+H61-$AL$35>0,I61+H61-$AL$35,0) -> 0 | K61: =H61+I61-J61 -> 68728.033 | M61: 0 | N61: =IF(B61<$BH$31,IF(B62<=35,$BI$4,IF(B62<=45,$BI$5,IF(B62<=50,$BI$6,IF(B62<=55,$BI$7,IF(B62<=60,$BI$8,IF(B62<=65,$BI$9,IF(B62<=70,$BI$10,$BI$11)))))))*$BH$37,0) -> 5362.7665 | O61: =N61+AT55 -> 5362.7665 | P61: =IF(B61<=55,$AL$5,$AN$6)*(IF(O61>=40000,40000,O61)) -> 268.13833 | Q61: =$AN$7*IF(O61>=40000,O61-40000,0) -> 0 | R61: =O61+P61+Q61 -> 5630.9048 | T61: =IF(J61>=0,J61,0) -> 0 | U61: 0 | V61: =IF(B61>=$BH$31,0,IF(B61<=35,$BH$4,IF(B61<=45,$BH$5,IF(B61<=50,$BH$6,IF(B61<=55,$BH$7,IF(B61<=60,$BH$8,IF(B61<=65,$BH$9,IF(B61<=70,$BH$10,$BH$11)))))))*$BH$37) -> 9032.107 | W61: =IF(B61<($BH$57+$BH$30),$BH$56*12,0) -> 0 | X61: =IF(B61<=34,$AN$31,IF(B61<=39,$AN$32,IF(B61<=44,$AN$33,IF(B61<=49,$AN$34,IF(B61<=54,$AN$35,IF(B61<=59,$AN$36,IF(B61<=69,$AN$37,0))))))) -> 298 | Y61: =AU55+V61-W61-X61-U61+T61 -> -392876.62 | Z61: =IF(B61<=55,$AL$3,$AN$3)*(IF(Y61>=20000,20000,Y61)) -> -13750.682 | AR61: ERS Choice
B62: =B61+1 -> 56 | C62: =IF(B62>=67,$BI$55,C61+(1.0244%*C61)) -> 407.40787 | D62: =IF(B62<=20,$AL$14,IF(B62<=30,$AL$15,IF(B62<=40,$AL$16,IF(B62<=50,$AL$17,IF(B62<=60,$AL$18,IF(B62<=65,$AL$19,IF(B62<=70,$AL$20, IF(B62<=73,$AL$21,IF(B62<=75,$AL$22,IF(B62<=78,$AL$23,IF(B62<=80,$AL$24,IF(B62<=83,$AL$25,IF(B62<=85,$AL$26,IF(B62<=90,$AL$27,$AL$28)))))))))))))) -> 800 | E62: =IF(B62<=20,$AM$14,IF(B62<=30,$AM$15,IF(B62<=40,$AM$16,IF(B62<=50,$AM$17,IF(B62<=60,$AM$18,IF(B62<=65,$AM$19,IF(B62<=70,$AM$20, IF(B62<=73,$AM$21,IF(B62<=75,$AM$22,IF(B62<=78,$AM$23,IF(B62<=80,$AM$24,IF(B62<=83,$AM$25,IF(B62<=85,$AM$26,IF(B62<=90,$AM$27,$AM$28)))))))))))))) -> 600 | F62: 600 | G62: =IF(B62>=$BH$31,0,IF(B62<=35,$BJ$4,IF(B62<=45,$BJ$5,IF(B62<=50,$BJ$6,IF(B62<=55,$BJ$7,IF(B62<=60,$BJ$8,IF(B62<=65,$BJ$9,IF(B62<=70,$BJ$10,$BJ$11)))))))*$BH$37) -> 6626.6655 | H62: =K61-C62-D62-E62-F62+G62 -> 72947.29 | I62: =$AL$8*H62 -> 2917.8916 | J62: =IF(I62+H62-$AL$35>0,I62+H62-$AL$35,0) -> 365.18205 | K62: =H62+I62-J62 -> 75500 | M62: =IF(R61>=BH49,BH49,0) -> 0 | N62: =IF(B62<$BH$31,IF(B63<=35,$BI$4,IF(B63<=45,$BI$5,IF(B63<=50,$BI$6,IF(B63<=55,$BI$7,IF(B63<=60,$BI$8,IF(B63<=65,$BI$9,IF(B63<=70,$BI$10,$BI$11)))))))*$BH$37,0) -> 5362.7665 | O62: =R61+N62-M62 -> 10993.671 | P62: =IF(B62<=55,$AL$5,$AN$6)*(IF(O62>=40000,40000,O62)) -> 659.62028 | Q62: =$AN$7*IF(O62>=40000,O62-40000,0) -> 0 | R62: =O62+P62+Q62 -> 11653.292 | T62: =IF(J62>=0,J62,0) -> 365.18205 | U62: =IF(AL142>=$BH$48,$BH$48-M62,0) -> 0 | V62: =IF(B62>=$BH$31,0,IF(B62<=35,$BH$4,IF(B62<=45,$BH$5,IF(B62<=50,$BH$6,IF(B62<=55,$BH$7,IF(B62<=60,$BH$8,IF(B62<=65,$BH$9,IF(B62<=70,$BH$10,$BH$11)))))))*$BH$37) -> 6040.1068 | W62: =IF(B62<($BH$57+$BH$30),$BH$56*12,0) -> 0 | X62: =IF(B62<=34,$AN$31,IF(B62<=39,$AN$32,IF(B62<=44,$AN$33,IF(B62<=49,$AN$34,IF(B62<=54,$AN$35,IF(B62<=59,$AN$36,IF(B62<=69,$AN$37,0))))))) -> 298 | Y62: =AL142+V62-W62-X62+T62-U62 -> -400520.02 | Z62: =IF(B62<=55,$AL$3,$AN$3)*(IF(Y62>=20000,20000,Y62)) -> -24031.201 | AR62: Age | AS62: CPF Life Payout | AT62: SA | AU62: OA | AV62: MA | AW62: Total Portfolio | AX62: Cash Income | BG62: Age Cash Withdrawal from CPF Ends (FRS) | BH62: 77
B63: =B62+1 -> 57 | C63: =IF(B63>=67,$BI$55,C62+(1.0244%*C62)) -> 411.58136 | D63: =IF(B63<=20,$AL$14,IF(B63<=30,$AL$15,IF(B63<=40,$AL$16,IF(B63<=50,$AL$17,IF(B63<=60,$AL$18,IF(B63<=65,$AL$19,IF(B63<=70,$AL$20, IF(B63<=73,$AL$21,IF(B63<=75,$AL$22,IF(B63<=78,$AL$23,IF(B63<=80,$AL$24,IF(B63<=83,$AL$25,IF(B63<=85,$AL$26,IF(B63<=90,$AL$27,$AL$28)))))))))))))) -> 800 | E63: =IF(B63<=20,$AM$14,IF(B63<=30,$AM$15,IF(B63<=40,$AM$16,IF(B63<=50,$AM$17,IF(B63<=60,$AM$18,IF(B63<=65,$AM$19,IF(B63<=70,$AM$20, IF(B63<=73,$AM$21,IF(B63<=75,$AM$22,IF(B63<=78,$AM$23,IF(B63<=80,$AM$24,IF(B63<=83,$AM$25,IF(B63<=85,$AM$26,IF(B63<=90,$AM$27,$AM$28)))))))))))))) -> 600 | F63: 600 | G63: =IF(B63>=$BH$31,0,IF(B63<=35,$BJ$4,IF(B63<=45,$BJ$5,IF(B63<=50,$BJ$6,IF(B63<=55,$BJ$7,IF(B63<=60,$BJ$8,IF(B63<=65,$BJ$9,IF(B63<=70,$BJ$10,$BJ$11)))))))*$BH$37) -> 6626.6655 | H63: =K62-C63-D63-E63-F63+G63 -> 79715.084 | I63: =$AL$8*H63 -> 3188.6034 | J63: =IF(I63+H63-$AL$35>0,I63+H63-$AL$35,0) -> 7403.6875 | K63: =H63+I63-J63 -> 75500 | M63: =IF(R62>=BH50,BH50,0) -> 645.1505 | N63: =IF(B63<$BH$31,IF(B64<=35,$BI$4,IF(B64<=45,$BI$5,IF(B64<=50,$BI$6,IF(B64<=55,$BI$7,IF(B64<=60,$BI$8,IF(B64<=65,$BI$9,IF(B64<=70,$BI$10,$BI$11)))))))*$BH$37,0) -> 5362.7665 | O63: =R62+N63-M63 -> 16370.908 | P63: =IF(B63<=55,$AL$5,$AN$6)*(IF(O63>=40000,40000,O63)) -> 982.25446 | Q63: =$AN$7*IF(O63>=40000,O63-40000,0) -> 0 | R63: =O63+P63+Q63 -> 17353.162 | T63: =IF(J63>=0,J63,0) -> 7403.6875 | U63: =IF(AL143>=$BH$48,$BH$48-M63,0) -> 0 | V63: =IF(B63>=$BH$31,0,IF(B63<=35,$BH$4,IF(B63<=45,$BH$5,IF(B63<=50,$BH$6,IF(B63<=55,$BH$7,IF(B63<=60,$BH$8,IF(B63<=65,$BH$9,IF(B63<=70,$BH$10,$BH$11)))))))*$BH$37) -> 6040.1068 | W63: =IF(B63<($BH$57+$BH$30),$BH$56*12,0) -> 0 | X63: =IF(B63<=34,$AN$31,IF(B63<=39,$AN$32,IF(B63<=44,$AN$33,IF(B63<=49,$AN$34,IF(B63<=54,$AN$35,IF(B63<=59,$AN$36,IF(B63<=69,$AN$37,0))))))) -> 298 | Y63: =AL143+V63-W63-X63+T63-U63 -> -411405.42 | Z63: =IF(B63<=55,$AL$3,$AN$3)*(IF(Y63>=20000,20000,Y63)) -> -24684.325 | BG63: Age Cash Withdrawal from CPF Ends (ERS) | BH63: 60
B64: =B63+1 -> 58 | C64: =IF(B64>=67,$BI$55,C63+(1.0244%*C63)) -> 415.7976 | D64: =IF(B64<=20,$AL$14,IF(B64<=30,$AL$15,IF(B64<=40,$AL$16,IF(B64<=50,$AL$17,IF(B64<=60,$AL$18,IF(B64<=65,$AL$19,IF(B64<=70,$AL$20, IF(B64<=73,$AL$21,IF(B64<=75,$AL$22,IF(B64<=78,$AL$23,IF(B64<=80,$AL$24,IF(B64<=83,$AL$25,IF(B64<=85,$AL$26,IF(B64<=90,$AL$27,$AL$28)))))))))))))) -> 800 | E64: =IF(B64<=20,$AM$14,IF(B64<=30,$AM$15,IF(B64<=40,$AM$16,IF(B64<=50,$AM$17,IF(B64<=60,$AM$18,IF(B64<=65,$AM$19,IF(B64<=70,$AM$20, IF(B64<=73,$AM$21,IF(B64<=75,$AM$22,IF(B64<=78,$AM$23,IF(B64<=80,$AM$24,IF(B64<=83,$AM$25,IF(B64<=85,$AM$26,IF(B64<=90,$AM$27,$AM$28)))))))))))))) -> 600 | F64: 600 | G64: =IF(B64>=$BH$31,0,IF(B64<=35,$BJ$4,IF(B64<=45,$BJ$5,IF(B64<=50,$BJ$6,IF(B64<=55,$BJ$7,IF(B64<=60,$BJ$8,IF(B64<=65,$BJ$9,IF(B64<=70,$BJ$10,$BJ$11)))))))*$BH$37) -> 6626.6655 | H64: =K63-C64-D64-E64-F64+G64 -> 79710.868 | I64: =$AL$8*H64 -> 3188.4347 | J64: =IF(I64+H64-$AL$35>0,I64+H64-$AL$35,0) -> 7399.3026 | K64: =H64+I64-J64 -> 75500 | M64: =IF(R63>=BH51,BH51,0) -> 494.4828 | N64: =IF(B64<$BH$31,IF(B65<=35,$BI$4,IF(B65<=45,$BI$5,IF(B65<=50,$BI$6,IF(B65<=55,$BI$7,IF(B65<=60,$BI$8,IF(B65<=65,$BI$9,IF(B65<=70,$BI$10,$BI$11)))))))*$BH$37,0) -> 5362.7665 | O64: =R63+N64-M64 -> 22221.446 | P64: =IF(B64<=55,$AL$5,$AN$6)*(IF(O64>=40000,40000,O64)) -> 1333.2867 | Q64: =$AN$7*IF(O64>=40000,O64-40000,0) -> 0 | R64: =O64+P64+Q64 -> 23554.733 | T64: =IF(J64>=0,J64,0) -> 7399.3026 | U64: =IF(AL144>=$BH$48,$BH$48-M64,0) -> 0 | V64: =IF(B64>=$BH$31,0,IF(B64<=35,$BH$4,IF(B64<=45,$BH$5,IF(B64<=50,$BH$6,IF(B64<=55,$BH$7,IF(B64<=60,$BH$8,IF(B64<=65,$BH$9,IF(B64<=70,$BH$10,$BH$11)))))))*$BH$37) -> 6040.1068 | W64: =IF(B64<($BH$57+$BH$30),$BH$56*12,0) -> 0 | X64: =IF(B64<=34,$AN$31,IF(B64<=39,$AN$32,IF(B64<=44,$AN$33,IF(B64<=49,$AN$34,IF(B64<=54,$AN$35,IF(B64<=59,$AN$36,IF(B64<=69,$AN$37,0))))))) -> 298 | Y64: =AL144+V64-W64-X64+T64-U64 -> -422948.34 | Z64: =IF(B64<=55,$AL$3,$AN$3)*(IF(Y64>=20000,20000,Y64)) -> -25376.9 | AR64: 55 | AS64: - | AT64: =IF(AU45-AY45>0,AU45-AY45,0) -> 0 | AU64: =IF(AU45-AY45>=0,AT45,AT45-(AY45-AU45)) -> -959778.47 | AV64: =AS45 -> 62168.79 | AW64: =SUM(AS64:AU64) -> -959778.47 | AX64: =BH8 -> 0.100334 | AY64: 55 | BG64: Age Cash Withdrawal from CPF Ends (BRS) | BH64: 90
B65: =B64+1 -> 59 | C65: =IF(B65>=67,$BI$55,C64+(1.0244%*C64)) -> 420.05703 | D65: =IF(B65<=20,$AL$14,IF(B65<=30,$AL$15,IF(B65<=40,$AL$16,IF(B65<=50,$AL$17,IF(B65<=60,$AL$18,IF(B65<=65,$AL$19,IF(B65<=70,$AL$20, IF(B65<=73,$AL$21,IF(B65<=75,$AL$22,IF(B65<=78,$AL$23,IF(B65<=80,$AL$24,IF(B65<=83,$AL$25,IF(B65<=85,$AL$26,IF(B65<=90,$AL$27,$AL$28)))))))))))))) -> 800 | E65: =IF(B65<=20,$AM$14,IF(B65<=30,$AM$15,IF(B65<=40,$AM$16,IF(B65<=50,$AM$17,IF(B65<=60,$AM$18,IF(B65<=65,$AM$19,IF(B65<=70,$AM$20, IF(B65<=73,$AM$21,IF(B65<=75,$AM$22,IF(B65<=78,$AM$23,IF(B65<=80,$AM$24,IF(B65<=83,$AM$25,IF(B65<=85,$AM$26,IF(B65<=90,$AM$27,$AM$28)))))))))))))) -> 600 | F65: 600 | G65: =IF(B65>=$BH$31,0,IF(B65<=35,$BJ$4,IF(B65<=45,$BJ$5,IF(B65<=50,$BJ$6,IF(B65<=55,$BJ$7,IF(B65<=60,$BJ$8,IF(B65<=65,$BJ$9,IF(B65<=70,$BJ$10,$BJ$11)))))))*$BH$37) -> 6626.6655 | H65: =K64-C65-D65-E65-F65+G65 -> 79706.608 | I65: =$AL$8*H65 -> 3188.2643 | J65: =IF(I65+H65-$AL$35>0,I65+H65-$AL$35,0) -> 7394.8728 | K65: =H65+I65-J65 -> 75500 | M65: =IF(R64>=BH52,BH52,0) -> 451.3667 | N65: =IF(B65<$BH$31,IF(B66<=35,$BI$4,IF(B66<=45,$BI$5,IF(B66<=50,$BI$6,IF(B66<=55,$BI$7,IF(B66<=60,$BI$8,IF(B66<=65,$BI$9,IF(B66<=70,$BI$10,$BI$11)))))))*$BH$37,0) -> 5362.7665 | O65: =R64+N65-M65 -> 28466.132 | P65: =IF(B65<=55,$AL$5,$AN$6)*(IF(O65>=40000,40000,O65)) -> 1707.9679 | Q65: =$AN$7*IF(O65>=40000,O65-40000,0) -> 0 | R65: =O65+P65+Q65 -> 30174.1 | T65: =IF(J65>=0,J65,0) -> 7394.8728 | U65: =IF(AL145>=$BH$48,$BH$48-M65,0) -> 0 | V65: =IF(B65>=$BH$31,0,IF(B65<=35,$BH$4,IF(B65<=45,$BH$5,IF(B65<=50,$BH$6,IF(B65<=55,$BH$7,IF(B65<=60,$BH$8,IF(B65<=65,$BH$9,IF(B65<=70,$BH$10,$BH$11)))))))*$BH$37) -> 6040.1068 | W65: =IF(B65<($BH$57+$BH$30),$BH$56*12,0) -> 0 | X65: =IF(B65<=34,$AN$31,IF(B65<=39,$AN$32,IF(B65<=44,$AN$33,IF(B65<=49,$AN$34,IF(B65<=54,$AN$35,IF(B65<=59,$AN$36,IF(B65<=69,$AN$37,0))))))) -> 298 | Y65: =AL145+V65-W65-X65+T65-U65 -> -435188.26 | Z65: =IF(B65<=55,$AL$3,$AN$3)*(IF(Y65>=20000,20000,Y65)) -> -26111.296 | AR65: 65 | AS65: =IF(AR65<=65,12,(AR65-65)*12)*$AT$52 -> 99336.991 | AT65: =VLOOKUP(AR65,B108:Z156,17,) -> 72698.288 | AU65: =VLOOKUP(AR65,$B$106:$Z$156,25,) -> -91991.757 | AV65: =VLOOKUP(AR65,$B$190:$AM$235,10,) -> 66000 | AW65: =SUM(AS65:AU65) -> 80043.522 | AX65: =$AT$52 -> 8278.0826 | AY65: 65
B66: =B65+1 -> 60 | C66: =IF(B66>=67,$BI$55,C65+(1.0244%*C65)) -> 424.3601 | D66: =IF(B66<=20,$AL$14,IF(B66<=30,$AL$15,IF(B66<=40,$AL$16,IF(B66<=50,$AL$17,IF(B66<=60,$AL$18,IF(B66<=65,$AL$19,IF(B66<=70,$AL$20, IF(B66<=73,$AL$21,IF(B66<=75,$AL$22,IF(B66<=78,$AL$23,IF(B66<=80,$AL$24,IF(B66<=83,$AL$25,IF(B66<=85,$AL$26,IF(B66<=90,$AL$27,$AL$28)))))))))))))) -> 800 | E66: =IF(B66<=20,$AM$14,IF(B66<=30,$AM$15,IF(B66<=40,$AM$16,IF(B66<=50,$AM$17,IF(B66<=60,$AM$18,IF(B66<=65,$AM$19,IF(B66<=70,$AM$20, IF(B66<=73,$AM$21,IF(B66<=75,$AM$22,IF(B66<=78,$AM$23,IF(B66<=80,$AM$24,IF(B66<=83,$AM$25,IF(B66<=85,$AM$26,IF(B66<=90,$AM$27,$AM$28)))))))))))))) -> 600 | F66: 600 | G66: =IF(B66>=$BH$31,0,IF(B66<=35,$BJ$4,IF(B66<=45,$BJ$5,IF(B66<=50,$BJ$6,IF(B66<=55,$BJ$7,IF(B66<=60,$BJ$8,IF(B66<=65,$BJ$9,IF(B66<=70,$BJ$10,$BJ$11)))))))*$BH$37) -> 6626.6655 | H66: =K65-C66-D66-E66-F66+G66 -> 79702.305 | I66: =$AL$8*H66 -> 3188.0922 | J66: =IF(I66+H66-$AL$35>0,I66+H66-$AL$35,0) -> 7390.3976 | K66: =H66+I66-J66 -> 75500 | M66: =IF(R65>=BH53,BH53,0) -> 0 | N66: =IF(B66<$BH$31,IF(B67<=35,$BI$4,IF(B67<=45,$BI$5,IF(B67<=50,$BI$6,IF(B67<=55,$BI$7,IF(B67<=60,$BI$8,IF(B67<=65,$BI$9,IF(B67<=70,$BI$10,$BI$11)))))))*$BH$37,0) -> 5143.8492 | O66: =R65+N66-M66 -> 35317.949 | P66: =IF(B66<=55,$AL$5,$AN$6)*(IF(O66>=40000,40000,O66)) -> 2119.077 | Q66: =$AN$7*IF(O66>=40000,O66-40000,0) -> 0 | R66: =O66+P66+Q66 -> 37437.026 | T66: =IF(J66>=0,J66,0) -> 7390.3976 | U66: =IF(AL146>=$BH$48,$BH$48-M66,0) -> 0 | V66: =IF(B66>=$BH$31,0,IF(B66<=35,$BH$4,IF(B66<=45,$BH$5,IF(B66<=50,$BH$6,IF(B66<=55,$BH$7,IF(B66<=60,$BH$8,IF(B66<=65,$BH$9,IF(B66<=70,$BH$10,$BH$11)))))))*$BH$37) -> 6040.1068 | W66: =IF(B66<($BH$57+$BH$30),$BH$56*12,0) -> 0 | X66: =IF(B66<=34,$AN$31,IF(B66<=39,$AN$32,IF(B66<=44,$AN$33,IF(B66<=49,$AN$34,IF(B66<=54,$AN$35,IF(B66<=59,$AN$36,IF(B66<=69,$AN$37,0))))))) -> 298 | Y66: =AL146+V66-W66-X66+T66-U66 -> -448167.05 | Z66: =IF(B66<=55,$AL$3,$AN$3)*(IF(Y66>=20000,20000,Y66)) -> -26890.023 | AR66: 75 | AS66: =IF(AR66<=65,12,(AR66-65)*12)*$AT$52 -> 993369.91 | AT66: =VLOOKUP(AR66,B109:Z157,17,) -> 121115.84 | AU66: =VLOOKUP(AR66,$B$106:$Z$156,25,) -> -164560.1 | AV66: =VLOOKUP(AR66,$B$190:$AM$235,10,) -> 66000 | AW66: =SUM(AS66:AU66) -> 949925.65 | AX66: =$AT$52 -> 8278.0826 | AY66: 75
B67: =B66+1 -> 61 | C67: =IF(B67>=67,$BI$55,C66+(1.0244%*C66)) -> 428.70724 | D67: =IF(B67<=20,$AL$14,IF(B67<=30,$AL$15,IF(B67<=40,$AL$16,IF(B67<=50,$AL$17,IF(B67<=60,$AL$18,IF(B67<=65,$AL$19,IF(B67<=70,$AL$20, IF(B67<=73,$AL$21,IF(B67<=75,$AL$22,IF(B67<=78,$AL$23,IF(B67<=80,$AL$24,IF(B67<=83,$AL$25,IF(B67<=85,$AL$26,IF(B67<=90,$AL$27,$AL$28)))))))))))))) -> 1020 | E67: =IF(B67<=20,$AM$14,IF(B67<=30,$AM$15,IF(B67<=40,$AM$16,IF(B67<=50,$AM$17,IF(B67<=60,$AM$18,IF(B67<=65,$AM$19,IF(B67<=70,$AM$20, IF(B67<=73,$AM$21,IF(B67<=75,$AM$22,IF(B67<=78,$AM$23,IF(B67<=80,$AM$24,IF(B67<=83,$AM$25,IF(B67<=85,$AM$26,IF(B67<=90,$AM$27,$AM$28)))))))))))))) -> 600 | F67: 600 | G67: =IF(B67>=$BH$31,0,IF(B67<=35,$BJ$4,IF(B67<=45,$BJ$5,IF(B67<=50,$BJ$6,IF(B67<=55,$BJ$7,IF(B67<=60,$BJ$8,IF(B67<=65,$BJ$9,IF(B67<=70,$BJ$10,$BJ$11)))))))*$BH$37) -> 6750.9484 | H67: =K66-C67-D67-E67-F67+G67 -> 79602.241 | I67: =$AL$8*H67 -> 3184.0896 | J67: =IF(I67+H67-$AL$35>0,I67+H67-$AL$35,0) -> 7286.3308 | K67: =H67+I67-J67 -> 75500 | M67: =IF(R66>=BH54,BH54,0) -> 800 | N67: =IF(B67<$BH$31,IF(B68<=35,$BI$4,IF(B68<=45,$BI$5,IF(B68<=50,$BI$6,IF(B68<=55,$BI$7,IF(B68<=60,$BI$8,IF(B68<=65,$BI$9,IF(B68<=70,$BI$10,$BI$11)))))))*$BH$37,0) -> 5143.8492 | O67: =R66+N67-M67 -> 41780.876 | P67: =IF(B67<=55,$AL$5,$AN$6)*(IF(O67>=40000,40000,O67)) -> 2400 | Q67: =$AN$7*IF(O67>=40000,O67-40000,0) -> 89.043781 | R67: =O67+P67+Q67 -> 44269.919 | T67: =IF(J67>=0,J67,0) -> 7286.3308 | U67: =IF(AL147>=$BH$48,$BH$48-M67,0) -> 0 | V67: =IF(B67>=$BH$31,0,IF(B67<=35,$BH$4,IF(B67<=45,$BH$5,IF(B67<=50,$BH$6,IF(B67<=55,$BH$7,IF(B67<=60,$BH$8,IF(B67<=65,$BH$9,IF(B67<=70,$BH$10,$BH$11)))))))*$BH$37) -> 2209.7614 | W67: =IF(B67<($BH$57+$BH$30),$BH$56*12,0) -> 0 | X67: =IF(B67<=34,$AN$31,IF(B67<=39,$AN$32,IF(B67<=44,$AN$33,IF(B67<=49,$AN$34,IF(B67<=54,$AN$35,IF(B67<=59,$AN$36,IF(B67<=69,$AN$37,0))))))) -> 298 | Y67: =AL147+V67-W67-X67+T67-U67 -> -465858.98 | Z67: =IF(B67<=55,$AL$3,$AN$3)*(IF(Y67>=20000,20000,Y67)) -> -27951.539 | AR67: 85 | AS67: =IF(AR67<=65,12,(AR67-65)*12)*$AT$52 -> 1986739.8 | AT67: =VLOOKUP(AR67,B110:Z158,17,) -> 201888.22 | AU67: =VLOOKUP(AR67,$B$106:$Z$156,25,) -> -294702.07 | AV67: =VLOOKUP(AR67,$B$190:$AM$235,10,) -> 73674.486 | AW67: =SUM(AS67:AU67) -> 1893926 | AX67: =$AT$52 -> 8278.0826 | AY67: 85
B68: =B67+1 -> 62 | C68: =IF(B68>=67,$BI$55,C67+(1.0244%*C67)) -> 433.09892 | D68: =IF(B68<=20,$AL$14,IF(B68<=30,$AL$15,IF(B68<=40,$AL$16,IF(B68<=50,$AL$17,IF(B68<=60,$AL$18,IF(B68<=65,$AL$19,IF(B68<=70,$AL$20, IF(B68<=73,$AL$21,IF(B68<=75,$AL$22,IF(B68<=78,$AL$23,IF(B68<=80,$AL$24,IF(B68<=83,$AL$25,IF(B68<=85,$AL$26,IF(B68<=90,$AL$27,$AL$28)))))))))))))) -> 1020 | E68: =IF(B68<=20,$AM$14,IF(B68<=30,$AM$15,IF(B68<=40,$AM$16,IF(B68<=50,$AM$17,IF(B68<=60,$AM$18,IF(B68<=65,$AM$19,IF(B68<=70,$AM$20, IF(B68<=73,$AM$21,IF(B68<=75,$AM$22,IF(B68<=78,$AM$23,IF(B68<=80,$AM$24,IF(B68<=83,$AM$25,IF(B68<=85,$AM$26,IF(B68<=90,$AM$27,$AM$28)))))))))))))) -> 600 | F68: 600 | G68: =IF(B68>=$BH$31,0,IF(B68<=35,$BJ$4,IF(B68<=45,$BJ$5,IF(B68<=50,$BJ$6,IF(B68<=55,$BJ$7,IF(B68<=60,$BJ$8,IF(B68<=65,$BJ$9,IF(B68<=70,$BJ$10,$BJ$11)))))))*$BH$37) -> 6750.9484 | H68: =K67-C68-D68-E68-F68+G68 -> 79597.849 | I68: =$AL$8*H68 -> 3183.914 | J68: =IF(I68+H68-$AL$35>0,I68+H68-$AL$35,0) -> 7281.7635 | K68: =H68+I68-J68 -> 75500 | M68: =IF(R67>=BH55,BH55,0) -> 0 | N68: =IF(B68<$BH$31,IF(B69<=35,$BI$4,IF(B69<=45,$BI$5,IF(B69<=50,$BI$6,IF(B69<=55,$BI$7,IF(B69<=60,$BI$8,IF(B69<=65,$BI$9,IF(B69<=70,$BI$10,$BI$11)))))))*$BH$37,0) -> 5143.8492 | O68: =R67+N68-M68 -> 49413.769 | P68: =IF(B68<=55,$AL$5,$AN$6)*(IF(O68>=40000,40000,O68)) -> 2400 | Q68: =$AN$7*IF(O68>=40000,O68-40000,0) -> 470.68843 | R68: =O68+P68+Q68 -> 52284.457 | T68: =IF(J68>=0,J68,0) -> 7281.7635 | U68: =IF(AL148>=$BH$48,$BH$48-M68,0) -> 0 | V68: =IF(B68>=$BH$31,0,IF(B68<=35,$BH$4,IF(B68<=45,$BH$5,IF(B68<=50,$BH$6,IF(B68<=55,$BH$7,IF(B68<=60,$BH$8,IF(B68<=65,$BH$9,IF(B68<=70,$BH$10,$BH$11)))))))*$BH$37) -> 2209.7614 | W68: =IF(B68<($BH$57+$BH$30),$BH$56*12,0) -> 0 | X68: =IF(B68<=34,$AN$31,IF(B68<=39,$AN$32,IF(B68<=44,$AN$33,IF(B68<=49,$AN$34,IF(B68<=54,$AN$35,IF(B68<=59,$AN$36,IF(B68<=69,$AN$37,0))))))) -> 298 | Y68: =AL148+V68-W68-X68+T68-U68 -> -484617 | Z68: =IF(B68<=55,$AL$3,$AN$3)*(IF(Y68>=20000,20000,Y68)) -> -29077.02 | AR68: ='[10]Retirement Dashboard'!E40 -> 90 | AS68: =IF(AR68<=65,12,(AR68-65)*12)*$AT$52 -> 2483424.8 | AT68: =VLOOKUP(AR68,B111:Z159,17,) -> #REF! | AU68: =VLOOKUP(AR68,$B$106:$Z$156,25,) -> -394377.85 | AV68: =VLOOKUP(AR68,$B$190:$AM$235,10,) -> 73159.824 | AW68: =SUM(AS68:AU68) -> #REF! | AX68: =$AT$52 -> 8278.0826 | AY68: 86
B69: =B68+1 -> 63 | C69: =IF(B69>=67,$BI$55,C68+(1.0244%*C68)) -> 437.53558 | D69: =IF(B69<=20,$AL$14,IF(B69<=30,$AL$15,IF(B69<=40,$AL$16,IF(B69<=50,$AL$17,IF(B69<=60,$AL$18,IF(B69<=65,$AL$19,IF(B69<=70,$AL$20, IF(B69<=73,$AL$21,IF(B69<=75,$AL$22,IF(B69<=78,$AL$23,IF(B69<=80,$AL$24,IF(B69<=83,$AL$25,IF(B69<=85,$AL$26,IF(B69<=90,$AL$27,$AL$28)))))))))))))) -> 1020 | E69: =IF(B69<=20,$AM$14,IF(B69<=30,$AM$15,IF(B69<=40,$AM$16,IF(B69<=50,$AM$17,IF(B69<=60,$AM$18,IF(B69<=65,$AM$19,IF(B69<=70,$AM$20, IF(B69<=73,$AM$21,IF(B69<=75,$AM$22,IF(B69<=78,$AM$23,IF(B69<=80,$AM$24,IF(B69<=83,$AM$25,IF(B69<=85,$AM$26,IF(B69<=90,$AM$27,$AM$28)))))))))))))) -> 600 | F69: 600 | G69: =IF(B69>=$BH$31,0,IF(B69<=35,$BJ$4,IF(B69<=45,$BJ$5,IF(B69<=50,$BJ$6,IF(B69<=55,$BJ$7,IF(B69<=60,$BJ$8,IF(B69<=65,$BJ$9,IF(B69<=70,$BJ$10,$BJ$11)))))))*$BH$37) -> 6750.9484 | H69: =K68-C69-D69-E69-F69+G69 -> 79593.413 | I69: =$AL$8*H69 -> 3183.7365 | J69: =IF(I69+H69-$AL$35>0,I69+H69-$AL$35,0) -> 7277.1493 | K69: =H69+I69-J69 -> 75500 | M69: =IF(R68>=BH56,BH56,0) -> 817.1376 | N69: =IF(B69<$BH$31,IF(B70<=35,$BI$4,IF(B70<=45,$BI$5,IF(B70<=50,$BI$6,IF(B70<=55,$BI$7,IF(B70<=60,$BI$8,IF(B70<=65,$BI$9,IF(B70<=70,$BI$10,$BI$11)))))))*$BH$37,0) -> 5143.8492 | O69: =R68+N69-M69 -> 56611.169 | P69: =IF(B69<=55,$AL$5,$AN$6)*(IF(O69>=40000,40000,O69)) -> 2400 | Q69: =$AN$7*IF(O69>=40000,O69-40000,0) -> 830.55843 | R69: =O69+P69+Q69 -> 59841.727 | T69: =IF(J69>=0,J69,0) -> 7277.1493 | U69: =IF(AL149>=$BH$48,$BH$48-M69,0) -> 0 | V69: =IF(B69>=$BH$31,0,IF(B69<=35,$BH$4,IF(B69<=45,$BH$5,IF(B69<=50,$BH$6,IF(B69<=55,$BH$7,IF(B69<=60,$BH$8,IF(B69<=65,$BH$9,IF(B69<=70,$BH$10,$BH$11)))))))*$BH$37) -> 2209.7614 | W69: =IF(B69<($BH$57+$BH$30),$BH$56*12,0) -> 0 | X69: =IF(B69<=34,$AN$31,IF(B69<=39,$AN$32,IF(B69<=44,$AN$33,IF(B69<=49,$AN$34,IF(B69<=54,$AN$35,IF(B69<=59,$AN$36,IF(B69<=69,$AN$37,0))))))) -> 298 | Y69: =AL149+V69-W69-X69+T69-U69 -> -504505.11 | Z69: =IF(B69<=55,$AL$3,$AN$3)*(IF(Y69>=20000,20000,Y69)) -> -30270.306
B70: =B69+1 -> 64 | C70: =IF(B70>=67,$BI$55,C69+(1.0244%*C69)) -> 442.0177 | D70: =IF(B70<=20,$AL$14,IF(B70<=30,$AL$15,IF(B70<=40,$AL$16,IF(B70<=50,$AL$17,IF(B70<=60,$AL$18,IF(B70<=65,$AL$19,IF(B70<=70,$AL$20, IF(B70<=73,$AL$21,IF(B70<=75,$AL$22,IF(B70<=78,$AL$23,IF(B70<=80,$AL$24,IF(B70<=83,$AL$25,IF(B70<=85,$AL$26,IF(B70<=90,$AL$27,$AL$28)))))))))))))) -> 1020 | E70: =IF(B70<=20,$AM$14,IF(B70<=30,$AM$15,IF(B70<=40,$AM$16,IF(B70<=50,$AM$17,IF(B70<=60,$AM$18,IF(B70<=65,$AM$19,IF(B70<=70,$AM$20, IF(B70<=73,$AM$21,IF(B70<=75,$AM$22,IF(B70<=78,$AM$23,IF(B70<=80,$AM$24,IF(B70<=83,$AM$25,IF(B70<=85,$AM$26,IF(B70<=90,$AM$27,$AM$28)))))))))))))) -> 600 | F70: 600 | G70: =IF(B70>=$BH$31,0,IF(B70<=35,$BJ$4,IF(B70<=45,$BJ$5,IF(B70<=50,$BJ$6,IF(B70<=55,$BJ$7,IF(B70<=60,$BJ$8,IF(B70<=65,$BJ$9,IF(B70<=70,$BJ$10,$BJ$11)))))))*$BH$37) -> 6750.9484 | H70: =K69-C70-D70-E70-F70+G70 -> 79588.931 | I70: =$AL$8*H70 -> 3183.5572 | J70: =IF(I70+H70-$AL$35>0,I70+H70-$AL$35,0) -> 7272.4879 | K70: =H70+I70-J70 -> 75500 | M70: =IF(R69>=BH57,BH57,0) -> 0 | N70: =IF(B70<$BH$31,IF(B71<=35,$BI$4,IF(B71<=45,$BI$5,IF(B71<=50,$BI$6,IF(B71<=55,$BI$7,IF(B71<=60,$BI$8,IF(B71<=65,$BI$9,IF(B71<=70,$BI$10,$BI$11)))))))*$BH$37,0) -> 5143.8492 | O70: =R69+N70-M70 -> 64985.576 | P70: =IF(B70<=55,$AL$5,$AN$6)*(IF(O70>=40000,40000,O70)) -> 2400 | Q70: =$AN$7*IF(O70>=40000,O70-40000,0) -> 1249.2788 | R70: =O70+P70+Q70 -> 68634.855 | T70: =IF(J70>=0,J70,0) -> 7272.4879 | U70: =IF(AL150>=$BH$48,$BH$48-M70,0) -> 0 | V70: =IF(B70>=$BH$31,0,IF(B70<=35,$BH$4,IF(B70<=45,$BH$5,IF(B70<=50,$BH$6,IF(B70<=55,$BH$7,IF(B70<=60,$BH$8,IF(B70<=65,$BH$9,IF(B70<=70,$BH$10,$BH$11)))))))*$BH$37) -> 2209.7614 | W70: =IF(B70<($BH$57+$BH$30),$BH$56*12,0) -> 0 | X70: =IF(B70<=34,$AN$31,IF(B70<=39,$AN$32,IF(B70<=44,$AN$33,IF(B70<=49,$AN$34,IF(B70<=54,$AN$35,IF(B70<=59,$AN$36,IF(B70<=69,$AN$37,0))))))) -> 298 | Y70: =AL150+V70-W70-X70+T70-U70 -> -525591.16 | Z70: =IF(B70<=55,$AL$3,$AN$3)*(IF(Y70>=20000,20000,Y70)) -> -31535.47
B71: =B70+1 -> 65 | C71: =IF(B71>=67,$BI$55,C70+(1.0244%*C70)) -> 446.54573 | D71: =IF(B71<=20,$AL$14,IF(B71<=30,$AL$15,IF(B71<=40,$AL$16,IF(B71<=50,$AL$17,IF(B71<=60,$AL$18,IF(B71<=65,$AL$19,IF(B71<=70,$AL$20, IF(B71<=73,$AL$21,IF(B71<=75,$AL$22,IF(B71<=78,$AL$23,IF(B71<=80,$AL$24,IF(B71<=83,$AL$25,IF(B71<=85,$AL$26,IF(B71<=90,$AL$27,$AL$28)))))))))))))) -> 1020 | E71: =IF(B71<=20,$AM$14,IF(B71<=30,$AM$15,IF(B71<=40,$AM$16,IF(B71<=50,$AM$17,IF(B71<=60,$AM$18,IF(B71<=65,$AM$19,IF(B71<=70,$AM$20, IF(B71<=73,$AM$21,IF(B71<=75,$AM$22,IF(B71<=78,$AM$23,IF(B71<=80,$AM$24,IF(B71<=83,$AM$25,IF(B71<=85,$AM$26,IF(B71<=90,$AM$27,$AM$28)))))))))))))) -> 600 | F71: 600 | G71: =IF(B71>=$BH$31,0,IF(B71<=35,$BJ$4,IF(B71<=45,$BJ$5,IF(B71<=50,$BJ$6,IF(B71<=55,$BJ$7,IF(B71<=60,$BJ$8,IF(B71<=65,$BJ$9,IF(B71<=70,$BJ$10,$BJ$11)))))))*$BH$37) -> 0 | H71: =K70-C71-D71-E71-F71+G71 -> 72833.454 | I71: =$AL$8*H71 -> 2913.3382 | J71: =IF(I71+H71-$AL$35>0,I71+H71-$AL$35,0) -> 246.79244 | K71: =H71+I71-J71 -> 75500 | M71: =IF(R70>=BH58,BH58,0) -> 188 | N71: =IF(B71<$BH$31,IF(B72<=35,$BI$4,IF(B72<=45,$BI$5,IF(B72<=50,$BI$6,IF(B72<=55,$BI$7,IF(B72<=60,$BI$8,IF(B72<=65,$BI$9,IF(B72<=70,$BI$10,$BI$11)))))))*$BH$37,0) -> 0 | O71: =R70+N71-M71 -> 68446.855 | P71: =IF(B71<=55,$AL$5,$AN$6)*(IF(O71>=40000,40000,O71)) -> 2400 | Q71: =$AN$7*IF(O71>=40000,O71-40000,0) -> 1422.3428 | R71: =O71+P71+Q71 -> 72269.198 | T71: =IF(J71>=0,J71,0) -> 246.79244 | U71: =IF(AL151>=$BH$48,$BH$48-M71,0) -> 0 | V71: =IF(B71>=$BH$31,0,IF(B71<=35,$BH$4,IF(B71<=45,$BH$5,IF(B71<=50,$BH$6,IF(B71<=55,$BH$7,IF(B71<=60,$BH$8,IF(B71<=65,$BH$9,IF(B71<=70,$BH$10,$BH$11)))))))*$BH$37) -> 0 | W71: =IF(B71<($BH$57+$BH$30),$BH$56*12,0) -> 0 | X71: =IF(B71<=34,$AN$31,IF(B71<=39,$AN$32,IF(B71<=44,$AN$33,IF(B71<=49,$AN$34,IF(B71<=54,$AN$35,IF(B71<=59,$AN$36,IF(B71<=69,$AN$37,0))))))) -> 298 | Y71: =AL151+V71-W71-X71+T71-U71 -> -557177.84 | Z71: =IF(B71<=55,$AL$3,$AN$3)*(IF(Y71>=20000,20000,Y71)) -> -33430.67
B72: =B71+1 -> 66 | C72: =IF(B72>=67,$BI$55,C71+(1.0244%*C71)) -> 451.12014 | D72: =IF(B72<=20,$AL$14,IF(B72<=30,$AL$15,IF(B72<=40,$AL$16,IF(B72<=50,$AL$17,IF(B72<=60,$AL$18,IF(B72<=65,$AL$19,IF(B72<=70,$AL$20, IF(B72<=73,$AL$21,IF(B72<=75,$AL$22,IF(B72<=78,$AL$23,IF(B72<=80,$AL$24,IF(B72<=83,$AL$25,IF(B72<=85,$AL$26,IF(B72<=90,$AL$27,$AL$28)))))))))))))) -> 1100 | E72: =IF(B72<=20,$AM$14,IF(B72<=30,$AM$15,IF(B72<=40,$AM$16,IF(B72<=50,$AM$17,IF(B72<=60,$AM$18,IF(B72<=65,$AM$19,IF(B72<=70,$AM$20, IF(B72<=73,$AM$21,IF(B72<=75,$AM$22,IF(B72<=78,$AM$23,IF(B72<=80,$AM$24,IF(B72<=83,$AM$25,IF(B72<=85,$AM$26,IF(B72<=90,$AM$27,$AM$28)))))))))))))) -> 600 | F72: 600 | G72: =IF(B72>=$BH$31,0,IF(B72<=35,$BJ$4,IF(B72<=45,$BJ$5,IF(B72<=50,$BJ$6,IF(B72<=55,$BJ$7,IF(B72<=60,$BJ$8,IF(B72<=65,$BJ$9,IF(B72<=70,$BJ$10,$BJ$11)))))))*$BH$37) -> 0 | H72: =K71-C72-D72-E72-F72+G72 -> 72748.88 | I72: =$AL$8*H72 -> 2909.9552 | J72: =IF(I72+H72-$AL$35>0,I72+H72-$AL$35,0) -> 158.83505 | K72: =H72+I72-J72 -> 75500 | M72: =IF(R71>=BH59,BH59,0) -> 600 | N72: =IF(B72<$BH$31,IF(B73<=35,$BI$4,IF(B73<=45,$BI$5,IF(B73<=50,$BI$6,IF(B73<=55,$BI$7,IF(B73<=60,$BI$8,IF(B73<=65,$BI$9,IF(B73<=70,$BI$10,$BI$11)))))))*$BH$37,0) -> 0 | O72: =R71+N72-M72 -> 71669.198 | P72: =IF(B72<=55,$AL$5,$AN$6)*(IF(O72>=40000,40000,O72)) -> 2400 | Q72: =$AN$7*IF(O72>=40000,O72-40000,0) -> 1583.4599 | R72: =O72+P72+Q72 -> 75652.658 | T72: =IF(J72>=0,J72,0) -> 158.83505 | U72: =IF(AL152>=$BH$48,$BH$48-M72,0) -> 0 | V72: =IF(B72>=$BH$31,0,IF(B72<=35,$BH$4,IF(B72<=45,$BH$5,IF(B72<=50,$BH$6,IF(B72<=55,$BH$7,IF(B72<=60,$BH$8,IF(B72<=65,$BH$9,IF(B72<=70,$BH$10,$BH$11)))))))*$BH$37) -> 0 | W72: =IF(B72<($BH$57+$BH$30),$BH$56*12,0) -> 0 | X72: =IF(B72<=34,$AN$31,IF(B72<=39,$AN$32,IF(B72<=44,$AN$33,IF(B72<=49,$AN$34,IF(B72<=54,$AN$35,IF(B72<=59,$AN$36,IF(B72<=69,$AN$37,0))))))) -> 298 | Y72: =AL152+V72-W72-X72+T72-U72 -> -590747.68 | Z72: =IF(B72<=55,$AL$3,$AN$3)*(IF(Y72>=20000,20000,Y72)) -> -35444.861 | AS72: BRS Choice
B73: =B72+1 -> 67 | C73: =IF(B73>=67,$BI$55,C72+(1.0244%*C72)) -> 0 | D73: =IF(B73<=20,$AL$14,IF(B73<=30,$AL$15,IF(B73<=40,$AL$16,IF(B73<=50,$AL$17,IF(B73<=60,$AL$18,IF(B73<=65,$AL$19,IF(B73<=70,$AL$20, IF(B73<=73,$AL$21,IF(B73<=75,$AL$22,IF(B73<=78,$AL$23,IF(B73<=80,$AL$24,IF(B73<=83,$AL$25,IF(B73<=85,$AL$26,IF(B73<=90,$AL$27,$AL$28)))))))))))))) -> 1100 | E73: =IF(B73<=20,$AM$14,IF(B73<=30,$AM$15,IF(B73<=40,$AM$16,IF(B73<=50,$AM$17,IF(B73<=60,$AM$18,IF(B73<=65,$AM$19,IF(B73<=70,$AM$20, IF(B73<=73,$AM$21,IF(B73<=75,$AM$22,IF(B73<=78,$AM$23,IF(B73<=80,$AM$24,IF(B73<=83,$AM$25,IF(B73<=85,$AM$26,IF(B73<=90,$AM$27,$AM$28)))))))))))))) -> 600 | F73: 600 | G73: =IF(B73>=$BH$31,0,IF(B73<=35,$BJ$4,IF(B73<=45,$BJ$5,IF(B73<=50,$BJ$6,IF(B73<=55,$BJ$7,IF(B73<=60,$BJ$8,IF(B73<=65,$BJ$9,IF(B73<=70,$BJ$10,$BJ$11)))))))*$BH$37) -> 0 | H73: =K72-C73-D73-E73-F73+G73 -> 73200 | I73: =$AL$8*H73 -> 2928 | J73: =IF(I73+H73-$AL$35>0,I73+H73-$AL$35,0) -> 628 | K73: =H73+I73-J73 -> 75500 | M73: =IF(R72>=BH60,BH60,0) -> 500 | N73: =IF(B73<$BH$31,IF(B74<=35,$BI$4,IF(B74<=45,$BI$5,IF(B74<=50,$BI$6,IF(B74<=55,$BI$7,IF(B74<=60,$BI$8,IF(B74<=65,$BI$9,IF(B74<=70,$BI$10,$BI$11)))))))*$BH$37,0) -> 0 | O73: =R72+N73-M73 -> 75152.658 | P73: =IF(B73<=55,$AL$5,$AN$6)*(IF(O73>=40000,40000,O73)) -> 2400 | Q73: =$AN$7*IF(O73>=40000,O73-40000,0) -> 1757.6329 | R73: =O73+P73+Q73 -> 79310.291 | T73: =IF(J73>=0,J73,0) -> 628 | U73: =IF(AL153>=$BH$48,$BH$48-M73,0) -> 0 | V73: =IF(B73>=$BH$31,0,IF(B73<=35,$BH$4,IF(B73<=45,$BH$5,IF(B73<=50,$BH$6,IF(B73<=55,$BH$7,IF(B73<=60,$BH$8,IF(B73<=65,$BH$9,IF(B73<=70,$BH$10,$BH$11)))))))*$BH$37) -> 0 | W73: =IF(B73<($BH$57+$BH$30),$BH$56*12,0) -> 0 | X73: =IF(B73<=34,$AN$31,IF(B73<=39,$AN$32,IF(B73<=44,$AN$33,IF(B73<=49,$AN$34,IF(B73<=54,$AN$35,IF(B73<=59,$AN$36,IF(B73<=69,$AN$37,0))))))) -> 298 | Y73: =AL153+V73-W73-X73+T73-U73 -> -625862.54 | Z73: =IF(B73<=55,$AL$3,$AN$3)*(IF(Y73>=20000,20000,Y73)) -> -37551.752 | AR73: Age | AS73: CPF Life Payout | AT73: SA | AU73: OA | AV73: MA | AW73: Total Portfolio | AX73: Cash Income
B74: =B73+1 -> 68 | C74: =IF(B74>=67,$BI$55,C73+(1.0244%*C73)) -> 0 | D74: =IF(B74<=20,$AL$14,IF(B74<=30,$AL$15,IF(B74<=40,$AL$16,IF(B74<=50,$AL$17,IF(B74<=60,$AL$18,IF(B74<=65,$AL$19,IF(B74<=70,$AL$20, IF(B74<=73,$AL$21,IF(B74<=75,$AL$22,IF(B74<=78,$AL$23,IF(B74<=80,$AL$24,IF(B74<=83,$AL$25,IF(B74<=85,$AL$26,IF(B74<=90,$AL$27,$AL$28)))))))))))))) -> 1100 | E74: =IF(B74<=20,$AM$14,IF(B74<=30,$AM$15,IF(B74<=40,$AM$16,IF(B74<=50,$AM$17,IF(B74<=60,$AM$18,IF(B74<=65,$AM$19,IF(B74<=70,$AM$20, IF(B74<=73,$AM$21,IF(B74<=75,$AM$22,IF(B74<=78,$AM$23,IF(B74<=80,$AM$24,IF(B74<=83,$AM$25,IF(B74<=85,$AM$26,IF(B74<=90,$AM$27,$AM$28)))))))))))))) -> 600 | F74: 600 | G74: =IF(B74>=$BH$31,0,IF(B74<=35,$BJ$4,IF(B74<=45,$BJ$5,IF(B74<=50,$BJ$6,IF(B74<=55,$BJ$7,IF(B74<=60,$BJ$8,IF(B74<=65,$BJ$9,IF(B74<=70,$BJ$10,$BJ$11)))))))*$BH$37) -> 0 | H74: =K73-C74-D74-E74-F74+G74 -> 73200 | I74: =$AL$8*H74 -> 2928 | J74: =IF(I74+H74-$AL$35>0,I74+H74-$AL$35,0) -> 628 | K74: =H74+I74-J74 -> 75500 | M74: =IF(R73>=BH61,BH61,0) -> 0 | N74: =IF(B74<$BH$31,IF(B75<=35,$BI$4,IF(B75<=45,$BI$5,IF(B75<=50,$BI$6,IF(B75<=55,$BI$7,IF(B75<=60,$BI$8,IF(B75<=65,$BI$9,IF(B75<=70,$BI$10,$BI$11)))))))*$BH$37,0) -> 0 | O74: =R73+N74-M74 -> 79310.291 | P74: =IF(B74<=55,$AL$5,$AN$6)*(IF(O74>=40000,40000,O74)) -> 2400 | Q74: =$AN$7*IF(O74>=40000,O74-40000,0) -> 1965.5145 | R74: =O74+P74+Q74 -> 83675.805 | T74: =IF(J74>=0,J74,0) -> 628 | U74: =IF(AL154>=$BH$48,$BH$48-M74,0) -> 0 | V74: =IF(B74>=$BH$31,0,IF(B74<=35,$BH$4,IF(B74<=45,$BH$5,IF(B74<=50,$BH$6,IF(B74<=55,$BH$7,IF(B74<=60,$BH$8,IF(B74<=65,$BH$9,IF(B74<=70,$BH$10,$BH$11)))))))*$BH$37) -> 0 | W74: =IF(B74<($BH$57+$BH$30),$BH$56*12,0) -> 0 | X74: =IF(B74<=34,$AN$31,IF(B74<=39,$AN$32,IF(B74<=44,$AN$33,IF(B74<=49,$AN$34,IF(B74<=54,$AN$35,IF(B74<=59,$AN$36,IF(B74<=69,$AN$37,0))))))) -> 298 | Y74: =AL154+V74-W74-X74+T74-U74 -> -663084.29 | Z74: =IF(B74<=55,$AL$3,$AN$3)*(IF(Y74>=20000,20000,Y74)) -> -39785.057
B75: =B74+1 -> 69 | C75: =IF(B75>=67,$BI$55,C74+(1.0244%*C74)) -> 0 | D75: =IF(B75<=20,$AL$14,IF(B75<=30,$AL$15,IF(B75<=40,$AL$16,IF(B75<=50,$AL$17,IF(B75<=60,$AL$18,IF(B75<=65,$AL$19,IF(B75<=70,$AL$20, IF(B75<=73,$AL$21,IF(B75<=75,$AL$22,IF(B75<=78,$AL$23,IF(B75<=80,$AL$24,IF(B75<=83,$AL$25,IF(B75<=85,$AL$26,IF(B75<=90,$AL$27,$AL$28)))))))))))))) -> 1100 | E75: =IF(B75<=20,$AM$14,IF(B75<=30,$AM$15,IF(B75<=40,$AM$16,IF(B75<=50,$AM$17,IF(B75<=60,$AM$18,IF(B75<=65,$AM$19,IF(B75<=70,$AM$20, IF(B75<=73,$AM$21,IF(B75<=75,$AM$22,IF(B75<=78,$AM$23,IF(B75<=80,$AM$24,IF(B75<=83,$AM$25,IF(B75<=85,$AM$26,IF(B75<=90,$AM$27,$AM$28)))))))))))))) -> 600 | F75: 600 | G75: =IF(B75>=$BH$31,0,IF(B75<=35,$BJ$4,IF(B75<=45,$BJ$5,IF(B75<=50,$BJ$6,IF(B75<=55,$BJ$7,IF(B75<=60,$BJ$8,IF(B75<=65,$BJ$9,IF(B75<=70,$BJ$10,$BJ$11)))))))*$BH$37) -> 0 | H75: =K74-C75-D75-E75-F75+G75 -> 73200 | I75: =$AL$8*H75 -> 2928 | J75: =IF(I75+H75-$AL$35>0,I75+H75-$AL$35,0) -> 628 | K75: =H75+I75-J75 -> 75500 | M75: =IF(R74>=BH62,BH62,0) -> 77 | N75: =IF(B75<$BH$31,IF(B76<=35,$BI$4,IF(B76<=45,$BI$5,IF(B76<=50,$BI$6,IF(B76<=55,$BI$7,IF(B76<=60,$BI$8,IF(B76<=65,$BI$9,IF(B76<=70,$BI$10,$BI$11)))))))*$BH$37,0) -> 0 | O75: =R74+N75-M75 -> 83598.805 | P75: =IF(B75<=55,$AL$5,$AN$6)*(IF(O75>=40000,40000,O75)) -> 2400 | Q75: =$AN$7*IF(O75>=40000,O75-40000,0) -> 2179.9403 | R75: =O75+P75+Q75 -> 88178.745 | T75: =IF(J75>=0,J75,0) -> 628 | U75: =IF(AL155>=$BH$48,$BH$48-M75,0) -> 0 | V75: =IF(B75>=$BH$31,0,IF(B75<=35,$BH$4,IF(B75<=45,$BH$5,IF(B75<=50,$BH$6,IF(B75<=55,$BH$7,IF(B75<=60,$BH$8,IF(B75<=65,$BH$9,IF(B75<=70,$BH$10,$BH$11)))))))*$BH$37) -> 0 | W75: =IF(B75<($BH$57+$BH$30),$BH$56*12,0) -> 0 | X75: =IF(B75<=34,$AN$31,IF(B75<=39,$AN$32,IF(B75<=44,$AN$33,IF(B75<=49,$AN$34,IF(B75<=54,$AN$35,IF(B75<=59,$AN$36,IF(B75<=69,$AN$37,0))))))) -> 298 | Y75: =AL155+V75-W75-X75+T75-U75 -> -702539.35 | Z75: =IF(B75<=55,$AL$3,$AN$3)*(IF(Y75>=20000,20000,Y75)) -> -42152.361 | AR75: 55 | AS75: - | AT75: =AU45-AW45 -> -178452.26 | AU75: =IF(AU45-AW45>=0,AT45,AT45-(AW45-AU45)) -> -122445.97 | AV75: =AS45 -> 62168.79 | AW75: =AU75+AT75 -> -300898.23 | AY75: 55
B76: =B75+1 -> 70 | C76: =IF(B76>=67,$BI$55,C75+(1.0244%*C75)) -> 0 | D76: =IF(B76<=20,$AL$14,IF(B76<=30,$AL$15,IF(B76<=40,$AL$16,IF(B76<=50,$AL$17,IF(B76<=60,$AL$18,IF(B76<=65,$AL$19,IF(B76<=70,$AL$20, IF(B76<=73,$AL$21,IF(B76<=75,$AL$22,IF(B76<=78,$AL$23,IF(B76<=80,$AL$24,IF(B76<=83,$AL$25,IF(B76<=85,$AL$26,IF(B76<=90,$AL$27,$AL$28)))))))))))))) -> 1100 | E76: =IF(B76<=20,$AM$14,IF(B76<=30,$AM$15,IF(B76<=40,$AM$16,IF(B76<=50,$AM$17,IF(B76<=60,$AM$18,IF(B76<=65,$AM$19,IF(B76<=70,$AM$20, IF(B76<=73,$AM$21,IF(B76<=75,$AM$22,IF(B76<=78,$AM$23,IF(B76<=80,$AM$24,IF(B76<=83,$AM$25,IF(B76<=85,$AM$26,IF(B76<=90,$AM$27,$AM$28)))))))))))))) -> 600 | F76: 600 | G76: =IF(B76>=$BH$31,0,IF(B76<=35,$BJ$4,IF(B76<=45,$BJ$5,IF(B76<=50,$BJ$6,IF(B76<=55,$BJ$7,IF(B76<=60,$BJ$8,IF(B76<=65,$BJ$9,IF(B76<=70,$BJ$10,$BJ$11)))))))*$BH$37) -> 0 | H76: =K75-C76-D76-E76-F76+G76 -> 73200 | I76: =$AL$8*H76 -> 2928 | J76: =IF(I76+H76-$AL$35>0,I76+H76-$AL$35,0) -> 628 | K76: =H76+I76-J76 -> 75500 | M76: =IF(R75>=BH63,BH63,0) -> 60 | N76: =IF(B76<$BH$31,IF(B77<=35,$BI$4,IF(B77<=45,$BI$5,IF(B77<=50,$BI$6,IF(B77<=55,$BI$7,IF(B77<=60,$BI$8,IF(B77<=65,$BI$9,IF(B77<=70,$BI$10,$BI$11)))))))*$BH$37,0) -> 0 | O76: =R75+N76-M76 -> 88118.745 | P76: =IF(B76<=55,$AL$5,$AN$6)*(IF(O76>=40000,40000,O76)) -> 2400 | Q76: =$AN$7*IF(O76>=40000,O76-40000,0) -> 2405.9373 | R76: =O76+P76+Q76 -> 92924.683 | T76: =IF(J76>=0,J76,0) -> 628 | U76: =IF(AL156>=$BH$48,$BH$48-M76,0) -> 0 | V76: =IF(B76>=$BH$31,0,IF(B76<=35,$BH$4,IF(B76<=45,$BH$5,IF(B76<=50,$BH$6,IF(B76<=55,$BH$7,IF(B76<=60,$BH$8,IF(B76<=65,$BH$9,IF(B76<=70,$BH$10,$BH$11)))))))*$BH$37) -> 0 | W76: =IF(B76<($BH$57+$BH$30),$BH$56*12,0) -> 0 | X76: =IF(B76<=34,$AN$31,IF(B76<=39,$AN$32,IF(B76<=44,$AN$33,IF(B76<=49,$AN$34,IF(B76<=54,$AN$35,IF(B76<=59,$AN$36,IF(B76<=69,$AN$37,0))))))) -> 0 | Y76: =AL156+V76-W76-X76+T76-U76 -> -744063.71 | Z76: =IF(B76<=55,$AL$3,$AN$3)*(IF(Y76>=20000,20000,Y76)) -> -44643.822 | AR76: 65 | AS76: =IF(AR76<=65,12,(AR76-65)*12)*$AT$50 -> 20040 | AT76: =VLOOKUP($AR$76,$B$240:$AK$287,17) -> #REF! | AU76: =VLOOKUP($AR$76,$B$240:$AK$287,26) -> 0 | AV76: =VLOOKUP(AR76,$B$235:$AK$287,10,) -> 66000 | AW76: =SUM(AS76:AU76) -> #REF! | AX76: =$AT$50 -> 1670 | AY76: 65
B77: =B76+1 -> 71 | C77: =IF(B77>=67,$BI$55,C76+(1.0244%*C76)) -> 0 | D77: =IF(B77<=20,$AL$14,IF(B77<=30,$AL$15,IF(B77<=40,$AL$16,IF(B77<=50,$AL$17,IF(B77<=60,$AL$18,IF(B77<=65,$AL$19,IF(B77<=70,$AL$20, IF(B77<=73,$AL$21,IF(B77<=75,$AL$22,IF(B77<=78,$AL$23,IF(B77<=80,$AL$24,IF(B77<=83,$AL$25,IF(B77<=85,$AL$26,IF(B77<=90,$AL$27,$AL$28)))))))))))))) -> 1195 | E77: =IF(B77<=20,$AM$14,IF(B77<=30,$AM$15,IF(B77<=40,$AM$16,IF(B77<=50,$AM$17,IF(B77<=60,$AM$18,IF(B77<=65,$AM$19,IF(B77<=70,$AM$20, IF(B77<=73,$AM$21,IF(B77<=75,$AM$22,IF(B77<=78,$AM$23,IF(B77<=80,$AM$24,IF(B77<=83,$AM$25,IF(B77<=85,$AM$26,IF(B77<=90,$AM$27,$AM$28)))))))))))))) -> 900 | F77: 600 | G77: =IF(B77>=$BH$31,0,IF(B77<=35,$BJ$4,IF(B77<=45,$BJ$5,IF(B77<=50,$BJ$6,IF(B77<=55,$BJ$7,IF(B77<=60,$BJ$8,IF(B77<=65,$BJ$9,IF(B77<=70,$BJ$10,$BJ$11)))))))*$BH$37) -> 0 | H77: =K76-C77-D77-E77-F77+G77 -> 72805 | I77: =$AL$8*H77 -> 2912.2 | J77: =IF(I77+H77-$AL$35>0,I77+H77-$AL$35,0) -> 217.2 | K77: =H77+I77-J77 -> 75500 | M77: =IF(R76>=BH64,BH64,0) -> 90 | N77: =IF(B77<$BH$31,IF(B78<=35,$BI$4,IF(B78<=45,$BI$5,IF(B78<=50,$BI$6,IF(B78<=55,$BI$7,IF(B78<=60,$BI$8,IF(B78<=65,$BI$9,IF(B78<=70,$BI$10,$BI$11)))))))*$BH$37,0) -> 0 | O77: =R76+N77-M77 -> 92834.683 | P77: =IF(B77<=55,$AL$5,$AN$6)*(IF(O77>=40000,40000,O77)) -> 2400 | Q77: =$AN$7*IF(O77>=40000,O77-40000,0) -> 2641.7341 | R77: =O77+P77+Q77 -> 97876.417 | T77: =IF(J77>=0,J77,0) -> 217.2 | U77: =IF(AL157>=$BH$48,$BH$48-M77,0) -> 0 | V77: =IF(B77>=$BH$31,0,IF(B77<=35,$BH$4,IF(B77<=45,$BH$5,IF(B77<=50,$BH$6,IF(B77<=55,$BH$7,IF(B77<=60,$BH$8,IF(B77<=65,$BH$9,IF(B77<=70,$BH$10,$BH$11)))))))*$BH$37) -> 0 | W77: =IF(B77<($BH$57+$BH$30),$BH$56*12,0) -> 0 | X77: =IF(B77<=34,$AN$31,IF(B77<=39,$AN$32,IF(B77<=44,$AN$33,IF(B77<=49,$AN$34,IF(B77<=54,$AN$35,IF(B77<=59,$AN$36,IF(B77<=69,$AN$37,0))))))) -> 0 | Y77: =AL157+V77-W77-X77+T77-U77 -> -788490.33 | Z77: =IF(B77<=55,$AL$3,$AN$3)*(IF(Y77>=20000,20000,Y77)) -> -47309.42 | AR77: 75 | AS77: =IF(AR77<=65,12,(AR77-65)*12)*$AT$50 -> 200400 | AT77: =VLOOKUP($AR$77,$B$240:$AK$287,17) -> #REF! | AU77: =VLOOKUP($AR$77,$B$240:$AK$287,26) -> 0 | AV77: =VLOOKUP(AR77,$B$235:$AK$287,10,) -> 66000 | AW77: =SUM(AS77:AU77) -> #REF! | AX77: =$AT$50 -> 1670 | AY77: 75
B78: =B77+1 -> 72 | C78: =IF(B78>=67,$BI$55,C77+(1.0244%*C77)) -> 0 | D78: =IF(B78<=20,$AL$14,IF(B78<=30,$AL$15,IF(B78<=40,$AL$16,IF(B78<=50,$AL$17,IF(B78<=60,$AL$18,IF(B78<=65,$AL$19,IF(B78<=70,$AL$20, IF(B78<=73,$AL$21,IF(B78<=75,$AL$22,IF(B78<=78,$AL$23,IF(B78<=80,$AL$24,IF(B78<=83,$AL$25,IF(B78<=85,$AL$26,IF(B78<=90,$AL$27,$AL$28)))))))))))))) -> 1195 | E78: =IF(B78<=20,$AM$14,IF(B78<=30,$AM$15,IF(B78<=40,$AM$16,IF(B78<=50,$AM$17,IF(B78<=60,$AM$18,IF(B78<=65,$AM$19,IF(B78<=70,$AM$20, IF(B78<=73,$AM$21,IF(B78<=75,$AM$22,IF(B78<=78,$AM$23,IF(B78<=80,$AM$24,IF(B78<=83,$AM$25,IF(B78<=85,$AM$26,IF(B78<=90,$AM$27,$AM$28)))))))))))))) -> 900 | F78: 600 | G78: =IF(B78>=$BH$31,0,IF(B78<=35,$BJ$4,IF(B78<=45,$BJ$5,IF(B78<=50,$BJ$6,IF(B78<=55,$BJ$7,IF(B78<=60,$BJ$8,IF(B78<=65,$BJ$9,IF(B78<=70,$BJ$10,$BJ$11)))))))*$BH$37) -> 0 | H78: =K77-C78-D78-E78-F78+G78 -> 72805 | I78: =$AL$8*H78 -> 2912.2 | J78: =IF(I78+H78-$AL$35>0,I78+H78-$AL$35,0) -> 217.2 | K78: =H78+I78-J78 -> 75500 | M78: =IF(R77>=BH65,BH65,0) -> 0 | N78: =IF(B78<$BH$31,IF(B79<=35,$BI$4,IF(B79<=45,$BI$5,IF(B79<=50,$BI$6,IF(B79<=55,$BI$7,IF(B79<=60,$BI$8,IF(B79<=65,$BI$9,IF(B79<=70,$BI$10,$BI$11)))))))*$BH$37,0) -> 0 | O78: =R77+N78-M78 -> 97876.417 | P78: =IF(B78<=55,$AL$5,$AN$6)*(IF(O78>=40000,40000,O78)) -> 2400 | Q78: =$AN$7*IF(O78>=40000,O78-40000,0) -> 2893.8208 | R78: =O78+P78+Q78 -> 103170.24 | T78: =IF(J78>=0,J78,0) -> 217.2 | U78: =IF(AL158>=$BH$48,$BH$48-M78,0) -> 0 | V78: =IF(B78>=$BH$31,0,IF(B78<=35,$BH$4,IF(B78<=45,$BH$5,IF(B78<=50,$BH$6,IF(B78<=55,$BH$7,IF(B78<=60,$BH$8,IF(B78<=65,$BH$9,IF(B78<=70,$BH$10,$BH$11)))))))*$BH$37) -> 0 | W78: =IF(B78<($BH$57+$BH$30),$BH$56*12,0) -> 0 | X78: =IF(B78<=34,$AN$31,IF(B78<=39,$AN$32,IF(B78<=44,$AN$33,IF(B78<=49,$AN$34,IF(B78<=54,$AN$35,IF(B78<=59,$AN$36,IF(B78<=69,$AN$37,0))))))) -> 0 | Y78: =AL158+V78-W78-X78+T78-U78 -> -835582.55 | Z78: =IF(B78<=55,$AL$3,$AN$3)*(IF(Y78>=20000,20000,Y78)) -> -50134.953 | AR78: 85 | AS78: =IF(AR78<=65,12,(AR78-65)*12)*$AT$50 -> 400800 | AT78: =VLOOKUP($AR$78,$B$240:$AK$287,17) -> #REF! | AU78: =VLOOKUP($AR$78,$B$240:$AK$287,26) -> 0 | AV78: =VLOOKUP(AR78,$B$235:$AK$287,10,) -> 66000 | AW78: =SUM(AS78:AU78) -> #REF! | AX78: =$AT$50 -> 1670 | AY78: 85
B79: =B78+1 -> 73 | C79: =IF(B79>=67,$BI$55,C78+(1.0244%*C78)) -> 0 | D79: =IF(B79<=20,$AL$14,IF(B79<=30,$AL$15,IF(B79<=40,$AL$16,IF(B79<=50,$AL$17,IF(B79<=60,$AL$18,IF(B79<=65,$AL$19,IF(B79<=70,$AL$20, IF(B79<=73,$AL$21,IF(B79<=75,$AL$22,IF(B79<=78,$AL$23,IF(B79<=80,$AL$24,IF(B79<=83,$AL$25,IF(B79<=85,$AL$26,IF(B79<=90,$AL$27,$AL$28)))))))))))))) -> 1195 | E79: =IF(B79<=20,$AM$14,IF(B79<=30,$AM$15,IF(B79<=40,$AM$16,IF(B79<=50,$AM$17,IF(B79<=60,$AM$18,IF(B79<=65,$AM$19,IF(B79<=70,$AM$20, IF(B79<=73,$AM$21,IF(B79<=75,$AM$22,IF(B79<=78,$AM$23,IF(B79<=80,$AM$24,IF(B79<=83,$AM$25,IF(B79<=85,$AM$26,IF(B79<=90,$AM$27,$AM$28)))))))))))))) -> 900 | F79: 600 | G79: =IF(B79>=$BH$31,0,IF(B79<=35,$BJ$4,IF(B79<=45,$BJ$5,IF(B79<=50,$BJ$6,IF(B79<=55,$BJ$7,IF(B79<=60,$BJ$8,IF(B79<=65,$BJ$9,IF(B79<=70,$BJ$10,$BJ$11)))))))*$BH$37) -> 0 | H79: =K78-C79-D79-E79-F79+G79 -> 72805 | I79: =$AL$8*H79 -> 2912.2 | J79: =IF(I79+H79-$AL$35>0,I79+H79-$AL$35,0) -> 217.2 | K79: =H79+I79-J79 -> 75500 | M79: =IF(R78>=AR43,AR43,0) -> 0 | N79: =IF(B79<$BH$31,IF(B80<=35,$BI$4,IF(B80<=45,$BI$5,IF(B80<=50,$BI$6,IF(B80<=55,$BI$7,IF(B80<=60,$BI$8,IF(B80<=65,$BI$9,IF(B80<=70,$BI$10,$BI$11)))))))*$BH$37,0) -> 0 | O79: =R78+N79-M79 -> 103170.24 | P79: =IF(B79<=55,$AL$5,$AN$6)*(IF(O79>=40000,40000,O79)) -> 2400 | Q79: =$AN$7*IF(O79>=40000,O79-40000,0) -> 3158.5119 | R79: =O79+P79+Q79 -> 108728.75 | T79: =IF(J79>=0,J79,0) -> 217.2 | U79: =IF(AL159>=$BH$48,$BH$48-M79,0) -> 0 | V79: =IF(B79>=$BH$31,0,IF(B79<=35,$BH$4,IF(B79<=45,$BH$5,IF(B79<=50,$BH$6,IF(B79<=55,$BH$7,IF(B79<=60,$BH$8,IF(B79<=65,$BH$9,IF(B79<=70,$BH$10,$BH$11)))))))*$BH$37) -> 0 | W79: =IF(B79<($BH$57+$BH$30),$BH$56*12,0) -> 0 | X79: =IF(B79<=34,$AN$31,IF(B79<=39,$AN$32,IF(B79<=44,$AN$33,IF(B79<=49,$AN$34,IF(B79<=54,$AN$35,IF(B79<=59,$AN$36,IF(B79<=69,$AN$37,0))))))) -> 0 | Y79: =AL159+V79-W79-X79+T79-U79 -> -885500.3 | Z79: =IF(B79<=55,$AL$3,$AN$3)*(IF(Y79>=20000,20000,Y79)) -> -53130.018 | AR79: ='[10]Retirement Dashboard'!E40 -> 90 | AS79: =IF(AR79<=65,12,(AR79-65)*12)*$AT$50 -> 501000 | AT79: =VLOOKUP($AR$79,$B$240:$AK$287,17) -> #REF! | AU79: =VLOOKUP($AR$79,$B$240:$AK$287,26) -> 0 | AV79: =VLOOKUP(AR79,$B$235:$AK$287,10,) -> 66000 | AW79: =SUM(AS79:AU79) -> #REF! | AX79: =$AT$50 -> 1670 | AY79: =BH31 -> 65
B80: =B79+1 -> 74 | C80: =IF(B80>=67,$BI$55,C79+(1.0244%*C79)) -> 0 | D80: =IF(B80<=20,$AL$14,IF(B80<=30,$AL$15,IF(B80<=40,$AL$16,IF(B80<=50,$AL$17,IF(B80<=60,$AL$18,IF(B80<=65,$AL$19,IF(B80<=70,$AL$20, IF(B80<=73,$AL$21,IF(B80<=75,$AL$22,IF(B80<=78,$AL$23,IF(B80<=80,$AL$24,IF(B80<=83,$AL$25,IF(B80<=85,$AL$26,IF(B80<=90,$AL$27,$AL$28)))))))))))))) -> 1320 | E80: =IF(B80<=20,$AM$14,IF(B80<=30,$AM$15,IF(B80<=40,$AM$16,IF(B80<=50,$AM$17,IF(B80<=60,$AM$18,IF(B80<=65,$AM$19,IF(B80<=70,$AM$20, IF(B80<=73,$AM$21,IF(B80<=75,$AM$22,IF(B80<=78,$AM$23,IF(B80<=80,$AM$24,IF(B80<=83,$AM$25,IF(B80<=85,$AM$26,IF(B80<=90,$AM$27,$AM$28)))))))))))))) -> 900 | F80: 600 | G80: =IF(B80>=$BH$31,0,IF(B80<=35,$BJ$4,IF(B80<=45,$BJ$5,IF(B80<=50,$BJ$6,IF(B80<=55,$BJ$7,IF(B80<=60,$BJ$8,IF(B80<=65,$BJ$9,IF(B80<=70,$BJ$10,$BJ$11)))))))*$BH$37) -> 0 | H80: =K79-C80-D80-E80-F80+G80 -> 72680 | I80: =$AL$8*H80 -> 2907.2 | J80: =IF(I80+H80-$AL$35>0,I80+H80-$AL$35,0) -> 87.2 | K80: =H80+I80-J80 -> 75500 | M80: =IF(R79>=AR44,AR44,0) -> 65 | N80: =IF(B80<$BH$31,IF(B81<=35,$BI$4,IF(B81<=45,$BI$5,IF(B81<=50,$BI$6,IF(B81<=55,$BI$7,IF(B81<=60,$BI$8,IF(B81<=65,$BI$9,IF(B81<=70,$BI$10,$BI$11)))))))*$BH$37,0) -> 0 | O80: =R79+N80-M80 -> 108663.75 | P80: =IF(B80<=55,$AL$5,$AN$6)*(IF(O80>=40000,40000,O80)) -> 2400 | Q80: =$AN$7*IF(O80>=40000,O80-40000,0) -> 3433.1875 | R80: =O80+P80+Q80 -> 114496.94 | T80: =IF(J80>=0,J80,0) -> 87.2 | U80: =IF(AL160>=$BH$48,$BH$48-M80,0) -> 0 | V80: =IF(B80>=$BH$31,0,IF(B80<=35,$BH$4,IF(B80<=45,$BH$5,IF(B80<=50,$BH$6,IF(B80<=55,$BH$7,IF(B80<=60,$BH$8,IF(B80<=65,$BH$9,IF(B80<=70,$BH$10,$BH$11)))))))*$BH$37) -> 0 | W80: =IF(B80<($BH$57+$BH$30),$BH$56*12,0) -> 0 | X80: =IF(B80<=34,$AN$31,IF(B80<=39,$AN$32,IF(B80<=44,$AN$33,IF(B80<=49,$AN$34,IF(B80<=54,$AN$35,IF(B80<=59,$AN$36,IF(B80<=69,$AN$37,0))))))) -> 0 | Y80: =AL160+V80-W80-X80+T80-U80 -> -938543.12 | Z80: =IF(B80<=55,$AL$3,$AN$3)*(IF(Y80>=20000,20000,Y80)) -> -56312.587
B81: =B80+1 -> 75 | C81: =IF(B81>=67,$BI$55,C80+(1.0244%*C80)) -> 0 | D81: =IF(B81<=20,$AL$14,IF(B81<=30,$AL$15,IF(B81<=40,$AL$16,IF(B81<=50,$AL$17,IF(B81<=60,$AL$18,IF(B81<=65,$AL$19,IF(B81<=70,$AL$20, IF(B81<=73,$AL$21,IF(B81<=75,$AL$22,IF(B81<=78,$AL$23,IF(B81<=80,$AL$24,IF(B81<=83,$AL$25,IF(B81<=85,$AL$26,IF(B81<=90,$AL$27,$AL$28)))))))))))))) -> 1320 | E81: =IF(B81<=20,$AM$14,IF(B81<=30,$AM$15,IF(B81<=40,$AM$16,IF(B81<=50,$AM$17,IF(B81<=60,$AM$18,IF(B81<=65,$AM$19,IF(B81<=70,$AM$20, IF(B81<=73,$AM$21,IF(B81<=75,$AM$22,IF(B81<=78,$AM$23,IF(B81<=80,$AM$24,IF(B81<=83,$AM$25,IF(B81<=85,$AM$26,IF(B81<=90,$AM$27,$AM$28)))))))))))))) -> 900 | F81: 600 | G81: =IF(B81>=$BH$31,0,IF(B81<=35,$BJ$4,IF(B81<=45,$BJ$5,IF(B81<=50,$BJ$6,IF(B81<=55,$BJ$7,IF(B81<=60,$BJ$8,IF(B81<=65,$BJ$9,IF(B81<=70,$BJ$10,$BJ$11)))))))*$BH$37) -> 0 | H81: =K80-C81-D81-E81-F81+G81 -> 72680 | I81: =$AL$8*H81 -> 2907.2 | J81: =IF(I81+H81-$AL$35>0,I81+H81-$AL$35,0) -> 87.2 | K81: =H81+I81-J81 -> 75500 | M81: =IF(R80>=AR45,AR45,0) -> 55 | N81: =IF(B81<$BH$31,IF(B82<=35,$BI$4,IF(B82<=45,$BI$5,IF(B82<=50,$BI$6,IF(B82<=55,$BI$7,IF(B82<=60,$BI$8,IF(B82<=65,$BI$9,IF(B82<=70,$BI$10,$BI$11)))))))*$BH$37,0) -> 0 | O81: =R80+N81-M81 -> 114441.94 | P81: =IF(B81<=55,$AL$5,$AN$6)*(IF(O81>=40000,40000,O81)) -> 2400 | Q81: =$AN$7*IF(O81>=40000,O81-40000,0) -> 3722.0968 | R81: =O81+P81+Q81 -> 120564.03 | T81: =IF(J81>=0,J81,0) -> 87.2 | U81: =IF(AL161>=$BH$48,$BH$48-M81,0) -> 0 | V81: =IF(B81>=$BH$31,0,IF(B81<=35,$BH$4,IF(B81<=45,$BH$5,IF(B81<=50,$BH$6,IF(B81<=55,$BH$7,IF(B81<=60,$BH$8,IF(B81<=65,$BH$9,IF(B81<=70,$BH$10,$BH$11)))))))*$BH$37) -> 0 | W81: =IF(B81<($BH$57+$BH$30),$BH$56*12,0) -> 0 | X81: =IF(B81<=34,$AN$31,IF(B81<=39,$AN$32,IF(B81<=44,$AN$33,IF(B81<=49,$AN$34,IF(B81<=54,$AN$35,IF(B81<=59,$AN$36,IF(B81<=69,$AN$37,0))))))) -> 0 | Y81: =AL161+V81-W81-X81+T81-U81 -> -994768.51 | Z81: =IF(B81<=55,$AL$3,$AN$3)*(IF(Y81>=20000,20000,Y81)) -> -59686.111
